{"metadata": {"dataVersion": "2", "matchId": "KR_6628843935", "participants": ["JtBO4lP5WxOJSri_h_4YZhSxSfWjPZXd6-78F0Moixfk_q3-K1_RAIhUtcOG5oKvpANOxwOk-WcqaQ", "aCAKhRl3SxNVAOM8LP1djcXXMcxyUjD9LoY5KJ5H1hnuCVF243sxOWxBBNEaHEYr90W-ooerd44U0w", "BnHE60b_adBNnPWTckiOvLOeRC3N4yS8qrCyZT3BDaC6c3SDxtcAhHQMeMUDfz0CwGH1T2Y7SiBY8w", "8PaXxtJeKfLIcIK2fmEHgPUm9GVXHWFZ_sjCi4A-M81MiecsgrAz3W25GKLwkSyw0lKfQcjV2sZmVw", "cdD-OmPAObkR2a2KFRlbF2Xf8a1rUmulugeFEOGzyN7R5lmy8BJOe93qFutGaa5P9O0nmiW3HNEqPw", "efvdQA3l61WwjnLHmOqwxL4sij6807p_4x1z8ANOC_mjf9y3Kr9oFi74PqXw_L8U1asyMhPhyyq9-Q", "LDtz3vBiOf0CTuDzWp0fDq3UhyjUZyvwhvY8bm7_K1mN_tTZoPSe2Mtx95F53eMoCe3HfC42yta93A", "7a1UxGBP5ydRjl5jwK_Ccjs6zWOHw5LP1XGxPxwpf38RKP_29b5xeG3aRTnlg20NCy2UO3555_mc1Q", "3MXueUlNBXkXMuaTmLwXNSt2-Fw8Od77SQ_RLEv1Vuxbj0GyJAxFMRqw6K0D2rO3bpNKBOh9OoPtdg", "NEYzqWWYEIMj7OrevLo8kOfaNc24vI_9yfpWKLpW4Bv78NeR4lnCH1N-GGi599EsAN4PnXNWMI9_PA"]}, "info": {"gameCreation": 1690964305826, "gameDuration": 1587, "gameEndTimestamp": 1690965909125, "gameId": 6628843935, "gameMode": "CLASSIC", "gameName": "teambuilder-match-6628843935", "gameStartTimestamp": 1690964321827, "gameType": "MATCHED_GAME", "gameVersion": "13.15.523.2423", "mapId": 11, "participants": [{"allInPings": 0, "assistMePings": 2, "assists": 2, "baitPings": 0, "baronKills": 0, "basicPings": 0, "bountyLevel": 0, "challenges": {"12AssistStreakCount": 0, "abilityUses": 144, "acesBefore15Minutes": 0, "alliedJungleMonsterKills": 3, "baronTakedowns": 0, "blastConeOppositeOpponentCount": 0, "bountyGold": 600, "buffsStolen": 0, "completeSupportQuestInTime": 0, "controlWardTimeCoverageInRiverOrEnemyHalf": 0.8119790826156539, "controlWardsPlaced": 4, "damagePerMinute": 449.76530550066116, "damageTakenOnTeamPercentage": 0.24871279311045452, "dancedWithRiftHerald": 0, "deathsByEnemyChamps": 5, "dodgeSkillShotsSmallWindow": 11, "doubleAces": 0, "dragonTakedowns": 1, "earliestDragonTakedown": 1168.1867856, "earlyLaningPhaseGoldExpAdvantage": 1, "effectiveHealAndShielding": 0, "elderDragonKillsWithOpposingSoul": 0, "elderDragonMultikills": 0, "enemyChampionImmobilizations": 10, "enemyJungleMonsterKills": 1, "epicMonsterKillsNearEnemyJungler": 0, "epicMonsterKillsWithin30SecondsOfSpawn": 0, "epicMonsterSteals": 0, "epicMonsterStolenWithoutSmite": 0, "firstTurretKilled": 0, "flawlessAces": 0, "fullTeamTakedown": 1, "gameLength": 1587.4567035, "getTakedownsInAllLanesEarlyJungleAsLaner": 0, "goldPerMinute": 381.43139209875153, "hadOpenNexus": 0, "immobilizeAndKillWithAlly": 3, "initialBuffCount": 0, "initialCrabCount": 0, "jungleCsBefore10Minutes": 0, "junglerTakedownsNearDamagedEpicMonster": 0, "kTurretsDestroyedBeforePlatesFall": 0, "kda": 1, "killAfterHiddenWithAlly": 2, "killParticipation": 0.29411764705882354, "killedChampTookFullTeamDamageSurvived": 0, "killingSprees": 0, "killsNearEnemyTurret": 0, "killsOnOtherLanesEarlyJungleAsLaner": 0, "killsOnRecentlyHealedByAramPack": 0, "killsUnderOwnTurret": 0, "killsWithHelpFromEpicMonster": 0, "knockEnemyIntoTeamAndKill": 0, "landSkillShotsEarlyGame": 0, "laneMinionsFirst10Minutes": 83, "laningPhaseGoldExpAdvantage": 0, "legendaryCount": 0, "lostAnInhibitor": 0, "maxCsAdvantageOnLaneOpponent": 33.5, "maxKillDeficit": 0, "maxLevelLeadLaneOpponent": 1, "mejaisFullStackInTime": 0, "moreEnemyJungleThanOpponent": 0, "multiKillOneSpell": 0, "multiTurretRiftHeraldCount": 0, "multikills": 0, "multikillsAfterAggressiveFlash": 0, "mythicItemUsed": 6631, "outerTurretExecutesBefore10Minutes": 0, "outnumberedKills": 1, "outnumberedNexusKill": 0, "perfectDragonSoulsTaken": 0, "perfectGame": 0, "pickKillWithAlly": 3, "playedChampSelectPosition": 1, "poroExplosions": 0, "quickCleanse": 0, "quickFirstTurret": 0, "quickSoloKills": 0, "riftHeraldTakedowns": 0, "saveAllyFromDeath": 0, "scuttleCrabKills": 0, "skillshotsDodged": 55, "skillshotsHit": 0, "snowballsHit": 0, "soloBaronKills": 0, "soloKills": 0, "soloTurretsLategame": 1, "stealthWardsPlaced": 9, "survivedSingleDigitHpCount": 0, "survivedThreeImmobilizesInFight": 0, "takedownOnFirstTurret": 0, "takedowns": 5, "takedownsAfterGainingLevelAdvantage": 0, "takedownsBeforeJungleMinionSpawn": 0, "takedownsFirstXMinutes": 0, "takedownsInAlcove": 0, "takedownsInEnemyFountain": 0, "teamBaronKills": 0, "teamDamagePercentage": 0.2045241971795897, "teamElderDragonKills": 0, "teamRiftHeraldKills": 0, "tookLargeDamageSurvived": 0, "turretPlatesTaken": 4, "turretTakedowns": 1, "turretsTakenWithRiftHerald": 0, "twentyMinionsIn3SecondsCount": 8, "twoWardsOneSweeperCount": 0, "unseenRecalls": 0, "visionScoreAdvantageLaneOpponent": -0.018623828887939453, "visionScorePerMinute": 0.9165173205185654, "wardTakedowns": 1, "wardTakedownsBefore20M": 1, "wardsGuarded": 0}, "champExperience": 11246, "champLevel": 13, "championId": 58, "championName": "Renekton", "championTransform": 0, "commandPings": 2, "consumablesPurchased": 5, "damageDealtToBuildings": 3030, "damageDealtToObjectives": 4577, "damageDealtToTurrets": 3030, "damageSelfMitigated": 19924, "dangerPings": 0, "deaths": 5, "detectorWardsPlaced": 4, "doubleKills": 0, "dragonKills": 0, "eligibleForProgression": true, "enemyMissingPings": 7, "enemyVisionPings": 2, "firstBloodAssist": false, "firstBloodKill": false, "firstTowerAssist": false, "firstTowerKill": false, "gameEndedInEarlySurrender": false, "gameEndedInSurrender": true, "getBackPings": 0, "goldEarned": 10091, "goldSpent": 9450, "holdPings": 0, "individualPosition": "TOP", "inhibitorKills": 0, "inhibitorTakedowns": 0, "inhibitorsLost": 1, "item0": 3071, "item1": 2031, "item2": 6631, "item3": 3111, "item4": 0, "item5": 3082, "item6": 3340, "itemsPurchased": 18, "killingSprees": 1, "kills": 3, "lane": "MIDDLE", "largestCriticalStrike": 0, "largestKillingSpree": 2, "largestMultiKill": 1, "longestTimeSpentLiving": 604, "magicDamageDealt": 3715, "magicDamageDealtToChampions": 2201, "magicDamageTaken": 15773, "needVisionPings": 0, "neutralMinionsKilled": 7, "nexusKills": 0, "nexusLost": 0, "nexusTakedowns": 0, "objectivesStolen": 0, "objectivesStolenAssists": 0, "onMyWayPings": 1, "participantId": 1, "pentaKills": 0, "perks": {"statPerks": {"defense": 5003, "flex": 5008, "offense": 5008}, "styles": [{"description": "primaryStyle", "selections": [{"perk": 8010, "var1": 480, "var2": 0, "var3": 0}, {"perk": 9111, "var1": 736, "var2": 100, "var3": 0}, {"perk": 9104, "var1": 19, "var2": 40, "var3": 0}, {"perk": 8299, "var1": 561, "var2": 0, "var3": 0}], "style": 8000}, {"description": "subStyle", "selections": [{"perk": 8444, "var1": 1054, "var2": 0, "var3": 0}, {"perk": 8242, "var1": 71, "var2": 0, "var3": 0}], "style": 8400}]}, "physicalDamageDealt": 98813, "physicalDamageDealtToChampions": 9638, "physicalDamageTaken": 10967, "placement": 0, "playerAugment1": 0, "playerAugment2": 0, "playerAugment3": 0, "playerAugment4": 0, "playerSubteamId": 0, "profileIcon": 539, "pushPings": 0, "puuid": "JtBO4lP5WxOJSri_h_4YZhSxSfWjPZXd6-78F0Moixfk_q3-K1_RAIhUtcOG5oKvpANOxwOk-WcqaQ", "quadraKills": 0, "riotIdName": "", "riotIdTagline": "", "role": "DUO", "sightWardsBoughtInGame": 0, "spell1Casts": 55, "spell2Casts": 21, "spell3Casts": 61, "spell4Casts": 7, "subteamPlacement": 0, "summoner1Casts": 3, "summoner1Id": 12, "summoner2Casts": 2, "summoner2Id": 4, "summonerId": "rRHGEEKN0E4Cj1b2t3U1FVm1CRfwYKz-j_iccxuVFDOPeA", "summonerLevel": 523, "summonerName": "Twitch \uacf0\ud321\ud638", "teamEarlySurrendered": false, "teamId": 100, "teamPosition": "TOP", "timeCCingOthers": 13, "timePlayed": 1587, "totalAllyJungleMinionsKilled": 6, "totalDamageDealt": 105968, "totalDamageDealtToChampions": 11899, "totalDamageShieldedOnTeammates": 0, "totalDamageTaken": 27081, "totalEnemyJungleMinionsKilled": 0, "totalHeal": 4236, "totalHealsOnTeammates": 0, "totalMinionsKilled": 169, "totalTimeCCDealt": 109, "totalTimeSpentDead": 139, "totalUnitsHealed": 1, "tripleKills": 0, "trueDamageDealt": 3440, "trueDamageDealtToChampions": 60, "trueDamageTaken": 340, "turretKills": 1, "turretTakedowns": 1, "turretsLost": 7, "unrealKills": 0, "visionClearedPings": 0, "visionScore": 24, "visionWardsBoughtInGame": 4, "wardsKilled": 1, "wardsPlaced": 13, "win": false}, {"allInPings": 3, "assistMePings": 1, "assists": 14, "baitPings": 0, "baronKills": 0, "basicPings": 0, "bountyLevel": 0, "challenges": {"12AssistStreakCount": 1, "abilityUses": 201, "acesBefore15Minutes": 0, "alliedJungleMonsterKills": 58, "baronTakedowns": 0, "blastConeOppositeOpponentCount": 0, "bountyGold": 0, "buffsStolen": 1, "completeSupportQuestInTime": 0, "controlWardTimeCoverageInRiverOrEnemyHalf": 0.6478249016383331, "controlWardsPlaced": 11, "damagePerMinute": 354.4041909006623, "damageTakenOnTeamPercentage": 0.25924804102753773, "dancedWithRiftHerald": 0, "deathsByEnemyChamps": 6, "dodgeSkillShotsSmallWindow": 26, "doubleAces": 0, "dragonTakedowns": 1, "earliestDragonTakedown": 1168.1867856, "earlyLaningPhaseGoldExpAdvantage": 0, "effectiveHealAndShielding": 2971.431396484375, "elderDragonKillsWithOpposingSoul": 0, "elderDragonMultikills": 0, "enemyChampionImmobilizations": 25, "enemyJungleMonsterKills": 1, "epicMonsterKillsNearEnemyJungler": 0, "epicMonsterKillsWithin30SecondsOfSpawn": 1, "epicMonsterSteals": 0, "epicMonsterStolenWithoutSmite": 0, "firstTurretKilled": 0, "flawlessAces": 0, "fullTeamTakedown": 1, "gameLength": 1587.4567035, "goldPerMinute": 296.1089063550482, "hadOpenNexus": 0, "immobilizeAndKillWithAlly": 11, "initialBuffCount": 2, "initialCrabCount": 1, "jungleCsBefore10Minutes": 45.000000059604645, "junglerKillsEarlyJungle": 0, "junglerTakedownsNearDamagedEpicMonster": 0, "kTurretsDestroyedBeforePlatesFall": 0, "kda": 2.3333333333333335, "killAfterHiddenWithAlly": 3, "killParticipation": 0.8235294117647058, "killedChampTookFullTeamDamageSurvived": 0, "killingSprees": 0, "killsNearEnemyTurret": 0, "killsOnLanersEarlyJungleAsJungler": 0, "killsOnRecentlyHealedByAramPack": 0, "killsUnderOwnTurret": 0, "killsWithHelpFromEpicMonster": 0, "knockEnemyIntoTeamAndKill": 0, "landSkillShotsEarlyGame": 0, "laneMinionsFirst10Minutes": 2, "laningPhaseGoldExpAdvantage": 0, "legendaryCount": 0, "lostAnInhibitor": 0, "maxCsAdvantageOnLaneOpponent": 4.000000029802322, "maxKillDeficit": 0, "maxLevelLeadLaneOpponent": 1, "mejaisFullStackInTime": 0, "moreEnemyJungleThanOpponent": -48.000000059604645, "multiKillOneSpell": 0, "multiTurretRiftHeraldCount": 0, "multikills": 0, "multikillsAfterAggressiveFlash": 0, "mythicItemUsed": 6667, "outerTurretExecutesBefore10Minutes": 0, "outnumberedKills": 0, "outnumberedNexusKill": 0, "perfectDragonSoulsTaken": 0, "perfectGame": 0, "pickKillWithAlly": 12, "playedChampSelectPosition": 1, "poroExplosions": 0, "quickCleanse": 0, "quickFirstTurret": 0, "quickSoloKills": 0, "riftHeraldTakedowns": 0, "saveAllyFromDeath": 28, "scuttleCrabKills": 3, "skillshotsDodged": 133, "skillshotsHit": 4, "snowballsHit": 0, "soloBaronKills": 0, "soloKills": 0, "stealthWardsPlaced": 1, "survivedSingleDigitHpCount": 0, "survivedThreeImmobilizesInFight": 2, "takedownOnFirstTurret": 0, "takedowns": 14, "takedownsAfterGainingLevelAdvantage": 0, "takedownsBeforeJungleMinionSpawn": 0, "takedownsFirstXMinutes": 7, "takedownsInAlcove": 0, "takedownsInEnemyFountain": 0, "teamBaronKills": 0, "teamDamagePercentage": 0.16116012447948463, "teamElderDragonKills": 0, "teamRiftHeraldKills": 0, "tookLargeDamageSurvived": 0, "turretPlatesTaken": 0, "turretTakedowns": 0, "turretsTakenWithRiftHerald": 0, "twentyMinionsIn3SecondsCount": 0, "twoWardsOneSweeperCount": 1, "unseenRecalls": 0, "visionScoreAdvantageLaneOpponent": -0.4889082908630371, "visionScorePerMinute": 1.3538260532031408, "wardTakedowns": 7, "wardTakedownsBefore20M": 4, "wardsGuarded": 1}, "champExperience": 10123, "champLevel": 13, "championId": 113, "championName": "Sejuani", "championTransform": 0, "commandPings": 7, "consumablesPurchased": 14, "damageDealtToBuildings": 0, "damageDealtToObjectives": 6638, "damageDealtToTurrets": 0, "damageSelfMitigated": 35091, "dangerPings": 0, "deaths": 6, "detectorWardsPlaced": 12, "doubleKills": 0, "dragonKills": 1, "eligibleForProgression": true, "enemyMissingPings": 4, "enemyVisionPings": 12, "firstBloodAssist": true, "firstBloodKill": false, "firstTowerAssist": false, "firstTowerKill": false, "gameEndedInEarlySurrender": false, "gameEndedInSurrender": true, "getBackPings": 20, "goldEarned": 7834, "goldSpent": 7675, "holdPings": 3, "individualPosition": "JUNGLE", "inhibitorKills": 0, "inhibitorTakedowns": 0, "inhibitorsLost": 1, "item0": 6667, "item1": 1011, "item2": 3111, "item3": 3076, "item4": 6660, "item5": 2055, "item6": 3364, "itemsPurchased": 31, "killingSprees": 0, "kills": 0, "lane": "JUNGLE", "largestCriticalStrike": 0, "largestKillingSpree": 0, "largestMultiKill": 0, "longestTimeSpentLiving": 719, "magicDamageDealt": 31802, "magicDamageDealtToChampions": 3382, "magicDamageTaken": 5686, "needVisionPings": 0, "neutralMinionsKilled": 111, "nexusKills": 0, "nexusLost": 0, "nexusTakedowns": 0, "objectivesStolen": 0, "objectivesStolenAssists": 0, "onMyWayPings": 9, "participantId": 2, "pentaKills": 0, "perks": {"statPerks": {"defense": 5002, "flex": 5008, "offense": 5005}, "styles": [{"description": "primaryStyle", "selections": [{"perk": 8439, "var1": 272, "var2": 570, "var3": 0}, {"perk": 8463, "var1": 2607, "var2": 0, "var3": 0}, {"perk": 8429, "var1": 54, "var2": 12, "var3": 12}, {"perk": 8451, "var1": 175, "var2": 0, "var3": 0}], "style": 8400}, {"description": "subStyle", "selections": [{"perk": 8304, "var1": 9, "var2": 0, "var3": 0}, {"perk": 8347, "var1": 0, "var2": 0, "var3": 0}], "style": 8300}]}, "physicalDamageDealt": 66547, "physicalDamageDealtToChampions": 5664, "physicalDamageTaken": 22024, "placement": 0, "playerAugment1": 0, "playerAugment2": 0, "playerAugment3": 0, "playerAugment4": 0, "playerSubteamId": 0, "profileIcon": 5919, "pushPings": 0, "puuid": "aCAKhRl3SxNVAOM8LP1djcXXMcxyUjD9LoY5KJ5H1hnuCVF243sxOWxBBNEaHEYr90W-ooerd44U0w", "quadraKills": 0, "riotIdName": "", "riotIdTagline": "", "role": "NONE", "sightWardsBoughtInGame": 0, "spell1Casts": 31, "spell2Casts": 90, "spell3Casts": 72, "spell4Casts": 8, "subteamPlacement": 0, "summoner1Casts": 13, "summoner1Id": 11, "summoner2Casts": 2, "summoner2Id": 4, "summonerId": "iOwgzspvOwkWeJyhd7vsTd8XjoVwY9TuxiwJOSxyWyGL1NU", "summonerLevel": 876, "summonerName": "DEL3076142849", "teamEarlySurrendered": false, "teamId": 100, "teamPosition": "JUNGLE", "timeCCingOthers": 22, "timePlayed": 1587, "totalAllyJungleMinionsKilled": 85, "totalDamageDealt": 129560, "totalDamageDealtToChampions": 9376, "totalDamageShieldedOnTeammates": 0, "totalDamageTaken": 28229, "totalEnemyJungleMinionsKilled": 4, "totalHeal": 12402, "totalHealsOnTeammates": 2971, "totalMinionsKilled": 12, "totalTimeCCDealt": 271, "totalTimeSpentDead": 85, "totalUnitsHealed": 5, "tripleKills": 0, "trueDamageDealt": 31211, "trueDamageDealtToChampions": 330, "trueDamageTaken": 518, "turretKills": 0, "turretTakedowns": 0, "turretsLost": 7, "unrealKills": 0, "visionClearedPings": 0, "visionScore": 35, "visionWardsBoughtInGame": 13, "wardsKilled": 7, "wardsPlaced": 13, "win": false}, {"allInPings": 0, "assistMePings": 2, "assists": 11, "baitPings": 0, "baronKills": 0, "basicPings": 0, "bountyLevel": 0, "challenges": {"12AssistStreakCount": 0, "abilityUses": 113, "acesBefore15Minutes": 0, "alliedJungleMonsterKills": 0, "baronTakedowns": 0, "blastConeOppositeOpponentCount": 0, "bountyGold": 0, "buffsStolen": 0, "completeSupportQuestInTime": 0, "controlWardsPlaced": 1, "damagePerMinute": 547.0157924963842, "damageTakenOnTeamPercentage": 0.19843099246159443, "dancedWithRiftHerald": 0, "deathsByEnemyChamps": 6, "dodgeSkillShotsSmallWindow": 18, "doubleAces": 0, "dragonTakedowns": 0, "earlyLaningPhaseGoldExpAdvantage": 0, "effectiveHealAndShielding": 0, "elderDragonKillsWithOpposingSoul": 0, "elderDragonMultikills": 0, "enemyChampionImmobilizations": 1, "enemyJungleMonsterKills": 0, "epicMonsterKillsNearEnemyJungler": 0, "epicMonsterKillsWithin30SecondsOfSpawn": 0, "epicMonsterSteals": 0, "epicMonsterStolenWithoutSmite": 0, "firstTurretKilled": 0, "flawlessAces": 0, "fullTeamTakedown": 1, "gameLength": 1587.4567035, "getTakedownsInAllLanesEarlyJungleAsLaner": 0, "goldPerMinute": 351.349703066878, "hadOpenNexus": 0, "immobilizeAndKillWithAlly": 0, "initialBuffCount": 0, "initialCrabCount": 0, "jungleCsBefore10Minutes": 0, "junglerTakedownsNearDamagedEpicMonster": 0, "kTurretsDestroyedBeforePlatesFall": 0, "kda": 2.5, "killAfterHiddenWithAlly": 3, "killParticipation": 0.8823529411764706, "killedChampTookFullTeamDamageSurvived": 0, "killingSprees": 0, "killsNearEnemyTurret": 2, "killsOnOtherLanesEarlyJungleAsLaner": 0, "killsOnRecentlyHealedByAramPack": 0, "killsUnderOwnTurret": 0, "killsWithHelpFromEpicMonster": 0, "knockEnemyIntoTeamAndKill": 0, "landSkillShotsEarlyGame": 0, "laneMinionsFirst10Minutes": 59, "laningPhaseGoldExpAdvantage": 0, "legendaryCount": 0, "lostAnInhibitor": 0, "maxCsAdvantageOnLaneOpponent": 29, "maxKillDeficit": 0, "maxLevelLeadLaneOpponent": 1, "mejaisFullStackInTime": 0, "moreEnemyJungleThanOpponent": 0, "multiKillOneSpell": 0, "multiTurretRiftHeraldCount": 0, "multikills": 0, "multikillsAfterAggressiveFlash": 0, "outerTurretExecutesBefore10Minutes": 0, "outnumberedKills": 0, "outnumberedNexusKill": 0, "perfectDragonSoulsTaken": 0, "perfectGame": 0, "pickKillWithAlly": 13, "playedChampSelectPosition": 1, "poroExplosions": 0, "quickCleanse": 0, "quickFirstTurret": 0, "quickSoloKills": 0, "riftHeraldTakedowns": 0, "saveAllyFromDeath": 0, "scuttleCrabKills": 1, "skillshotsDodged": 96, "skillshotsHit": 0, "snowballsHit": 0, "soloBaronKills": 0, "soloKills": 0, "stealthWardsPlaced": 2, "survivedSingleDigitHpCount": 1, "survivedThreeImmobilizesInFight": 2, "takedownOnFirstTurret": 0, "takedowns": 15, "takedownsAfterGainingLevelAdvantage": 0, "takedownsBeforeJungleMinionSpawn": 0, "takedownsFirstXMinutes": 9, "takedownsInAlcove": 0, "takedownsInEnemyFountain": 0, "teamBaronKills": 0, "teamDamagePercentage": 0.24874743435432797, "teamElderDragonKills": 0, "teamRiftHeraldKills": 0, "tookLargeDamageSurvived": 0, "turretPlatesTaken": 0, "turretTakedowns": 0, "turretsTakenWithRiftHerald": 0, "twentyMinionsIn3SecondsCount": 7, "twoWardsOneSweeperCount": 0, "unseenRecalls": 0, "visionScoreAdvantageLaneOpponent": -0.18510222434997559, "visionScorePerMinute": 0.8979454499659564, "wardTakedowns": 10, "wardTakedownsBefore20M": 8, "wardsGuarded": 0}, "champExperience": 10771, "champLevel": 13, "championId": 55, "championName": "Katarina", "championTransform": 0, "commandPings": 3, "consumablesPurchased": 1, "damageDealtToBuildings": 0, "damageDealtToObjectives": 1755, "damageDealtToTurrets": 0, "damageSelfMitigated": 10304, "dangerPings": 0, "deaths": 6, "detectorWardsPlaced": 1, "doubleKills": 0, "dragonKills": 0, "eligibleForProgression": true, "enemyMissingPings": 3, "enemyVisionPings": 21, "firstBloodAssist": false, "firstBloodKill": true, "firstTowerAssist": false, "firstTowerKill": false, "gameEndedInEarlySurrender": false, "gameEndedInSurrender": true, "getBackPings": 2, "goldEarned": 9295, "goldSpent": 9125, "holdPings": 0, "individualPosition": "MIDDLE", "inhibitorKills": 0, "inhibitorTakedowns": 0, "inhibitorsLost": 1, "item0": 3152, "item1": 3145, "item2": 0, "item3": 1082, "item4": 3115, "item5": 3020, "item6": 3364, "itemsPurchased": 20, "killingSprees": 1, "kills": 4, "lane": "MIDDLE", "largestCriticalStrike": 0, "largestKillingSpree": 2, "largestMultiKill": 1, "longestTimeSpentLiving": 597, "magicDamageDealt": 85946, "magicDamageDealtToChampions": 13515, "magicDamageTaken": 5780, "needVisionPings": 0, "neutralMinionsKilled": 4, "nexusKills": 0, "nexusLost": 0, "nexusTakedowns": 0, "objectivesStolen": 0, "objectivesStolenAssists": 0, "onMyWayPings": 25, "participantId": 3, "pentaKills": 0, "perks": {"statPerks": {"defense": 5003, "flex": 5008, "offense": 5008}, "styles": [{"description": "primaryStyle", "selections": [{"perk": 8010, "var1": 504, "var2": 0, "var3": 0}, {"perk": 9111, "var1": 1033, "var2": 300, "var3": 0}, {"perk": 9105, "var1": 13, "var2": 20, "var3": 0}, {"perk": 8014, "var1": 283, "var2": 0, "var3": 0}], "style": 8000}, {"description": "subStyle", "selections": [{"perk": 8143, "var1": 831, "var2": 0, "var3": 0}, {"perk": 8105, "var1": 13, "var2": 5, "var3": 0}], "style": 8100}]}, "physicalDamageDealt": 8062, "physicalDamageDealtToChampions": 957, "physicalDamageTaken": 14487, "placement": 0, "playerAugment1": 0, "playerAugment2": 0, "playerAugment3": 0, "playerAugment4": 0, "playerSubteamId": 0, "profileIcon": 3838, "pushPings": 0, "puuid": "BnHE60b_adBNnPWTckiOvLOeRC3N4yS8qrCyZT3BDaC6c3SDxtcAhHQMeMUDfz0CwGH1T2Y7SiBY8w", "quadraKills": 0, "riotIdName": "", "riotIdTagline": "", "role": "DUO", "sightWardsBoughtInGame": 0, "spell1Casts": 62, "spell2Casts": 41, "spell3Casts": 0, "spell4Casts": 10, "subteamPlacement": 0, "summoner1Casts": 3, "summoner1Id": 12, "summoner2Casts": 3, "summoner2Id": 4, "summonerId": "YXR9v0AM3v7OJGy4USf8ed0A1nMfCQIPRRoaiMYiJT00fEc", "summonerLevel": 868, "summonerName": "\uce74\ud0c0\ud615", "teamEarlySurrendered": false, "teamId": 100, "teamPosition": "MIDDLE", "timeCCingOthers": 0, "timePlayed": 1587, "totalAllyJungleMinionsKilled": 0, "totalDamageDealt": 95705, "totalDamageDealtToChampions": 14472, "totalDamageShieldedOnTeammates": 0, "totalDamageTaken": 21606, "totalEnemyJungleMinionsKilled": 0, "totalHeal": 4267, "totalHealsOnTeammates": 0, "totalMinionsKilled": 160, "totalTimeCCDealt": 13, "totalTimeSpentDead": 133, "totalUnitsHealed": 1, "tripleKills": 0, "trueDamageDealt": 1695, "trueDamageDealtToChampions": 0, "trueDamageTaken": 1338, "turretKills": 0, "turretTakedowns": 0, "turretsLost": 7, "unrealKills": 0, "visionClearedPings": 0, "visionScore": 23, "visionWardsBoughtInGame": 1, "wardsKilled": 10, "wardsPlaced": 3, "win": false}, {"allInPings": 0, "assistMePings": 8, "assists": 4, "baitPings": 0, "baronKills": 0, "basicPings": 0, "bountyLevel": 0, "challenges": {"12AssistStreakCount": 0, "abilityUses": 201, "acesBefore15Minutes": 0, "alliedJungleMonsterKills": 12, "baronTakedowns": 0, "blastConeOppositeOpponentCount": 0, "bountyGold": 750, "buffsStolen": 0, "completeSupportQuestInTime": 0, "controlWardTimeCoverageInRiverOrEnemyHalf": 0.2727442595728093, "controlWardsPlaced": 1, "damagePerMinute": 643.1777532491928, "damageTakenOnTeamPercentage": 0.12223660815201061, "dancedWithRiftHerald": 0, "deathsByEnemyChamps": 6, "dodgeSkillShotsSmallWindow": 9, "doubleAces": 0, "dragonTakedowns": 1, "earliestDragonTakedown": 1168.1867856, "earlyLaningPhaseGoldExpAdvantage": 0, "effectiveHealAndShielding": 0, "elderDragonKillsWithOpposingSoul": 0, "elderDragonMultikills": 0, "enemyChampionImmobilizations": 5, "enemyJungleMonsterKills": 0, "epicMonsterKillsNearEnemyJungler": 0, "epicMonsterKillsWithin30SecondsOfSpawn": 0, "epicMonsterSteals": 0, "epicMonsterStolenWithoutSmite": 0, "firstTurretKilled": 0, "flawlessAces": 0, "fullTeamTakedown": 1, "gameLength": 1587.4567035, "getTakedownsInAllLanesEarlyJungleAsLaner": 0, "goldPerMinute": 470.47786597318054, "hadOpenNexus": 0, "immobilizeAndKillWithAlly": 1, "initialBuffCount": 0, "initialCrabCount": 0, "jungleCsBefore10Minutes": 0, "junglerTakedownsNearDamagedEpicMonster": 0, "kTurretsDestroyedBeforePlatesFall": 0, "kda": 2.1666666666666665, "killAfterHiddenWithAlly": 4, "killParticipation": 0.7647058823529411, "killedChampTookFullTeamDamageSurvived": 0, "killingSprees": 0, "killsNearEnemyTurret": 3, "killsOnOtherLanesEarlyJungleAsLaner": 1, "killsOnRecentlyHealedByAramPack": 0, "killsUnderOwnTurret": 1, "killsWithHelpFromEpicMonster": 0, "knockEnemyIntoTeamAndKill": 0, "landSkillShotsEarlyGame": 1, "laneMinionsFirst10Minutes": 47, "laningPhaseGoldExpAdvantage": 0, "legendaryCount": 0, "lostAnInhibitor": 0, "maxCsAdvantageOnLaneOpponent": 7, "maxKillDeficit": 0, "maxLevelLeadLaneOpponent": 1, "mejaisFullStackInTime": 0, "moreEnemyJungleThanOpponent": 0, "multiKillOneSpell": 0, "multiTurretRiftHeraldCount": 0, "multikills": 3, "multikillsAfterAggressiveFlash": 0, "mythicItemUsed": 3031, "outerTurretExecutesBefore10Minutes": 0, "outnumberedKills": 1, "outnumberedNexusKill": 0, "perfectDragonSoulsTaken": 0, "perfectGame": 0, "pickKillWithAlly": 11, "playedChampSelectPosition": 1, "poroExplosions": 0, "quickCleanse": 0, "quickFirstTurret": 0, "quickSoloKills": 0, "riftHeraldTakedowns": 0, "saveAllyFromDeath": 0, "scuttleCrabKills": 0, "skillshotsDodged": 48, "skillshotsHit": 15, "snowballsHit": 0, "soloBaronKills": 0, "soloKills": 0, "stealthWardsPlaced": 6, "survivedSingleDigitHpCount": 0, "survivedThreeImmobilizesInFight": 0, "takedownOnFirstTurret": 0, "takedowns": 13, "takedownsAfterGainingLevelAdvantage": 0, "takedownsBeforeJungleMinionSpawn": 0, "takedownsFirstXMinutes": 6, "takedownsInAlcove": 0, "takedownsInEnemyFountain": 0, "teamBaronKills": 0, "teamDamagePercentage": 0.29247568013418057, "teamElderDragonKills": 0, "teamRiftHeraldKills": 0, "tookLargeDamageSurvived": 0, "turretPlatesTaken": 1, "turretTakedowns": 0, "turretsTakenWithRiftHerald": 0, "twentyMinionsIn3SecondsCount": 9, "twoWardsOneSweeperCount": 0, "unseenRecalls": 0, "visionScoreAdvantageLaneOpponent": 0.06320071220397949, "visionScorePerMinute": 0.7120464455156758, "wardTakedowns": 4, "wardTakedownsBefore20M": 3, "wardsGuarded": 0}, "champExperience": 10100, "champLevel": 13, "championId": 222, "championName": "Jinx", "championTransform": 0, "commandPings": 26, "consumablesPurchased": 3, "damageDealtToBuildings": 1374, "damageDealtToObjectives": 7822, "damageDealtToTurrets": 1374, "damageSelfMitigated": 6301, "dangerPings": 0, "deaths": 6, "detectorWardsPlaced": 1, "doubleKills": 3, "dragonKills": 0, "eligibleForProgression": true, "enemyMissingPings": 8, "enemyVisionPings": 2, "firstBloodAssist": false, "firstBloodKill": false, "firstTowerAssist": false, "firstTowerKill": false, "gameEndedInEarlySurrender": false, "gameEndedInSurrender": true, "getBackPings": 8, "goldEarned": 12447, "goldSpent": 12575, "holdPings": 0, "individualPosition": "BOTTOM", "inhibitorKills": 0, "inhibitorTakedowns": 0, "inhibitorsLost": 1, "item0": 3006, "item1": 1018, "item2": 1053, "item3": 3031, "item4": 6672, "item5": 3094, "item6": 3363, "itemsPurchased": 24, "killingSprees": 4, "kills": 9, "lane": "BOTTOM", "largestCriticalStrike": 678, "largestKillingSpree": 2, "largestMultiKill": 2, "longestTimeSpentLiving": 386, "magicDamageDealt": 1886, "magicDamageDealtToChampions": 394, "magicDamageTaken": 3627, "needVisionPings": 0, "neutralMinionsKilled": 4, "nexusKills": 0, "nexusLost": 0, "nexusTakedowns": 0, "objectivesStolen": 0, "objectivesStolenAssists": 0, "onMyWayPings": 24, "participantId": 4, "pentaKills": 0, "perks": {"statPerks": {"defense": 5002, "flex": 5008, "offense": 5005}, "styles": [{"description": "primaryStyle", "selections": [{"perk": 8008, "var1": 17, "var2": 2, "var3": 0}, {"perk": 8009, "var1": 1386, "var2": 0, "var3": 0}, {"perk": 9103, "var1": 19, "var2": 20, "var3": 0}, {"perk": 8014, "var1": 400, "var2": 0, "var3": 0}], "style": 8000}, {"description": "subStyle", "selections": [{"perk": 8233, "var1": 18, "var2": 0, "var3": 0}, {"perk": 8236, "var1": 14, "var2": 0, "var3": 0}], "style": 8200}]}, "physicalDamageDealt": 152557, "physicalDamageDealtToChampions": 16587, "physicalDamageTaken": 9279, "placement": 0, "playerAugment1": 0, "playerAugment2": 0, "playerAugment3": 0, "playerAugment4": 0, "playerSubteamId": 0, "profileIcon": 5847, "pushPings": 4, "puuid": "8PaXxtJeKfLIcIK2fmEHgPUm9GVXHWFZ_sjCi4A-M81MiecsgrAz3W25GKLwkSyw0lKfQcjV2sZmVw", "quadraKills": 0, "riotIdName": "", "riotIdTagline": "", "role": "CARRY", "sightWardsBoughtInGame": 0, "spell1Casts": 142, "spell2Casts": 38, "spell3Casts": 14, "spell4Casts": 7, "subteamPlacement": 0, "summoner1Casts": 2, "summoner1Id": 1, "summoner2Casts": 3, "summoner2Id": 4, "summonerId": "0xOvv5kF4F1GMNrAD_p1MMBFtcTyWLzH_VEcKSUmt7PmPhgpzVL1ATMSrg", "summonerLevel": 86, "summonerName": "xingka bi", "teamEarlySurrendered": false, "teamId": 100, "teamPosition": "BOTTOM", "timeCCingOthers": 8, "timePlayed": 1587, "totalAllyJungleMinionsKilled": 4, "totalDamageDealt": 154760, "totalDamageDealtToChampions": 17016, "totalDamageShieldedOnTeammates": 0, "totalDamageTaken": 13310, "totalEnemyJungleMinionsKilled": 0, "totalHeal": 2036, "totalHealsOnTeammates": 0, "totalMinionsKilled": 208, "totalTimeCCDealt": 46, "totalTimeSpentDead": 110, "totalUnitsHealed": 1, "tripleKills": 0, "trueDamageDealt": 316, "trueDamageDealtToChampions": 35, "trueDamageTaken": 403, "turretKills": 0, "turretTakedowns": 0, "turretsLost": 7, "unrealKills": 0, "visionClearedPings": 0, "visionScore": 18, "visionWardsBoughtInGame": 1, "wardsKilled": 4, "wardsPlaced": 9, "win": false}, {"allInPings": 0, "assistMePings": 0, "assists": 10, "baitPings": 0, "baronKills": 0, "basicPings": 0, "bountyLevel": 0, "challenges": {"12AssistStreakCount": 0, "abilityUses": 92, "acesBefore15Minutes": 0, "alliedJungleMonsterKills": 0, "baronTakedowns": 0, "blastConeOppositeOpponentCount": 0, "bountyGold": 0, "buffsStolen": 0, "completeSupportQuestInTime": 1, "controlWardTimeCoverageInRiverOrEnemyHalf": 0.6121785307009477, "controlWardsPlaced": 8, "damagePerMinute": 204.71810181050083, "damageTakenOnTeamPercentage": 0.17137156524840272, "dancedWithRiftHerald": 0, "deathsByEnemyChamps": 8, "dodgeSkillShotsSmallWindow": 28, "doubleAces": 0, "dragonTakedowns": 1, "earliestDragonTakedown": 1168.1867856, "earlyLaningPhaseGoldExpAdvantage": 0, "effectiveHealAndShielding": 0, "elderDragonKillsWithOpposingSoul": 0, "elderDragonMultikills": 0, "enemyChampionImmobilizations": 71, "enemyJungleMonsterKills": 0, "epicMonsterKillsNearEnemyJungler": 0, "epicMonsterKillsWithin30SecondsOfSpawn": 0, "epicMonsterSteals": 0, "epicMonsterStolenWithoutSmite": 0, "fasterSupportQuestCompletion": 1, "firstTurretKilled": 0, "flawlessAces": 0, "fullTeamTakedown": 1, "gameLength": 1587.4567035, "getTakedownsInAllLanesEarlyJungleAsLaner": 0, "goldPerMinute": 230.18000441208568, "hadOpenNexus": 0, "highestCrowdControlScore": 1, "immobilizeAndKillWithAlly": 9, "initialBuffCount": 0, "initialCrabCount": 0, "jungleCsBefore10Minutes": 0, "junglerTakedownsNearDamagedEpicMonster": 0, "kTurretsDestroyedBeforePlatesFall": 0, "kda": 1.375, "killAfterHiddenWithAlly": 4, "killParticipation": 0.6470588235294118, "killedChampTookFullTeamDamageSurvived": 0, "killingSprees": 0, "killsNearEnemyTurret": 0, "killsOnOtherLanesEarlyJungleAsLaner": 0, "killsOnRecentlyHealedByAramPack": 0, "killsUnderOwnTurret": 1, "killsWithHelpFromEpicMonster": 0, "knockEnemyIntoTeamAndKill": 5, "landSkillShotsEarlyGame": 3, "laneMinionsFirst10Minutes": 16, "laningPhaseGoldExpAdvantage": 0, "legendaryCount": 0, "lostAnInhibitor": 0, "maxCsAdvantageOnLaneOpponent": 7, "maxKillDeficit": 0, "maxLevelLeadLaneOpponent": 2, "mejaisFullStackInTime": 0, "moreEnemyJungleThanOpponent": 0, "multiKillOneSpell": 0, "multiTurretRiftHeraldCount": 0, "multikills": 0, "multikillsAfterAggressiveFlash": 0, "mythicItemUsed": 3001, "outerTurretExecutesBefore10Minutes": 0, "outnumberedKills": 1, "outnumberedNexusKill": 0, "perfectDragonSoulsTaken": 0, "perfectGame": 0, "pickKillWithAlly": 9, "playedChampSelectPosition": 1, "poroExplosions": 0, "quickCleanse": 0, "quickFirstTurret": 0, "quickSoloKills": 0, "riftHeraldTakedowns": 0, "saveAllyFromDeath": 0, "scuttleCrabKills": 0, "skillshotsDodged": 145, "skillshotsHit": 9, "snowballsHit": 0, "soloBaronKills": 0, "soloKills": 1, "stealthWardsPlaced": 12, "survivedSingleDigitHpCount": 0, "survivedThreeImmobilizesInFight": 2, "takedownOnFirstTurret": 0, "takedowns": 11, "takedownsAfterGainingLevelAdvantage": 0, "takedownsBeforeJungleMinionSpawn": 0, "takedownsFirstXMinutes": 8, "takedownsInAlcove": 0, "takedownsInEnemyFountain": 0, "teamBaronKills": 0, "teamDamagePercentage": 0.0930925638524171, "teamElderDragonKills": 0, "teamRiftHeraldKills": 0, "tookLargeDamageSurvived": 0, "turretPlatesTaken": 1, "turretTakedowns": 0, "turretsTakenWithRiftHerald": 0, "twentyMinionsIn3SecondsCount": 0, "twoWardsOneSweeperCount": 0, "unseenRecalls": 0, "visionScoreAdvantageLaneOpponent": -0.5053749084472656, "visionScorePerMinute": 1.355607271043563, "wardTakedowns": 2, "wardTakedownsBefore20M": 2, "wardsGuarded": 0}, "champExperience": 7781, "champLevel": 11, "championId": 111, "championName": "Nautilus", "championTransform": 0, "commandPings": 7, "consumablesPurchased": 11, "damageDealtToBuildings": 0, "damageDealtToObjectives": 438, "damageDealtToTurrets": 0, "damageSelfMitigated": 25079, "dangerPings": 0, "deaths": 8, "detectorWardsPlaced": 8, "doubleKills": 0, "dragonKills": 0, "eligibleForProgression": true, "enemyMissingPings": 2, "enemyVisionPings": 0, "firstBloodAssist": false, "firstBloodKill": false, "firstTowerAssist": false, "firstTowerKill": false, "gameEndedInEarlySurrender": false, "gameEndedInSurrender": true, "getBackPings": 0, "goldEarned": 6090, "goldSpent": 5725, "holdPings": 0, "individualPosition": "UTILITY", "inhibitorKills": 0, "inhibitorTakedowns": 0, "inhibitorsLost": 1, "item0": 3860, "item1": 2055, "item2": 3082, "item3": 3001, "item4": 3111, "item5": 0, "item6": 3364, "itemsPurchased": 24, "killingSprees": 0, "kills": 1, "lane": "BOTTOM", "largestCriticalStrike": 0, "largestKillingSpree": 0, "largestMultiKill": 1, "longestTimeSpentLiving": 297, "magicDamageDealt": 5589, "magicDamageDealtToChampions": 3025, "magicDamageTaken": 3434, "needVisionPings": 0, "neutralMinionsKilled": 0, "nexusKills": 0, "nexusLost": 0, "nexusTakedowns": 0, "objectivesStolen": 0, "objectivesStolenAssists": 0, "onMyWayPings": 0, "participantId": 5, "pentaKills": 0, "perks": {"statPerks": {"defense": 5002, "flex": 5002, "offense": 5005}, "styles": [{"description": "primaryStyle", "selections": [{"perk": 8351, "var1": 55, "var2": 848, "var3": 0}, {"perk": 8306, "var1": 5, "var2": 0, "var3": 0}, {"perk": 8345, "var1": 3, "var2": 0, "var3": 0}, {"perk": 8347, "var1": 0, "var2": 0, "var3": 0}], "style": 8300}, {"description": "subStyle", "selections": [{"perk": 8473, "var1": 501, "var2": 0, "var3": 0}, {"perk": 8242, "var1": 68, "var2": 0, "var3": 0}], "style": 8400}]}, "physicalDamageDealt": 6582, "physicalDamageDealtToChampions": 1795, "physicalDamageTaken": 14851, "placement": 0, "playerAugment1": 0, "playerAugment2": 0, "playerAugment3": 0, "playerAugment4": 0, "playerSubteamId": 0, "profileIcon": 23, "pushPings": 0, "puuid": "cdD-OmPAObkR2a2KFRlbF2Xf8a1rUmulugeFEOGzyN7R5lmy8BJOe93qFutGaa5P9O0nmiW3HNEqPw", "quadraKills": 0, "riotIdName": "", "riotIdTagline": "", "role": "SUPPORT", "sightWardsBoughtInGame": 0, "spell1Casts": 39, "spell2Casts": 27, "spell3Casts": 19, "spell4Casts": 7, "subteamPlacement": 0, "summoner1Casts": 5, "summoner1Id": 14, "summoner2Casts": 10, "summoner2Id": 4, "summonerId": "VJG5tuL90F3SpkIstLAEW12pgQ-F-4BU1nWewothONy21kE", "summonerLevel": 881, "summonerName": "\ud54f\ube5b \uacc4\uc57d", "teamEarlySurrendered": false, "teamId": 100, "teamPosition": "UTILITY", "timeCCingOthers": 46, "timePlayed": 1587, "totalAllyJungleMinionsKilled": 0, "totalDamageDealt": 17934, "totalDamageDealtToChampions": 5416, "totalDamageShieldedOnTeammates": 0, "totalDamageTaken": 18660, "totalEnemyJungleMinionsKilled": 0, "totalHeal": 631, "totalHealsOnTeammates": 0, "totalMinionsKilled": 29, "totalTimeCCDealt": 232, "totalTimeSpentDead": 156, "totalUnitsHealed": 1, "tripleKills": 0, "trueDamageDealt": 5762, "trueDamageDealtToChampions": 595, "trueDamageTaken": 374, "turretKills": 0, "turretTakedowns": 0, "turretsLost": 7, "unrealKills": 0, "visionClearedPings": 0, "visionScore": 35, "visionWardsBoughtInGame": 9, "wardsKilled": 2, "wardsPlaced": 20, "win": false}, {"allInPings": 0, "assistMePings": 1, "assists": 5, "baitPings": 0, "baronKills": 0, "basicPings": 0, "bountyLevel": 2, "challenges": {"12AssistStreakCount": 0, "abilityUses": 461, "acesBefore15Minutes": 0, "alliedJungleMonsterKills": 0, "baronBuffGoldAdvantageOverThreshold": 1, "baronTakedowns": 1, "blastConeOppositeOpponentCount": 0, "bountyGold": 0, "buffsStolen": 0, "completeSupportQuestInTime": 0, "controlWardTimeCoverageInRiverOrEnemyHalf": 0.16388277477200508, "controlWardsPlaced": 3, "damagePerMinute": 668.7098226266679, "damageTakenOnTeamPercentage": 0.22272942050050026, "dancedWithRiftHerald": 0, "deathsByEnemyChamps": 2, "dodgeSkillShotsSmallWindow": 0, "doubleAces": 0, "dragonTakedowns": 0, "earliestBaron": 1275.1103647999998, "earlyLaningPhaseGoldExpAdvantage": 0, "effectiveHealAndShielding": 0, "elderDragonKillsWithOpposingSoul": 0, "elderDragonMultikills": 0, "enemyChampionImmobilizations": 4, "enemyJungleMonsterKills": 0, "epicMonsterKillsNearEnemyJungler": 0, "epicMonsterKillsWithin30SecondsOfSpawn": 0, "epicMonsterSteals": 0, "epicMonsterStolenWithoutSmite": 0, "firstTurretKilled": 1, "firstTurretKilledTime": 734.2218237999999, "flawlessAces": 0, "fullTeamTakedown": 0, "gameLength": 1587.4567035, "getTakedownsInAllLanesEarlyJungleAsLaner": 0, "goldPerMinute": 342.94807136687996, "hadOpenNexus": 0, "immobilizeAndKillWithAlly": 2, "initialBuffCount": 0, "initialCrabCount": 0, "jungleCsBefore10Minutes": 0, "junglerTakedownsNearDamagedEpicMonster": 0, "kTurretsDestroyedBeforePlatesFall": 0, "kda": 4, "killAfterHiddenWithAlly": 0, "killParticipation": 0.25806451612903225, "killedChampTookFullTeamDamageSurvived": 0, "killingSprees": 0, "killsNearEnemyTurret": 1, "killsOnOtherLanesEarlyJungleAsLaner": 0, "killsOnRecentlyHealedByAramPack": 0, "killsUnderOwnTurret": 0, "killsWithHelpFromEpicMonster": 0, "knockEnemyIntoTeamAndKill": 0, "landSkillShotsEarlyGame": 1, "laneMinionsFirst10Minutes": 70, "laningPhaseGoldExpAdvantage": 0, "legendaryCount": 0, "lostAnInhibitor": 0, "maxCsAdvantageOnLaneOpponent": 2, "maxKillDeficit": 2, "maxLevelLeadLaneOpponent": 2, "mejaisFullStackInTime": 0, "moreEnemyJungleThanOpponent": 0, "multiKillOneSpell": 0, "multiTurretRiftHeraldCount": 0, "multikills": 0, "multikillsAfterAggressiveFlash": 0, "mythicItemUsed": 6657, "outerTurretExecutesBefore10Minutes": 0, "outnumberedKills": 1, "outnumberedNexusKill": 0, "perfectDragonSoulsTaken": 0, "perfectGame": 0, "pickKillWithAlly": 4, "playedChampSelectPosition": 1, "poroExplosions": 0, "quickCleanse": 0, "quickFirstTurret": 0, "quickSoloKills": 0, "riftHeraldTakedowns": 1, "saveAllyFromDeath": 0, "scuttleCrabKills": 0, "skillshotsDodged": 8, "skillshotsHit": 9, "snowballsHit": 0, "soloBaronKills": 0, "soloKills": 1, "stealthWardsPlaced": 4, "survivedSingleDigitHpCount": 0, "survivedThreeImmobilizesInFight": 2, "takedownOnFirstTurret": 0, "takedowns": 8, "takedownsAfterGainingLevelAdvantage": 0, "takedownsBeforeJungleMinionSpawn": 0, "takedownsFirstXMinutes": 3, "takedownsInAlcove": 0, "takedownsInEnemyFountain": 0, "teamBaronKills": 1, "teamDamagePercentage": 0.19609883328878996, "teamElderDragonKills": 0, "teamRiftHeraldKills": 2, "tookLargeDamageSurvived": 0, "turretPlatesTaken": 1, "turretTakedowns": 0, "turretsTakenWithRiftHerald": 10, "twentyMinionsIn3SecondsCount": 7, "twoWardsOneSweeperCount": 0, "unseenRecalls": 0, "visionScoreAdvantageLaneOpponent": 0.01897728443145752, "visionScorePerMinute": 0.9339102913081655, "wardTakedowns": 2, "wardTakedownsBefore20M": 1, "wardsGuarded": 0}, "champExperience": 14056, "champLevel": 15, "championId": 69, "championName": "Cassiopeia", "championTransform": 0, "commandPings": 3, "consumablesPurchased": 7, "damageDealtToBuildings": 1218, "damageDealtToObjectives": 5165, "damageDealtToTurrets": 1218, "damageSelfMitigated": 10425, "dangerPings": 0, "deaths": 2, "detectorWardsPlaced": 3, "doubleKills": 0, "dragonKills": 0, "eligibleForProgression": true, "enemyMissingPings": 3, "enemyVisionPings": 0, "firstBloodAssist": false, "firstBloodKill": false, "firstTowerAssist": false, "firstTowerKill": false, "gameEndedInEarlySurrender": false, "gameEndedInSurrender": true, "getBackPings": 5, "goldEarned": 9073, "goldSpent": 8075, "holdPings": 0, "individualPosition": "TOP", "inhibitorKills": 0, "inhibitorTakedowns": 0, "inhibitorsLost": 0, "item0": 3040, "item1": 0, "item2": 2420, "item3": 6657, "item4": 3191, "item5": 0, "item6": 3363, "itemsPurchased": 21, "killingSprees": 1, "kills": 3, "lane": "TOP", "largestCriticalStrike": 0, "largestKillingSpree": 2, "largestMultiKill": 1, "longestTimeSpentLiving": 806, "magicDamageDealt": 82366, "magicDamageDealtToChampions": 16724, "magicDamageTaken": 4374, "needVisionPings": 0, "neutralMinionsKilled": 0, "nexusKills": 0, "nexusLost": 0, "nexusTakedowns": 0, "objectivesStolen": 0, "objectivesStolenAssists": 0, "onMyWayPings": 8, "participantId": 6, "pentaKills": 0, "perks": {"statPerks": {"defense": 5002, "flex": 5008, "offense": 5008}, "styles": [{"description": "primaryStyle", "selections": [{"perk": 8010, "var1": 411, "var2": 0, "var3": 0}, {"perk": 8009, "var1": 3350, "var2": 0, "var3": 0}, {"perk": 9105, "var1": 20, "var2": 40, "var3": 0}, {"perk": 8299, "var1": 387, "var2": 0, "var3": 0}], "style": 8000}, {"description": "subStyle", "selections": [{"perk": 8226, "var1": 250, "var2": 1190, "var3": 0}, {"perk": 8210, "var1": 11, "var2": 0, "var3": 0}], "style": 8200}]}, "physicalDamageDealt": 9077, "physicalDamageDealtToChampions": 968, "physicalDamageTaken": 12790, "placement": 0, "playerAugment1": 0, "playerAugment2": 0, "playerAugment3": 0, "playerAugment4": 0, "playerSubteamId": 0, "profileIcon": 21, "pushPings": 0, "puuid": "efvdQA3l61WwjnLHmOqwxL4sij6807p_4x1z8ANOC_mjf9y3Kr9oFi74PqXw_L8U1asyMhPhyyq9-Q", "quadraKills": 0, "riotIdName": "", "riotIdTagline": "", "role": "SOLO", "sightWardsBoughtInGame": 0, "spell1Casts": 102, "spell2Casts": 15, "spell3Casts": 337, "spell4Casts": 7, "subteamPlacement": 0, "summoner1Casts": 4, "summoner1Id": 12, "summoner2Casts": 3, "summoner2Id": 4, "summonerId": "jIbx5zAUGZOVQVCP_IpxQPZXkp1AR2ZnupRWPUYgO0NhtL6jwHJXZh2tTQ", "summonerLevel": 150, "summonerName": "\uc0ac\ub791\uc2a4\ub7ec\uc6b4 \uc2ac\uae30", "teamEarlySurrendered": false, "teamId": 200, "teamPosition": "TOP", "timeCCingOthers": 11, "timePlayed": 1587, "totalAllyJungleMinionsKilled": 0, "totalDamageDealt": 91533, "totalDamageDealtToChampions": 17692, "totalDamageShieldedOnTeammates": 0, "totalDamageTaken": 17499, "totalEnemyJungleMinionsKilled": 0, "totalHeal": 7243, "totalHealsOnTeammates": 0, "totalMinionsKilled": 153, "totalTimeCCDealt": 213, "totalTimeSpentDead": 71, "totalUnitsHealed": 1, "tripleKills": 0, "trueDamageDealt": 90, "trueDamageDealtToChampions": 0, "trueDamageTaken": 335, "turretKills": 0, "turretTakedowns": 0, "turretsLost": 1, "unrealKills": 0, "visionClearedPings": 3, "visionScore": 24, "visionWardsBoughtInGame": 4, "wardsKilled": 2, "wardsPlaced": 10, "win": true}, {"allInPings": 0, "assistMePings": 7, "assists": 2, "baitPings": 0, "baronKills": 1, "basicPings": 0, "bountyLevel": 2, "challenges": {"12AssistStreakCount": 0, "abilityUses": 408, "acesBefore15Minutes": 0, "alliedJungleMonsterKills": 67, "baronBuffGoldAdvantageOverThreshold": 1, "baronTakedowns": 1, "blastConeOppositeOpponentCount": 0, "bountyGold": 0, "buffsStolen": 4, "completeSupportQuestInTime": 0, "controlWardTimeCoverageInRiverOrEnemyHalf": 0.4860106571089232, "controlWardsPlaced": 2, "damagePerMinute": 763.2424451426937, "damageTakenOnTeamPercentage": 0.25001943674035515, "dancedWithRiftHerald": 0, "deathsByEnemyChamps": 2, "dodgeSkillShotsSmallWindow": 1, "doubleAces": 0, "dragonTakedowns": 3, "earliestBaron": 1275.1103647999998, "earliestDragonTakedown": 425.0044317, "earlyLaningPhaseGoldExpAdvantage": 0, "effectiveHealAndShielding": 0, "elderDragonKillsWithOpposingSoul": 0, "elderDragonMultikills": 0, "enemyChampionImmobilizations": 0, "enemyJungleMonsterKills": 16, "epicMonsterKillsNearEnemyJungler": 0, "epicMonsterKillsWithin30SecondsOfSpawn": 1, "epicMonsterSteals": 0, "epicMonsterStolenWithoutSmite": 0, "fastestLegendary": 1178.961869, "firstTurretKilled": 1, "firstTurretKilledTime": 734.2218237999999, "flawlessAces": 0, "fullTeamTakedown": 0, "gameLength": 1587.4567035, "goldPerMinute": 574.0948159739842, "hadOpenNexus": 0, "highestWardKills": 1, "immobilizeAndKillWithAlly": 0, "initialBuffCount": 2, "initialCrabCount": 1, "jungleCsBefore10Minutes": 67.00000005960464, "junglerKillsEarlyJungle": 0, "junglerTakedownsNearDamagedEpicMonster": 0, "kTurretsDestroyedBeforePlatesFall": 0, "kda": 6.5, "killAfterHiddenWithAlly": 2, "killParticipation": 0.41935483870967744, "killedChampTookFullTeamDamageSurvived": 0, "killingSprees": 1, "killsNearEnemyTurret": 1, "killsOnLanersEarlyJungleAsJungler": 0, "killsOnRecentlyHealedByAramPack": 0, "killsUnderOwnTurret": 0, "killsWithHelpFromEpicMonster": 0, "knockEnemyIntoTeamAndKill": 0, "landSkillShotsEarlyGame": 3, "laneMinionsFirst10Minutes": 1, "laningPhaseGoldExpAdvantage": 1, "legendaryCount": 1, "lostAnInhibitor": 0, "maxCsAdvantageOnLaneOpponent": 97.20000004768372, "maxKillDeficit": 2, "maxLevelLeadLaneOpponent": 3, "mejaisFullStackInTime": 0, "moreEnemyJungleThanOpponent": -24.500000059604645, "multiKillOneSpell": 0, "multiTurretRiftHeraldCount": 0, "multikills": 1, "multikillsAfterAggressiveFlash": 1, "mythicItemUsed": 6692, "outerTurretExecutesBefore10Minutes": 0, "outnumberedKills": 3, "outnumberedNexusKill": 0, "perfectDragonSoulsTaken": 0, "perfectGame": 0, "pickKillWithAlly": 9, "playedChampSelectPosition": 1, "poroExplosions": 0, "quickCleanse": 0, "quickFirstTurret": 0, "quickSoloKills": 0, "riftHeraldTakedowns": 2, "saveAllyFromDeath": 0, "scuttleCrabKills": 4, "skillshotsDodged": 10, "skillshotsHit": 27, "snowballsHit": 0, "soloBaronKills": 0, "soloKills": 1, "stealthWardsPlaced": 2, "survivedSingleDigitHpCount": 0, "survivedThreeImmobilizesInFight": 2, "takedownOnFirstTurret": 0, "takedowns": 13, "takedownsAfterGainingLevelAdvantage": 0, "takedownsBeforeJungleMinionSpawn": 0, "takedownsFirstXMinutes": 9, "takedownsInAlcove": 0, "takedownsInEnemyFountain": 0, "teamBaronKills": 1, "teamDamagePercentage": 0.22382047929408816, "teamElderDragonKills": 0, "teamRiftHeraldKills": 2, "tookLargeDamageSurvived": 0, "turretPlatesTaken": 3, "turretTakedowns": 3, "turretsTakenWithRiftHerald": 10, "twentyMinionsIn3SecondsCount": 1, "twoWardsOneSweeperCount": 1, "unseenRecalls": 0, "visionScoreAdvantageLaneOpponent": 0.9565960168838501, "visionScorePerMinute": 2.648890661263031, "wardTakedowns": 16, "wardTakedownsBefore20M": 9, "wardsGuarded": 0}, "champExperience": 14647, "champLevel": 15, "championId": 121, "championName": "Khazix", "championTransform": 0, "commandPings": 13, "consumablesPurchased": 3, "damageDealtToBuildings": 3336, "damageDealtToObjectives": 48535, "damageDealtToTurrets": 3336, "damageSelfMitigated": 23183, "dangerPings": 0, "deaths": 2, "detectorWardsPlaced": 2, "doubleKills": 1, "dragonKills": 3, "eligibleForProgression": true, "enemyMissingPings": 2, "enemyVisionPings": 0, "firstBloodAssist": false, "firstBloodKill": false, "firstTowerAssist": false, "firstTowerKill": false, "gameEndedInEarlySurrender": false, "gameEndedInSurrender": true, "getBackPings": 6, "goldEarned": 15189, "goldSpent": 14250, "holdPings": 0, "individualPosition": "JUNGLE", "inhibitorKills": 0, "inhibitorTakedowns": 1, "inhibitorsLost": 0, "item0": 6692, "item1": 3814, "item2": 1038, "item3": 3111, "item4": 6694, "item5": 3179, "item6": 3364, "itemsPurchased": 17, "killingSprees": 2, "kills": 11, "lane": "JUNGLE", "largestCriticalStrike": 0, "largestKillingSpree": 8, "largestMultiKill": 2, "longestTimeSpentLiving": 880, "magicDamageDealt": 977, "magicDamageDealtToChampions": 977, "magicDamageTaken": 5171, "needVisionPings": 0, "neutralMinionsKilled": 186, "nexusKills": 0, "nexusLost": 0, "nexusTakedowns": 0, "objectivesStolen": 0, "objectivesStolenAssists": 0, "onMyWayPings": 31, "participantId": 7, "pentaKills": 0, "perks": {"statPerks": {"defense": 5002, "flex": 5008, "offense": 5008}, "styles": [{"description": "primaryStyle", "selections": [{"perk": 8369, "var1": 727, "var2": 600, "var3": 0}, {"perk": 8304, "var1": 9, "var2": 0, "var3": 0}, {"perk": 8321, "var1": 3, "var2": 0, "var3": 0}, {"perk": 8347, "var1": 0, "var2": 0, "var3": 0}], "style": 8300}, {"description": "subStyle", "selections": [{"perk": 8136, "var1": 17, "var2": 30, "var3": 0}, {"perk": 8143, "var1": 592, "var2": 0, "var3": 0}], "style": 8100}]}, "physicalDamageDealt": 212766, "physicalDamageDealtToChampions": 17987, "physicalDamageTaken": 14385, "placement": 0, "playerAugment1": 0, "playerAugment2": 0, "playerAugment3": 0, "playerAugment4": 0, "playerSubteamId": 0, "profileIcon": 5860, "pushPings": 0, "puuid": "LDtz3vBiOf0CTuDzWp0fDq3UhyjUZyvwhvY8bm7_K1mN_tTZoPSe2Mtx95F53eMoCe3HfC42yta93A", "quadraKills": 0, "riotIdName": "", "riotIdTagline": "", "role": "NONE", "sightWardsBoughtInGame": 0, "spell1Casts": 237, "spell2Casts": 107, "spell3Casts": 48, "spell4Casts": 16, "subteamPlacement": 0, "summoner1Casts": 4, "summoner1Id": 4, "summoner2Casts": 16, "summoner2Id": 11, "summonerId": "p6rMKeNcYoMwykd_NMncwo3CeUVjXjtZX6ZYeK1ymQMVFA", "summonerLevel": 610, "summonerName": "\uba85\uce58\uc5d0\ud314\ucf58\ud380\uce58\uaf42\ub294\uc774\ub3c4\uc724", "teamEarlySurrendered": false, "teamId": 200, "teamPosition": "JUNGLE", "timeCCingOthers": 8, "timePlayed": 1587, "totalAllyJungleMinionsKilled": 106, "totalDamageDealt": 252359, "totalDamageDealtToChampions": 20193, "totalDamageShieldedOnTeammates": 0, "totalDamageTaken": 19643, "totalEnemyJungleMinionsKilled": 35, "totalHeal": 12622, "totalHealsOnTeammates": 0, "totalMinionsKilled": 34, "totalTimeCCDealt": 368, "totalTimeSpentDead": 53, "totalUnitsHealed": 1, "tripleKills": 0, "trueDamageDealt": 38615, "trueDamageDealtToChampions": 1228, "trueDamageTaken": 85, "turretKills": 3, "turretTakedowns": 3, "turretsLost": 1, "unrealKills": 0, "visionClearedPings": 0, "visionScore": 70, "visionWardsBoughtInGame": 2, "wardsKilled": 16, "wardsPlaced": 21, "win": true}, {"allInPings": 1, "assistMePings": 31, "assists": 20, "baitPings": 0, "baronKills": 0, "basicPings": 0, "bountyLevel": 0, "challenges": {"12AssistStreakCount": 1, "abilityUses": 263, "acesBefore15Minutes": 0, "alliedJungleMonsterKills": 6, "baronBuffGoldAdvantageOverThreshold": 1, "baronTakedowns": 1, "blastConeOppositeOpponentCount": 0, "bountyGold": 0, "buffsStolen": 0, "completeSupportQuestInTime": 0, "controlWardTimeCoverageInRiverOrEnemyHalf": 0.748486619559637, "controlWardsPlaced": 3, "damagePerMinute": 450.28629657993065, "damageTakenOnTeamPercentage": 0.2060337235369013, "dancedWithRiftHerald": 0, "deathsByEnemyChamps": 7, "dodgeSkillShotsSmallWindow": 1, "doubleAces": 0, "dragonTakedowns": 1, "earliestBaron": 1275.1103647999998, "earliestDragonTakedown": 425.0044317, "earlyLaningPhaseGoldExpAdvantage": 0, "effectiveHealAndShielding": 0, "elderDragonKillsWithOpposingSoul": 0, "elderDragonMultikills": 0, "enemyChampionImmobilizations": 17, "enemyJungleMonsterKills": 0, "epicMonsterKillsNearEnemyJungler": 0, "epicMonsterKillsWithin30SecondsOfSpawn": 0, "epicMonsterSteals": 0, "epicMonsterStolenWithoutSmite": 0, "firstTurretKilled": 1, "firstTurretKilledTime": 734.2218237999999, "flawlessAces": 0, "fullTeamTakedown": 0, "gameLength": 1587.4567035, "getTakedownsInAllLanesEarlyJungleAsLaner": 0, "goldPerMinute": 398.89203071106, "hadOpenNexus": 0, "immobilizeAndKillWithAlly": 7, "initialBuffCount": 0, "initialCrabCount": 0, "jungleCsBefore10Minutes": 0, "junglerTakedownsNearDamagedEpicMonster": 1, "kTurretsDestroyedBeforePlatesFall": 0, "kda": 3, "killAfterHiddenWithAlly": 1, "killParticipation": 0.6774193548387096, "killedChampTookFullTeamDamageSurvived": 0, "killingSprees": 0, "killsNearEnemyTurret": 0, "killsOnOtherLanesEarlyJungleAsLaner": 0, "killsOnRecentlyHealedByAramPack": 0, "killsUnderOwnTurret": 1, "killsWithHelpFromEpicMonster": 0, "knockEnemyIntoTeamAndKill": 0, "landSkillShotsEarlyGame": 8, "laneMinionsFirst10Minutes": 63, "laningPhaseGoldExpAdvantage": 0, "legendaryCount": 0, "lostAnInhibitor": 0, "maxCsAdvantageOnLaneOpponent": 17, "maxKillDeficit": 2, "maxLevelLeadLaneOpponent": 1, "mejaisFullStackInTime": 0, "moreEnemyJungleThanOpponent": 0, "multiKillOneSpell": 0, "multiTurretRiftHeraldCount": 0, "multikills": 0, "multikillsAfterAggressiveFlash": 0, "mythicItemUsed": 6656, "outerTurretExecutesBefore10Minutes": 0, "outnumberedKills": 0, "outnumberedNexusKill": 0, "perfectDragonSoulsTaken": 0, "perfectGame": 0, "pickKillWithAlly": 12, "playedChampSelectPosition": 1, "poroExplosions": 0, "quickCleanse": 0, "quickFirstTurret": 0, "quickSoloKills": 0, "riftHeraldTakedowns": 1, "saveAllyFromDeath": 0, "scuttleCrabKills": 0, "shortestTimeToAceFromFirstTakedown": 13.913513400000056, "skillshotsDodged": 12, "skillshotsHit": 38, "snowballsHit": 0, "soloBaronKills": 0, "soloKills": 0, "stealthWardsPlaced": 8, "survivedSingleDigitHpCount": 0, "survivedThreeImmobilizesInFight": 2, "takedownOnFirstTurret": 0, "takedowns": 21, "takedownsAfterGainingLevelAdvantage": 1, "takedownsBeforeJungleMinionSpawn": 0, "takedownsFirstXMinutes": 15, "takedownsInAlcove": 0, "takedownsInEnemyFountain": 0, "teamBaronKills": 1, "teamDamagePercentage": 0.13204623951598743, "teamElderDragonKills": 0, "teamRiftHeraldKills": 2, "tookLargeDamageSurvived": 0, "turretPlatesTaken": 0, "turretTakedowns": 2, "turretsTakenWithRiftHerald": 10, "twentyMinionsIn3SecondsCount": 6, "twoWardsOneSweeperCount": 0, "unseenRecalls": 0, "visionScoreAdvantageLaneOpponent": 0.22714781761169434, "visionScorePerMinute": 1.1019117619258998, "wardTakedowns": 1, "wardTakedownsBefore20M": 0, "wardsGuarded": 0}, "champExperience": 12525, "champLevel": 14, "championId": 4, "championName": "TwistedFate", "championTransform": 0, "commandPings": 17, "consumablesPurchased": 7, "damageDealtToBuildings": 848, "damageDealtToObjectives": 3155, "damageDealtToTurrets": 848, "damageSelfMitigated": 9673, "dangerPings": 0, "deaths": 7, "detectorWardsPlaced": 3, "doubleKills": 0, "dragonKills": 0, "eligibleForProgression": true, "enemyMissingPings": 29, "enemyVisionPings": 6, "firstBloodAssist": false, "firstBloodKill": false, "firstTowerAssist": false, "firstTowerKill": false, "gameEndedInEarlySurrender": false, "gameEndedInSurrender": true, "getBackPings": 44, "goldEarned": 10553, "goldSpent": 9575, "holdPings": 0, "individualPosition": "MIDDLE", "inhibitorKills": 0, "inhibitorTakedowns": 1, "inhibitorsLost": 0, "item0": 3157, "item1": 3113, "item2": 3108, "item3": 6656, "item4": 3111, "item5": 1082, "item6": 3340, "itemsPurchased": 23, "killingSprees": 0, "kills": 1, "lane": "MIDDLE", "largestCriticalStrike": 0, "largestKillingSpree": 0, "largestMultiKill": 1, "longestTimeSpentLiving": 374, "magicDamageDealt": 87972, "magicDamageDealtToChampions": 10042, "magicDamageTaken": 7110, "needVisionPings": 0, "neutralMinionsKilled": 4, "nexusKills": 0, "nexusLost": 0, "nexusTakedowns": 0, "objectivesStolen": 0, "objectivesStolenAssists": 0, "onMyWayPings": 54, "participantId": 8, "pentaKills": 0, "perks": {"statPerks": {"defense": 5003, "flex": 5008, "offense": 5005}, "styles": [{"description": "primaryStyle", "selections": [{"perk": 8112, "var1": 793, "var2": 0, "var3": 0}, {"perk": 8139, "var1": 536, "var2": 0, "var3": 0}, {"perk": 8138, "var1": 30, "var2": 0, "var3": 0}, {"perk": 8135, "var1": 450, "var2": 5, "var3": 0}], "style": 8100}, {"description": "subStyle", "selections": [{"perk": 8316, "var1": 3344, "var2": 0, "var3": 0}, {"perk": 8352, "var1": 124, "var2": 425, "var3": 0}], "style": 8300}]}, "physicalDamageDealt": 9533, "physicalDamageDealtToChampions": 1180, "physicalDamageTaken": 8725, "placement": 0, "playerAugment1": 0, "playerAugment2": 0, "playerAugment3": 0, "playerAugment4": 0, "playerSubteamId": 0, "profileIcon": 23, "pushPings": 0, "puuid": "7a1UxGBP5ydRjl5jwK_Ccjs6zWOHw5LP1XGxPxwpf38RKP_29b5xeG3aRTnlg20NCy2UO3555_mc1Q", "quadraKills": 0, "riotIdName": "", "riotIdTagline": "", "role": "SOLO", "sightWardsBoughtInGame": 0, "spell1Casts": 76, "spell2Casts": 174, "spell3Casts": 0, "spell4Casts": 13, "subteamPlacement": 0, "summoner1Casts": 5, "summoner1Id": 14, "summoner2Casts": 3, "summoner2Id": 4, "summonerId": "zkqHcHxGxU0Y-yTStsBAbW3Lpu7FqsuFG0X2RvAUqBTpLNftnMmL0_aLcQ", "summonerLevel": 90, "summonerName": "Jiri", "teamEarlySurrendered": false, "teamId": 200, "teamPosition": "MIDDLE", "timeCCingOthers": 21, "timePlayed": 1587, "totalAllyJungleMinionsKilled": 4, "totalDamageDealt": 105083, "totalDamageDealtToChampions": 11913, "totalDamageShieldedOnTeammates": 0, "totalDamageTaken": 16187, "totalEnemyJungleMinionsKilled": 0, "totalHeal": 2223, "totalHealsOnTeammates": 0, "totalMinionsKilled": 151, "totalTimeCCDealt": 99, "totalTimeSpentDead": 152, "totalUnitsHealed": 1, "tripleKills": 0, "trueDamageDealt": 7576, "trueDamageDealtToChampions": 690, "trueDamageTaken": 351, "turretKills": 0, "turretTakedowns": 2, "turretsLost": 1, "unrealKills": 0, "visionClearedPings": 0, "visionScore": 29, "visionWardsBoughtInGame": 3, "wardsKilled": 1, "wardsPlaced": 12, "win": true}, {"allInPings": 0, "assistMePings": 12, "assists": 4, "baitPings": 0, "baronKills": 0, "basicPings": 0, "bountyLevel": 4, "challenges": {"12AssistStreakCount": 0, "abilityUses": 566, "acesBefore15Minutes": 0, "alliedJungleMonsterKills": 9, "baronBuffGoldAdvantageOverThreshold": 1, "baronTakedowns": 1, "blastConeOppositeOpponentCount": 0, "bountyGold": 0, "buffsStolen": 1, "completeSupportQuestInTime": 0, "controlWardTimeCoverageInRiverOrEnemyHalf": 0.49656144993563284, "controlWardsPlaced": 2, "damagePerMinute": 1330.985414651972, "damageTakenOnTeamPercentage": 0.16047851607836372, "dancedWithRiftHerald": 0, "deathsByEnemyChamps": 1, "dodgeSkillShotsSmallWindow": 2, "doubleAces": 0, "dragonTakedowns": 1, "earliestBaron": 1275.1103647999998, "earliestDragonTakedown": 1507.7112522999998, "earlyLaningPhaseGoldExpAdvantage": 1, "effectiveHealAndShielding": 0, "elderDragonKillsWithOpposingSoul": 0, "elderDragonMultikills": 0, "enemyChampionImmobilizations": 7, "enemyJungleMonsterKills": 4, "epicMonsterKillsNearEnemyJungler": 0, "epicMonsterKillsWithin30SecondsOfSpawn": 0, "epicMonsterSteals": 0, "epicMonsterStolenWithoutSmite": 0, "fastestLegendary": 703.772117, "firstTurretKilled": 1, "firstTurretKilledTime": 734.2218237999999, "flawlessAces": 0, "fullTeamTakedown": 0, "gameLength": 1587.4567035, "getTakedownsInAllLanesEarlyJungleAsLaner": 0, "goldPerMinute": 616.1265233445782, "hadOpenNexus": 0, "highestChampionDamage": 1, "immobilizeAndKillWithAlly": 3, "initialBuffCount": 0, "initialCrabCount": 0, "jungleCsBefore10Minutes": 0, "junglerTakedownsNearDamagedEpicMonster": 0, "kTurretsDestroyedBeforePlatesFall": 1, "kda": 19, "killAfterHiddenWithAlly": 0, "killParticipation": 0.6129032258064516, "killedChampTookFullTeamDamageSurvived": 0, "killingSprees": 2, "killsNearEnemyTurret": 4, "killsOnOtherLanesEarlyJungleAsLaner": 2, "killsOnRecentlyHealedByAramPack": 0, "killsUnderOwnTurret": 1, "killsWithHelpFromEpicMonster": 0, "knockEnemyIntoTeamAndKill": 0, "landSkillShotsEarlyGame": 5, "laneMinionsFirst10Minutes": 62, "laningPhaseGoldExpAdvantage": 1, "legendaryCount": 1, "lostAnInhibitor": 0, "maxCsAdvantageOnLaneOpponent": 44.599999994039536, "maxKillDeficit": 2, "maxLevelLeadLaneOpponent": 2, "mejaisFullStackInTime": 0, "moreEnemyJungleThanOpponent": 0, "multiKillOneSpell": 0, "multiTurretRiftHeraldCount": 0, "multikills": 7, "multikillsAfterAggressiveFlash": 0, "mythicItemUsed": 6671, "outerTurretExecutesBefore10Minutes": 0, "outnumberedKills": 8, "outnumberedNexusKill": 0, "perfectDragonSoulsTaken": 0, "perfectGame": 0, "pickKillWithAlly": 9, "playedChampSelectPosition": 1, "poroExplosions": 0, "quickCleanse": 1, "quickFirstTurret": 0, "quickSoloKills": 0, "riftHeraldTakedowns": 1, "saveAllyFromDeath": 0, "scuttleCrabKills": 0, "shortestTimeToAceFromFirstTakedown": 13.913513400000056, "skillshotsDodged": 11, "skillshotsHit": 80, "snowballsHit": 0, "soloBaronKills": 0, "soloKills": 2, "soloTurretsLategame": 1, "stealthWardsPlaced": 4, "survivedSingleDigitHpCount": 0, "survivedThreeImmobilizesInFight": 2, "takedownOnFirstTurret": 1, "takedowns": 19, "takedownsAfterGainingLevelAdvantage": 0, "takedownsBeforeJungleMinionSpawn": 0, "takedownsFirstXMinutes": 13, "takedownsInAlcove": 0, "takedownsInEnemyFountain": 0, "teamBaronKills": 1, "teamDamagePercentage": 0.3903108315538586, "teamElderDragonKills": 0, "teamRiftHeraldKills": 2, "tookLargeDamageSurvived": 0, "turretPlatesTaken": 5, "turretTakedowns": 4, "turretsTakenWithRiftHerald": 10, "twentyMinionsIn3SecondsCount": 9, "twoWardsOneSweeperCount": 0, "unseenRecalls": 0, "visionScoreAdvantageLaneOpponent": -0.05944383144378662, "visionScorePerMinute": 0.6697196690431683, "wardTakedowns": 4, "wardTakedownsBefore20M": 3, "wardsGuarded": 0}, "champExperience": 12924, "champLevel": 14, "championId": 523, "championName": "Aphelios", "championTransform": 0, "commandPings": 16, "consumablesPurchased": 5, "damageDealtToBuildings": 10876, "damageDealtToObjectives": 24006, "damageDealtToTurrets": 10876, "damageSelfMitigated": 12153, "dangerPings": 0, "deaths": 1, "detectorWardsPlaced": 2, "doubleKills": 6, "dragonKills": 0, "eligibleForProgression": true, "enemyMissingPings": 3, "enemyVisionPings": 0, "firstBloodAssist": false, "firstBloodKill": false, "firstTowerAssist": false, "firstTowerKill": true, "gameEndedInEarlySurrender": false, "gameEndedInSurrender": true, "getBackPings": 8, "goldEarned": 16301, "goldSpent": 15450, "holdPings": 5, "individualPosition": "BOTTOM", "inhibitorKills": 1, "inhibitorTakedowns": 1, "inhibitorsLost": 0, "item0": 2421, "item1": 6673, "item2": 6671, "item3": 3006, "item4": 3072, "item5": 6672, "item6": 3363, "itemsPurchased": 26, "killingSprees": 2, "kills": 15, "lane": "BOTTOM", "largestCriticalStrike": 703, "largestKillingSpree": 11, "largestMultiKill": 3, "longestTimeSpentLiving": 1295, "magicDamageDealt": 2678, "magicDamageDealtToChampions": 432, "magicDamageTaken": 3500, "needVisionPings": 0, "neutralMinionsKilled": 14, "nexusKills": 0, "nexusLost": 0, "nexusTakedowns": 0, "objectivesStolen": 0, "objectivesStolenAssists": 0, "onMyWayPings": 34, "participantId": 9, "pentaKills": 0, "perks": {"statPerks": {"defense": 5002, "flex": 5008, "offense": 5005}, "styles": [{"description": "primaryStyle", "selections": [{"perk": 8010, "var1": 440, "var2": 0, "var3": 0}, {"perk": 9101, "var1": 2388, "var2": 3457, "var3": 0}, {"perk": 9103, "var1": 13, "var2": 30, "var3": 0}, {"perk": 8017, "var1": 1682, "var2": 0, "var3": 0}], "style": 8000}, {"description": "subStyle", "selections": [{"perk": 8233, "var1": 17, "var2": 50, "var3": 0}, {"perk": 8236, "var1": 14, "var2": 0, "var3": 0}], "style": 8200}]}, "physicalDamageDealt": 212571, "physicalDamageDealtToChampions": 34360, "physicalDamageTaken": 8903, "placement": 0, "playerAugment1": 0, "playerAugment2": 0, "playerAugment3": 0, "playerAugment4": 0, "playerSubteamId": 0, "profileIcon": 5272, "pushPings": 0, "puuid": "3MXueUlNBXkXMuaTmLwXNSt2-Fw8Od77SQ_RLEv1Vuxbj0GyJAxFMRqw6K0D2rO3bpNKBOh9OoPtdg", "quadraKills": 0, "riotIdName": "", "riotIdTagline": "", "role": "CARRY", "sightWardsBoughtInGame": 0, "spell1Casts": 107, "spell2Casts": 453, "spell3Casts": 0, "spell4Casts": 6, "subteamPlacement": 0, "summoner1Casts": 4, "summoner1Id": 1, "summoner2Casts": 3, "summoner2Id": 4, "summonerId": "ruMRMpuViTQ9_v-rrJEDJGCsHszeKnvEPHVx2DaEzdzKB_kwMxvqu3_DvQ", "summonerLevel": 575, "summonerName": "\ub3fc\uc9c0\ud06c\uba74\ub9d8\ubaa8\uc2a4", "teamEarlySurrendered": false, "teamId": 200, "teamPosition": "BOTTOM", "timeCCingOthers": 11, "timePlayed": 1587, "totalAllyJungleMinionsKilled": 8, "totalDamageDealt": 219117, "totalDamageDealtToChampions": 35214, "totalDamageShieldedOnTeammates": 0, "totalDamageTaken": 12608, "totalEnemyJungleMinionsKilled": 5, "totalHeal": 7034, "totalHealsOnTeammates": 0, "totalMinionsKilled": 213, "totalTimeCCDealt": 180, "totalTimeSpentDead": 42, "totalUnitsHealed": 1, "tripleKills": 1, "trueDamageDealt": 3867, "trueDamageDealtToChampions": 420, "trueDamageTaken": 204, "turretKills": 4, "turretTakedowns": 4, "turretsLost": 1, "unrealKills": 0, "visionClearedPings": 0, "visionScore": 17, "visionWardsBoughtInGame": 4, "wardsKilled": 4, "wardsPlaced": 6, "win": true}, {"allInPings": 0, "assistMePings": 0, "assists": 16, "baitPings": 1, "baronKills": 0, "basicPings": 0, "bountyLevel": 0, "challenges": {"12AssistStreakCount": 1, "abilityUses": 78, "acesBefore15Minutes": 0, "alliedJungleMonsterKills": 0, "baronBuffGoldAdvantageOverThreshold": 1, "baronTakedowns": 1, "blastConeOppositeOpponentCount": 0, "bountyGold": 0, "buffsStolen": 0, "completeSupportQuestInTime": 0, "controlWardTimeCoverageInRiverOrEnemyHalf": 0.8046477268852329, "controlWardsPlaced": 12, "damagePerMinute": 196.8412998771434, "damageTakenOnTeamPercentage": 0.16073890314387954, "dancedWithRiftHerald": 0, "deathsByEnemyChamps": 5, "dodgeSkillShotsSmallWindow": 1, "doubleAces": 0, "dragonTakedowns": 1, "earliestBaron": 1275.1103647999998, "earliestDragonTakedown": 1507.7112522999998, "earlyLaningPhaseGoldExpAdvantage": 0, "effectiveHealAndShielding": 1578.4923095703125, "elderDragonKillsWithOpposingSoul": 0, "elderDragonMultikills": 0, "enemyChampionImmobilizations": 41, "enemyJungleMonsterKills": 0, "epicMonsterKillsNearEnemyJungler": 0, "epicMonsterKillsWithin30SecondsOfSpawn": 0, "epicMonsterSteals": 0, "epicMonsterStolenWithoutSmite": 0, "firstTurretKilled": 1, "firstTurretKilledTime": 734.2218237999999, "flawlessAces": 0, "fullTeamTakedown": 0, "gameLength": 1587.4567035, "getTakedownsInAllLanesEarlyJungleAsLaner": 0, "goldPerMinute": 275.3306083612976, "hadOpenNexus": 0, "immobilizeAndKillWithAlly": 10, "initialBuffCount": 0, "initialCrabCount": 0, "jungleCsBefore10Minutes": 0, "junglerTakedownsNearDamagedEpicMonster": 0, "kTurretsDestroyedBeforePlatesFall": 0, "kda": 3.4, "killAfterHiddenWithAlly": 1, "killParticipation": 0.5483870967741935, "killedChampTookFullTeamDamageSurvived": 0, "killingSprees": 0, "killsNearEnemyTurret": 0, "killsOnOtherLanesEarlyJungleAsLaner": 0, "killsOnRecentlyHealedByAramPack": 0, "killsUnderOwnTurret": 0, "killsWithHelpFromEpicMonster": 0, "knockEnemyIntoTeamAndKill": 7, "landSkillShotsEarlyGame": 3, "laneMinionsFirst10Minutes": 15, "laningPhaseGoldExpAdvantage": 0, "legendaryCount": 0, "lostAnInhibitor": 0, "maxCsAdvantageOnLaneOpponent": 3, "maxKillDeficit": 2, "maxLevelLeadLaneOpponent": 1, "mejaisFullStackInTime": 0, "moreEnemyJungleThanOpponent": 0, "multiKillOneSpell": 0, "multiTurretRiftHeraldCount": 0, "multikills": 0, "multikillsAfterAggressiveFlash": 0, "mythicItemUsed": 3001, "outerTurretExecutesBefore10Minutes": 0, "outnumberedKills": 1, "outnumberedNexusKill": 0, "perfectDragonSoulsTaken": 0, "perfectGame": 0, "pickKillWithAlly": 10, "playedChampSelectPosition": 1, "poroExplosions": 0, "quickCleanse": 0, "quickFirstTurret": 0, "quickSoloKills": 0, "riftHeraldTakedowns": 1, "saveAllyFromDeath": 13, "scuttleCrabKills": 0, "skillshotsDodged": 12, "skillshotsHit": 12, "snowballsHit": 0, "soloBaronKills": 0, "soloKills": 0, "stealthWardsPlaced": 28, "survivedSingleDigitHpCount": 0, "survivedThreeImmobilizesInFight": 4, "takedownOnFirstTurret": 0, "takedowns": 17, "takedownsAfterGainingLevelAdvantage": 0, "takedownsBeforeJungleMinionSpawn": 0, "takedownsFirstXMinutes": 9, "takedownsInAlcove": 0, "takedownsInEnemyFountain": 0, "teamBaronKills": 1, "teamDamagePercentage": 0.05772361634727584, "teamElderDragonKills": 0, "teamRiftHeraldKills": 2, "tookLargeDamageSurvived": 0, "turretPlatesTaken": 0, "turretTakedowns": 0, "turretsTakenWithRiftHerald": 10, "twentyMinionsIn3SecondsCount": 0, "twoWardsOneSweeperCount": 0, "unseenRecalls": 0, "visionScoreAdvantageLaneOpponent": 1.021733283996582, "visionScorePerMinute": 2.740676294643073, "wardTakedowns": 5, "wardTakedownsBefore20M": 2, "wardsGuarded": 1}, "champExperience": 8409, "champLevel": 11, "championId": 412, "championName": "Thresh", "championTransform": 0, "commandPings": 9, "consumablesPurchased": 16, "damageDealtToBuildings": 0, "damageDealtToObjectives": 174, "damageDealtToTurrets": 0, "damageSelfMitigated": 10846, "dangerPings": 0, "deaths": 5, "detectorWardsPlaced": 12, "doubleKills": 0, "dragonKills": 0, "eligibleForProgression": true, "enemyMissingPings": 6, "enemyVisionPings": 9, "firstBloodAssist": false, "firstBloodKill": false, "firstTowerAssist": false, "firstTowerKill": false, "gameEndedInEarlySurrender": false, "gameEndedInSurrender": true, "getBackPings": 5, "goldEarned": 7284, "goldSpent": 7150, "holdPings": 0, "individualPosition": "UTILITY", "inhibitorKills": 0, "inhibitorTakedowns": 1, "inhibitorsLost": 0, "item0": 3857, "item1": 3001, "item2": 2055, "item3": 3158, "item4": 3109, "item5": 0, "item6": 3364, "itemsPurchased": 31, "killingSprees": 0, "kills": 1, "lane": "BOTTOM", "largestCriticalStrike": 0, "largestKillingSpree": 0, "largestMultiKill": 1, "longestTimeSpentLiving": 448, "magicDamageDealt": 6680, "magicDamageDealtToChampions": 3925, "magicDamageTaken": 4505, "needVisionPings": 1, "neutralMinionsKilled": 0, "nexusKills": 0, "nexusLost": 0, "nexusTakedowns": 0, "objectivesStolen": 0, "objectivesStolenAssists": 0, "onMyWayPings": 9, "participantId": 10, "pentaKills": 0, "perks": {"statPerks": {"defense": 5002, "flex": 5003, "offense": 5008}, "styles": [{"description": "primaryStyle", "selections": [{"perk": 8439, "var1": 216, "var2": 479, "var3": 0}, {"perk": 8463, "var1": 1215, "var2": 0, "var3": 0}, {"perk": 8473, "var1": 195, "var2": 0, "var3": 0}, {"perk": 8242, "var1": 42, "var2": 0, "var3": 0}], "style": 8400}, {"description": "subStyle", "selections": [{"perk": 8306, "var1": 4, "var2": 0, "var3": 0}, {"perk": 8347, "var1": 0, "var2": 0, "var3": 0}], "style": 8300}]}, "physicalDamageDealt": 3790, "physicalDamageDealtToChampions": 645, "physicalDamageTaken": 8079, "placement": 0, "playerAugment1": 0, "playerAugment2": 0, "playerAugment3": 0, "playerAugment4": 0, "playerSubteamId": 0, "profileIcon": 5488, "pushPings": 0, "puuid": "NEYzqWWYEIMj7OrevLo8kOfaNc24vI_9yfpWKLpW4Bv78NeR4lnCH1N-GGi599EsAN4PnXNWMI9_PA", "quadraKills": 0, "riotIdName": "", "riotIdTagline": "", "role": "SUPPORT", "sightWardsBoughtInGame": 0, "spell1Casts": 29, "spell2Casts": 30, "spell3Casts": 14, "spell4Casts": 5, "subteamPlacement": 0, "summoner1Casts": 7, "summoner1Id": 4, "summoner2Casts": 5, "summoner2Id": 14, "summonerId": "1UyBfLNu_MWreJJh67H-10VW2n_fdPmYSn889yIyp1SgJzY", "summonerLevel": 311, "summonerName": "\ubcf8\ucc44 \ub9cc\uccb4", "teamEarlySurrendered": false, "teamId": 200, "teamPosition": "UTILITY", "timeCCingOthers": 24, "timePlayed": 1587, "totalAllyJungleMinionsKilled": 0, "totalDamageDealt": 15366, "totalDamageDealtToChampions": 5207, "totalDamageShieldedOnTeammates": 1113, "totalDamageTaken": 12628, "totalEnemyJungleMinionsKilled": 0, "totalHeal": 848, "totalHealsOnTeammates": 464, "totalMinionsKilled": 30, "totalTimeCCDealt": 57, "totalTimeSpentDead": 68, "totalUnitsHealed": 5, "tripleKills": 0, "trueDamageDealt": 4895, "trueDamageDealtToChampions": 636, "trueDamageTaken": 44, "turretKills": 0, "turretTakedowns": 0, "turretsLost": 1, "unrealKills": 0, "visionClearedPings": 0, "visionScore": 72, "visionWardsBoughtInGame": 14, "wardsKilled": 5, "wardsPlaced": 40, "win": true}], "platformId": "KR", "queueId": 420, "teams": [{"bans": [{"championId": 18, "pickTurn": 1}, {"championId": 518, "pickTurn": 2}, {"championId": 526, "pickTurn": 3}, {"championId": 7, "pickTurn": 4}, {"championId": 39, "pickTurn": 5}], "objectives": {"baron": {"first": false, "kills": 0}, "champion": {"first": true, "kills": 17}, "dragon": {"first": false, "kills": 1}, "inhibitor": {"first": false, "kills": 0}, "riftHerald": {"first": false, "kills": 0}, "tower": {"first": false, "kills": 1}}, "teamId": 100, "win": false}, {"bans": [{"championId": 119, "pickTurn": 6}, {"championId": 950, "pickTurn": 7}, {"championId": 114, "pickTurn": 8}, {"championId": 91, "pickTurn": 9}, {"championId": 81, "pickTurn": 10}], "objectives": {"baron": {"first": true, "kills": 1}, "champion": {"first": false, "kills": 31}, "dragon": {"first": true, "kills": 3}, "inhibitor": {"first": true, "kills": 1}, "riftHerald": {"first": true, "kills": 2}, "tower": {"first": true, "kills": 7}}, "teamId": 200, "win": true}], "tournamentCode": ""}}