{"metadata": {"dataVersion": "2", "matchId": "KR_6603220229", "participants": ["DvzDiWEB1JkBWAKV1w6sW2-rc2X8RAr5AUpIPICAhIHUgT2fJjvyAe8yl_LT6RZVPQK7w5uK-O5p6A", "LYy-fFjgtjA_qUP8qqesy4Xrq48SfTUR84V42R61RwFwydiUK5LeRLjRQ_SfaGOaSfDzCYmNdRMLPQ", "N45Z1YqIKz7nSzK1nDU5CjWvwSHIx05rBKBwEmt9DROEfkLgdkhheThH7QZ_Cwps2L8saRzqhtbdbg", "n6UlmuWVow8qS4255iyg7y7cqAHZe4JJT9o5EONa5J5O1mf2Ct5qHyA8G2WuORwz01yB0op7LwoVuw", "3qgg1SNPYTbh4gbEJZjjzGrahLOWxunug9lL6L447HmMoyQIp_oei26Jsg8irEJ27pakpEaOCYAcDw", "Se0nhBylutdQG_zcmHMUvgc_P-PdBGC-VaQILyhKWcLaMwQ3tF3Ax_HwpfkCFUpHPysqp8zt9LVkpQ", "3eh8U-42rwY5jw7o0dJpcfa67gUiUMToI1Ns12o2a7Nr2_P1YROOmsxtn5F3SEldTSjrVQR2cDch0g", "u2T4Y6r2-llySjrkM6o-WCsDGBWCeNL7UkD71vBOh9SlNjDjiH28gcPt2AlMm_8fmhjBWWFayCirvw", "_uo1JZcYEFP8MPoR9RHGYEW-uGi4dduu7BhopwGdi6lO_qctGGAmqg7REjCLsQJDSbbgRcpGurs9lA", "smMrpOc9vfIyklOx1iSIzPDcz2eeZfu6yL0z0PTpy4JwJBWMCKvaVgP8lOYs6FcRCzMNwZ9mFWpO_g"]}, "info": {"gameCreation": 1689850003311, "gameDuration": 1691, "gameEndTimestamp": 1689851738379, "gameId": 6603220229, "gameMode": "CLASSIC", "gameName": "teambuilder-match-6603220229", "gameStartTimestamp": 1689850046664, "gameType": "MATCHED_GAME", "gameVersion": "13.14.520.6878", "mapId": 11, "participants": [{"allInPings": 1, "assistMePings": 1, "assists": 14, "baitPings": 0, "baronKills": 0, "basicPings": 0, "bountyLevel": 0, "challenges": {"12AssistStreakCount": 0, "abilityUses": 397, "acesBefore15Minutes": 0, "alliedJungleMonsterKills": 3, "baronTakedowns": 1, "blastConeOppositeOpponentCount": 0, "bountyGold": 0, "buffsStolen": 0, "completeSupportQuestInTime": 0, "controlWardTimeCoverageInRiverOrEnemyHalf": 0.33039485297395277, "controlWardsPlaced": 3, "damagePerMinute": 802.5858905752294, "damageTakenOnTeamPercentage": 0.17970465088692153, "dancedWithRiftHerald": 0, "deathsByEnemyChamps": 4, "dodgeSkillShotsSmallWindow": 0, "doubleAces": 0, "dragonTakedowns": 0, "earliestBaron": 1314.4455773, "earlyLaningPhaseGoldExpAdvantage": 0, "effectiveHealAndShielding": 0, "elderDragonKillsWithOpposingSoul": 0, "elderDragonMultikills": 0, "enemyChampionImmobilizations": 28, "enemyJungleMonsterKills": 6, "epicMonsterKillsNearEnemyJungler": 0, "epicMonsterKillsWithin30SecondsOfSpawn": 0, "epicMonsterSteals": 0, "epicMonsterStolenWithoutSmite": 0, "firstTurretKilled": 0, "flawlessAces": 1, "fullTeamTakedown": 1, "gameLength": 1691.8844863, "getTakedownsInAllLanesEarlyJungleAsLaner": 0, "goldPerMinute": 475.90152677449373, "hadOpenNexus": 0, "immobilizeAndKillWithAlly": 11, "initialBuffCount": 0, "initialCrabCount": 0, "jungleCsBefore10Minutes": 0, "junglerTakedownsNearDamagedEpicMonster": 0, "kTurretsDestroyedBeforePlatesFall": 0, "kda": 4.75, "killAfterHiddenWithAlly": 0, "killParticipation": 0.5135135135135135, "killedChampTookFullTeamDamageSurvived": 0, "killingSprees": 1, "killsNearEnemyTurret": 0, "killsOnOtherLanesEarlyJungleAsLaner": 1, "killsOnRecentlyHealedByAramPack": 0, "killsUnderOwnTurret": 1, "killsWithHelpFromEpicMonster": 0, "knockEnemyIntoTeamAndKill": 0, "landSkillShotsEarlyGame": 1, "laneMinionsFirst10Minutes": 61, "laningPhaseGoldExpAdvantage": 0, "legendaryCount": 0, "lostAnInhibitor": 0, "maxCsAdvantageOnLaneOpponent": 2, "maxKillDeficit": 1, "maxLevelLeadLaneOpponent": 0, "mejaisFullStackInTime": 0, "moreEnemyJungleThanOpponent": 0, "multiKillOneSpell": 0, "multiTurretRiftHeraldCount": 0, "multikills": 1, "multikillsAfterAggressiveFlash": 0, "mythicItemUsed": 6671, "outerTurretExecutesBefore10Minutes": 0, "outnumberedKills": 0, "outnumberedNexusKill": 0, "perfectDragonSoulsTaken": 1, "perfectGame": 0, "pickKillWithAlly": 14, "playedChampSelectPosition": 1, "poroExplosions": 0, "quickCleanse": 0, "quickFirstTurret": 0, "quickSoloKills": 0, "riftHeraldTakedowns": 1, "saveAllyFromDeath": 0, "scuttleCrabKills": 0, "shortestTimeToAceFromFirstTakedown": 27.926360799999884, "skillshotsDodged": 5, "skillshotsHit": 10, "snowballsHit": 0, "soloBaronKills": 0, "soloKills": 0, "soloTurretsLategame": 1, "stealthWardsPlaced": 4, "survivedSingleDigitHpCount": 0, "survivedThreeImmobilizesInFight": 0, "takedownOnFirstTurret": 0, "takedowns": 19, "takedownsAfterGainingLevelAdvantage": 0, "takedownsBeforeJungleMinionSpawn": 0, "takedownsFirstXMinutes": 3, "takedownsInAlcove": 0, "takedownsInEnemyFountain": 0, "teamBaronKills": 1, "teamDamagePercentage": 0.2256778472644846, "teamElderDragonKills": 0, "teamRiftHeraldKills": 1, "teleportTakedowns": 2, "tookLargeDamageSurvived": 0, "turretPlatesTaken": 2, "turretTakedowns": 6, "turretsTakenWithRiftHerald": 0, "twentyMinionsIn3SecondsCount": 8, "twoWardsOneSweeperCount": 0, "unseenRecalls": 0, "visionScoreAdvantageLaneOpponent": 0.06715083122253418, "visionScorePerMinute": 0.7816443187321639, "wardTakedowns": 4, "wardTakedownsBefore20M": 3, "wardsGuarded": 1}, "champExperience": 15326, "champLevel": 16, "championId": 777, "championName": "Yone", "championTransform": 0, "commandPings": 8, "consumablesPurchased": 7, "damageDealtToBuildings": 8365, "damageDealtToObjectives": 12657, "damageDealtToTurrets": 8365, "damageSelfMitigated": 19213, "dangerPings": 0, "deaths": 4, "detectorWardsPlaced": 4, "doubleKills": 1, "dragonKills": 0, "eligibleForProgression": true, "enemyMissingPings": 3, "enemyVisionPings": 0, "firstBloodAssist": false, "firstBloodKill": false, "firstTowerAssist": false, "firstTowerKill": false, "gameEndedInEarlySurrender": false, "gameEndedInSurrender": false, "getBackPings": 0, "goldEarned": 13419, "goldSpent": 11750, "holdPings": 0, "individualPosition": "TOP", "inhibitorKills": 1, "inhibitorTakedowns": 2, "inhibitorsLost": 0, "item0": 3072, "item1": 6671, "item2": 6672, "item3": 0, "item4": 3006, "item5": 0, "item6": 3363, "itemsPurchased": 27, "killingSprees": 1, "kills": 5, "lane": "TOP", "largestCriticalStrike": 540, "largestKillingSpree": 4, "largestMultiKill": 2, "longestTimeSpentLiving": 839, "magicDamageDealt": 23075, "magicDamageDealtToChampions": 4088, "magicDamageTaken": 2945, "needVisionPings": 0, "neutralMinionsKilled": 8, "nexusKills": 0, "nexusLost": 0, "nexusTakedowns": 1, "objectivesStolen": 0, "objectivesStolenAssists": 0, "onMyWayPings": 17, "participantId": 1, "pentaKills": 0, "perks": {"statPerks": {"defense": 5002, "flex": 5008, "offense": 5005}, "styles": [{"description": "primaryStyle", "selections": [{"perk": 8008, "var1": 21, "var2": 1, "var3": 0}, {"perk": 9111, "var1": 1259, "var2": 380, "var3": 0}, {"perk": 9104, "var1": 16, "var2": 10, "var3": 0}, {"perk": 8299, "var1": 436, "var2": 0, "var3": 0}], "style": 8000}, {"description": "subStyle", "selections": [{"perk": 8446, "var1": 3147, "var2": 0, "var3": 0}, {"perk": 8473, "var1": 1017, "var2": 0, "var3": 0}], "style": 8400}]}, "physicalDamageDealt": 143066, "physicalDamageDealtToChampions": 16073, "physicalDamageTaken": 14623, "placement": 0, "playerAugment1": 0, "playerAugment2": 0, "playerAugment3": 0, "playerAugment4": 0, "playerSubteamId": 0, "profileIcon": 5719, "pushPings": 0, "puuid": "DvzDiWEB1JkBWAKV1w6sW2-rc2X8RAr5AUpIPICAhIHUgT2fJjvyAe8yl_LT6RZVPQK7w5uK-O5p6A", "quadraKills": 0, "riotIdName": "", "riotIdTagline": "", "role": "SOLO", "sightWardsBoughtInGame": 0, "spell1Casts": 226, "spell2Casts": 77, "spell3Casts": 84, "spell4Casts": 10, "subteamPlacement": 0, "summoner1Casts": 4, "summoner1Id": 12, "summoner2Casts": 4, "summoner2Id": 4, "summonerId": "1OdMDQh_ClkBNJ29l9SKiHAvjR21Aw5WNwVuJ2wh76c2p6u0qOvIWUUOdg", "summonerLevel": 55, "summonerName": "\uc778\uc0dd\uc758 \uae68\ub2ec\uc74c", "teamEarlySurrendered": false, "teamId": 100, "teamPosition": "TOP", "timeCCingOthers": 19, "timePlayed": 1691, "totalAllyJungleMinionsKilled": 4, "totalDamageDealt": 168944, "totalDamageDealtToChampions": 22631, "totalDamageShieldedOnTeammates": 0, "totalDamageTaken": 18131, "totalEnemyJungleMinionsKilled": 4, "totalHeal": 4754, "totalHealsOnTeammates": 0, "totalMinionsKilled": 183, "totalTimeCCDealt": 156, "totalTimeSpentDead": 122, "totalUnitsHealed": 1, "tripleKills": 0, "trueDamageDealt": 2802, "trueDamageDealtToChampions": 2468, "trueDamageTaken": 562, "turretKills": 4, "turretTakedowns": 6, "turretsLost": 4, "unrealKills": 0, "visionClearedPings": 0, "visionScore": 22, "visionWardsBoughtInGame": 5, "wardsKilled": 4, "wardsPlaced": 12, "win": true}, {"allInPings": 0, "assistMePings": 11, "assists": 11, "baitPings": 0, "baronKills": 1, "basicPings": 0, "bountyLevel": 2, "challenges": {"12AssistStreakCount": 0, "abilityUses": 507, "acesBefore15Minutes": 0, "alliedJungleMonsterKills": 70, "baronTakedowns": 1, "blastConeOppositeOpponentCount": 0, "bountyGold": 0, "buffsStolen": 2, "completeSupportQuestInTime": 0, "controlWardTimeCoverageInRiverOrEnemyHalf": 0.6199877210848801, "controlWardsPlaced": 7, "damagePerMinute": 696.4652258940097, "damageTakenOnTeamPercentage": 0.258863117648735, "dancedWithRiftHerald": 0, "deathsByEnemyChamps": 2, "dodgeSkillShotsSmallWindow": 1, "doubleAces": 0, "dragonTakedowns": 4, "earliestBaron": 1314.4455773, "earliestDragonTakedown": 535.3205105999999, "earlyLaningPhaseGoldExpAdvantage": 0, "effectiveHealAndShielding": 102.88645935058594, "elderDragonKillsWithOpposingSoul": 0, "elderDragonMultikills": 0, "enemyChampionImmobilizations": 25, "enemyJungleMonsterKills": 5, "epicMonsterKillsNearEnemyJungler": 1, "epicMonsterKillsWithin30SecondsOfSpawn": 1, "epicMonsterSteals": 0, "epicMonsterStolenWithoutSmite": 0, "firstTurretKilled": 0, "flawlessAces": 1, "fullTeamTakedown": 1, "gameLength": 1691.8844863, "goldPerMinute": 475.2432025196353, "hadOpenNexus": 0, "immobilizeAndKillWithAlly": 13, "initialBuffCount": 3, "initialCrabCount": 1, "jungleCsBefore10Minutes": 64.00000005960464, "junglerKillsEarlyJungle": 0, "junglerTakedownsNearDamagedEpicMonster": 1, "kTurretsDestroyedBeforePlatesFall": 0, "kda": 10.5, "killAfterHiddenWithAlly": 1, "killParticipation": 0.5675675675675675, "killedChampTookFullTeamDamageSurvived": 0, "killingSprees": 1, "killsNearEnemyTurret": 4, "killsOnLanersEarlyJungleAsJungler": 3, "killsOnRecentlyHealedByAramPack": 0, "killsUnderOwnTurret": 1, "killsWithHelpFromEpicMonster": 0, "knockEnemyIntoTeamAndKill": 0, "landSkillShotsEarlyGame": 5, "laneMinionsFirst10Minutes": 1, "laningPhaseGoldExpAdvantage": 1, "legendaryCount": 0, "lostAnInhibitor": 0, "maxCsAdvantageOnLaneOpponent": 42.650000005960464, "maxKillDeficit": 1, "maxLevelLeadLaneOpponent": 3, "mejaisFullStackInTime": 0, "moreEnemyJungleThanOpponent": -37.00000008940697, "multiKillOneSpell": 0, "multiTurretRiftHeraldCount": 0, "multikills": 2, "multikillsAfterAggressiveFlash": 0, "mythicItemUsed": 6632, "outerTurretExecutesBefore10Minutes": 0, "outnumberedKills": 2, "outnumberedNexusKill": 0, "perfectDragonSoulsTaken": 1, "perfectGame": 0, "pickKillWithAlly": 16, "playedChampSelectPosition": 1, "poroExplosions": 0, "quickCleanse": 0, "quickFirstTurret": 0, "quickSoloKills": 0, "riftHeraldTakedowns": 1, "saveAllyFromDeath": 0, "scuttleCrabKills": 5, "shortestTimeToAceFromFirstTakedown": 27.926360799999884, "skillshotsDodged": 11, "skillshotsHit": 28, "snowballsHit": 0, "soloBaronKills": 0, "soloKills": 0, "stealthWardsPlaced": 2, "survivedSingleDigitHpCount": 0, "survivedThreeImmobilizesInFight": 8, "takedownOnFirstTurret": 0, "takedowns": 21, "takedownsAfterGainingLevelAdvantage": 0, "takedownsBeforeJungleMinionSpawn": 0, "takedownsFirstXMinutes": 13, "takedownsInAlcove": 1, "takedownsInEnemyFountain": 0, "teamBaronKills": 1, "teamDamagePercentage": 0.19583794671705645, "teamElderDragonKills": 0, "teamRiftHeraldKills": 1, "tookLargeDamageSurvived": 0, "turretPlatesTaken": 1, "turretTakedowns": 2, "turretsTakenWithRiftHerald": 0, "twentyMinionsIn3SecondsCount": 1, "twoWardsOneSweeperCount": 0, "unseenRecalls": 0, "visionScoreAdvantageLaneOpponent": 0.5765174627304077, "visionScorePerMinute": 1.5682986780319592, "wardTakedowns": 8, "wardTakedownsBefore20M": 5, "wardsGuarded": 1}, "champExperience": 15211, "champLevel": 16, "championId": 234, "championName": "Viego", "championTransform": 0, "commandPings": 6, "consumablesPurchased": 9, "damageDealtToBuildings": 936, "damageDealtToObjectives": 45160, "damageDealtToTurrets": 936, "damageSelfMitigated": 27996, "dangerPings": 0, "deaths": 2, "detectorWardsPlaced": 7, "doubleKills": 2, "dragonKills": 4, "eligibleForProgression": true, "enemyMissingPings": 1, "enemyVisionPings": 2, "firstBloodAssist": true, "firstBloodKill": false, "firstTowerAssist": false, "firstTowerKill": false, "gameEndedInEarlySurrender": false, "gameEndedInSurrender": false, "getBackPings": 11, "goldEarned": 13400, "goldSpent": 11300, "holdPings": 1, "individualPosition": "JUNGLE", "inhibitorKills": 0, "inhibitorTakedowns": 2, "inhibitorsLost": 0, "item0": 3071, "item1": 2055, "item2": 3047, "item3": 3026, "item4": 6632, "item5": 0, "item6": 3364, "itemsPurchased": 22, "killingSprees": 2, "kills": 10, "lane": "JUNGLE", "largestCriticalStrike": 557, "largestKillingSpree": 7, "largestMultiKill": 2, "longestTimeSpentLiving": 1158, "magicDamageDealt": 7815, "magicDamageDealtToChampions": 1847, "magicDamageTaken": 4072, "needVisionPings": 0, "neutralMinionsKilled": 155, "nexusKills": 0, "nexusLost": 0, "nexusTakedowns": 1, "objectivesStolen": 0, "objectivesStolenAssists": 0, "onMyWayPings": 32, "participantId": 2, "pentaKills": 0, "perks": {"statPerks": {"defense": 5002, "flex": 5008, "offense": 5005}, "styles": [{"description": "primaryStyle", "selections": [{"perk": 8010, "var1": 429, "var2": 0, "var3": 0}, {"perk": 9111, "var1": 1011, "var2": 420, "var3": 0}, {"perk": 9104, "var1": 8, "var2": 20, "var3": 0}, {"perk": 8014, "var1": 569, "var2": 0, "var3": 0}], "style": 8000}, {"description": "subStyle", "selections": [{"perk": 8304, "var1": 7, "var2": 3, "var3": 0}, {"perk": 8347, "var1": 0, "var2": 0, "var3": 0}], "style": 8300}]}, "physicalDamageDealt": 183626, "physicalDamageDealtToChampions": 16502, "physicalDamageTaken": 21124, "placement": 0, "playerAugment1": 0, "playerAugment2": 0, "playerAugment3": 0, "playerAugment4": 0, "playerSubteamId": 0, "profileIcon": 22, "pushPings": 1, "puuid": "LYy-fFjgtjA_qUP8qqesy4Xrq48SfTUR84V42R61RwFwydiUK5LeRLjRQ_SfaGOaSfDzCYmNdRMLPQ", "quadraKills": 0, "riotIdName": "", "riotIdTagline": "", "role": "NONE", "sightWardsBoughtInGame": 0, "spell1Casts": 226, "spell2Casts": 178, "spell3Casts": 83, "spell4Casts": 20, "subteamPlacement": 0, "summoner1Casts": 19, "summoner1Id": 11, "summoner2Casts": 4, "summoner2Id": 4, "summonerId": "BoqewSc7wvI_8pgDIG-Jns_vxozZDmXt-IvolzbgIYN7MRo", "summonerLevel": 604, "summonerName": "T1 \ud3ec\ub808\uc2a4\ud2b8", "teamEarlySurrendered": false, "teamId": 100, "teamPosition": "JUNGLE", "timeCCingOthers": 24, "timePlayed": 1691, "totalAllyJungleMinionsKilled": 86, "totalDamageDealt": 230197, "totalDamageDealtToChampions": 19638, "totalDamageShieldedOnTeammates": 102, "totalDamageTaken": 26118, "totalEnemyJungleMinionsKilled": 18, "totalHeal": 16072, "totalHealsOnTeammates": 0, "totalMinionsKilled": 45, "totalTimeCCDealt": 286, "totalTimeSpentDead": 84, "totalUnitsHealed": 1, "tripleKills": 0, "trueDamageDealt": 38755, "trueDamageDealtToChampions": 1288, "trueDamageTaken": 921, "turretKills": 1, "turretTakedowns": 2, "turretsLost": 4, "unrealKills": 0, "visionClearedPings": 0, "visionScore": 44, "visionWardsBoughtInGame": 18, "wardsKilled": 8, "wardsPlaced": 9, "win": true}, {"allInPings": 0, "assistMePings": 4, "assists": 16, "baitPings": 0, "baronKills": 0, "basicPings": 0, "bountyLevel": 2, "challenges": {"12AssistStreakCount": 0, "abilityUses": 280, "acesBefore15Minutes": 0, "alliedJungleMonsterKills": 7, "baronTakedowns": 0, "blastConeOppositeOpponentCount": 0, "bountyGold": 0, "buffsStolen": 0, "completeSupportQuestInTime": 0, "controlWardTimeCoverageInRiverOrEnemyHalf": 0.8208684048148068, "controlWardsPlaced": 3, "damagePerMinute": 850.4418976449363, "damageTakenOnTeamPercentage": 0.21390022860622368, "dancedWithRiftHerald": 0, "deathsByEnemyChamps": 5, "dodgeSkillShotsSmallWindow": 2, "doubleAces": 0, "dragonTakedowns": 0, "earliestBaron": 1314.4455773, "earlyLaningPhaseGoldExpAdvantage": 0, "effectiveHealAndShielding": 0, "elderDragonKillsWithOpposingSoul": 0, "elderDragonMultikills": 0, "enemyChampionImmobilizations": 46, "enemyJungleMonsterKills": 0, "epicMonsterKillsNearEnemyJungler": 0, "epicMonsterKillsWithin30SecondsOfSpawn": 0, "epicMonsterSteals": 0, "epicMonsterStolenWithoutSmite": 0, "firstTurretKilled": 0, "flawlessAces": 1, "fullTeamTakedown": 1, "gameLength": 1691.8844863, "getTakedownsInAllLanesEarlyJungleAsLaner": 0, "goldPerMinute": 431.69544613667637, "hadOpenNexus": 0, "highestCrowdControlScore": 1, "immobilizeAndKillWithAlly": 15, "initialBuffCount": 0, "initialCrabCount": 0, "jungleCsBefore10Minutes": 0, "junglerTakedownsNearDamagedEpicMonster": 0, "kTurretsDestroyedBeforePlatesFall": 0, "kda": 4.4, "killAfterHiddenWithAlly": 2, "killParticipation": 0.5945945945945946, "killedChampTookFullTeamDamageSurvived": 0, "killingSprees": 0, "killsNearEnemyTurret": 2, "killsOnOtherLanesEarlyJungleAsLaner": 1, "killsOnRecentlyHealedByAramPack": 0, "killsUnderOwnTurret": 0, "killsWithHelpFromEpicMonster": 0, "knockEnemyIntoTeamAndKill": 0, "landSkillShotsEarlyGame": 7, "laneMinionsFirst10Minutes": 88, "laningPhaseGoldExpAdvantage": 1, "legendaryCount": 0, "lostAnInhibitor": 0, "maxCsAdvantageOnLaneOpponent": 74.00000002980232, "maxKillDeficit": 1, "maxLevelLeadLaneOpponent": 3, "mejaisFullStackInTime": 0, "moreEnemyJungleThanOpponent": 0, "multiKillOneSpell": 0, "multiTurretRiftHeraldCount": 0, "multikills": 0, "multikillsAfterAggressiveFlash": 0, "mythicItemUsed": 6656, "outerTurretExecutesBefore10Minutes": 0, "outnumberedKills": 1, "outnumberedNexusKill": 0, "perfectDragonSoulsTaken": 1, "perfectGame": 0, "pickKillWithAlly": 15, "playedChampSelectPosition": 1, "poroExplosions": 0, "quickCleanse": 0, "quickFirstTurret": 0, "quickSoloKills": 0, "riftHeraldTakedowns": 0, "saveAllyFromDeath": 0, "scuttleCrabKills": 0, "skillshotsDodged": 18, "skillshotsHit": 46, "snowballsHit": 0, "soloBaronKills": 0, "soloKills": 1, "stealthWardsPlaced": 2, "survivedSingleDigitHpCount": 0, "survivedThreeImmobilizesInFight": 4, "takedownOnFirstTurret": 0, "takedowns": 22, "takedownsAfterGainingLevelAdvantage": 0, "takedownsBeforeJungleMinionSpawn": 0, "takedownsFirstXMinutes": 8, "takedownsInAlcove": 0, "takedownsInEnemyFountain": 0, "teamBaronKills": 1, "teamDamagePercentage": 0.2391344016108671, "teamElderDragonKills": 0, "teamRiftHeraldKills": 1, "teleportTakedowns": 2, "tookLargeDamageSurvived": 0, "turretPlatesTaken": 2, "turretTakedowns": 0, "turretsTakenWithRiftHerald": 0, "twentyMinionsIn3SecondsCount": 10, "twoWardsOneSweeperCount": 0, "unseenRecalls": 0, "visionScoreAdvantageLaneOpponent": 0.002117156982421875, "visionScorePerMinute": 1.2436920430171272, "wardTakedowns": 10, "wardTakedownsBefore20M": 5, "wardsGuarded": 1}, "champExperience": 14847, "champLevel": 16, "championId": 127, "championName": "Lissandra", "championTransform": 0, "commandPings": 9, "consumablesPurchased": 4, "damageDealtToBuildings": 866, "damageDealtToObjectives": 917, "damageDealtToTurrets": 866, "damageSelfMitigated": 13195, "dangerPings": 0, "deaths": 5, "detectorWardsPlaced": 3, "doubleKills": 0, "dragonKills": 0, "eligibleForProgression": true, "enemyMissingPings": 6, "enemyVisionPings": 0, "firstBloodAssist": false, "firstBloodKill": false, "firstTowerAssist": false, "firstTowerKill": false, "gameEndedInEarlySurrender": false, "gameEndedInSurrender": false, "getBackPings": 0, "goldEarned": 12172, "goldSpent": 10800, "holdPings": 0, "individualPosition": "MIDDLE", "inhibitorKills": 0, "inhibitorTakedowns": 1, "inhibitorsLost": 0, "item0": 1058, "item1": 6656, "item2": 2421, "item3": 3158, "item4": 3108, "item5": 4645, "item6": 3364, "itemsPurchased": 19, "killingSprees": 2, "kills": 6, "lane": "MIDDLE", "largestCriticalStrike": 0, "largestKillingSpree": 2, "largestMultiKill": 1, "longestTimeSpentLiving": 548, "magicDamageDealt": 141770, "magicDamageDealtToChampions": 22200, "magicDamageTaken": 3948, "needVisionPings": 0, "neutralMinionsKilled": 8, "nexusKills": 0, "nexusLost": 0, "nexusTakedowns": 1, "objectivesStolen": 0, "objectivesStolenAssists": 0, "onMyWayPings": 36, "participantId": 3, "pentaKills": 0, "perks": {"statPerks": {"defense": 5003, "flex": 5008, "offense": 5005}, "styles": [{"description": "primaryStyle", "selections": [{"perk": 8112, "var1": 1632, "var2": 0, "var3": 0}, {"perk": 8139, "var1": 845, "var2": 0, "var3": 0}, {"perk": 8138, "var1": 30, "var2": 0, "var3": 0}, {"perk": 8106, "var1": 5, "var2": 0, "var3": 0}], "style": 8100}, {"description": "subStyle", "selections": [{"perk": 8352, "var1": 321, "var2": 686, "var3": 720}, {"perk": 8316, "var1": 4695, "var2": 0, "var3": 0}], "style": 8300}]}, "physicalDamageDealt": 10679, "physicalDamageDealtToChampions": 1779, "physicalDamageTaken": 16207, "placement": 0, "playerAugment1": 0, "playerAugment2": 0, "playerAugment3": 0, "playerAugment4": 0, "playerSubteamId": 0, "profileIcon": 5333, "pushPings": 0, "puuid": "N45Z1YqIKz7nSzK1nDU5CjWvwSHIx05rBKBwEmt9DROEfkLgdkhheThH7QZ_Cwps2L8saRzqhtbdbg", "quadraKills": 0, "riotIdName": "", "riotIdTagline": "", "role": "SOLO", "sightWardsBoughtInGame": 0, "spell1Casts": 136, "spell2Casts": 56, "spell3Casts": 73, "spell4Casts": 15, "subteamPlacement": 0, "summoner1Casts": 5, "summoner1Id": 4, "summoner2Casts": 5, "summoner2Id": 12, "summonerId": "2NOXRDvxr9hYqq9dJE1BXUBzWPkxtuuGX93CTb9T3UkGAq0HaP76opU8oA", "summonerLevel": 105, "summonerName": "404mobsharenfan1", "teamEarlySurrendered": false, "teamId": 100, "teamPosition": "MIDDLE", "timeCCingOthers": 58, "timePlayed": 1691, "totalAllyJungleMinionsKilled": 8, "totalDamageDealt": 153972, "totalDamageDealtToChampions": 23980, "totalDamageShieldedOnTeammates": 0, "totalDamageTaken": 21581, "totalEnemyJungleMinionsKilled": 0, "totalHeal": 4320, "totalHealsOnTeammates": 0, "totalMinionsKilled": 217, "totalTimeCCDealt": 628, "totalTimeSpentDead": 176, "totalUnitsHealed": 1, "tripleKills": 0, "trueDamageDealt": 1522, "trueDamageDealtToChampions": 0, "trueDamageTaken": 1425, "turretKills": 0, "turretTakedowns": 0, "turretsLost": 4, "unrealKills": 0, "visionClearedPings": 0, "visionScore": 35, "visionWardsBoughtInGame": 4, "wardsKilled": 10, "wardsPlaced": 5, "win": true}, {"allInPings": 0, "assistMePings": 3, "assists": 7, "baitPings": 0, "baronKills": 0, "basicPings": 0, "bountyLevel": 5, "challenges": {"12AssistStreakCount": 0, "abilityUses": 240, "acesBefore15Minutes": 0, "alliedJungleMonsterKills": 0, "baronTakedowns": 1, "blastConeOppositeOpponentCount": 0, "bountyGold": 0, "buffsStolen": 1, "completeSupportQuestInTime": 0, "controlWardsPlaced": 1, "damagePerMinute": 941.019682167707, "damageTakenOnTeamPercentage": 0.17203861094386091, "dancedWithRiftHerald": 0, "deathsByEnemyChamps": 2, "dodgeSkillShotsSmallWindow": 3, "doubleAces": 0, "dragonTakedowns": 2, "earliestBaron": 1314.4455773, "earliestDragonTakedown": 1231.6421257, "earlyLaningPhaseGoldExpAdvantage": 1, "effectiveHealAndShielding": 116.759765625, "elderDragonKillsWithOpposingSoul": 0, "elderDragonMultikills": 0, "enemyChampionImmobilizations": 0, "enemyJungleMonsterKills": 1, "epicMonsterKillsNearEnemyJungler": 0, "epicMonsterKillsWithin30SecondsOfSpawn": 0, "epicMonsterSteals": 0, "epicMonsterStolenWithoutSmite": 0, "firstTurretKilled": 0, "flawlessAces": 1, "fullTeamTakedown": 1, "gameLength": 1691.8844863, "getTakedownsInAllLanesEarlyJungleAsLaner": 0, "goldPerMinute": 584.57462219417, "hadOpenNexus": 0, "highestChampionDamage": 1, "immobilizeAndKillWithAlly": 0, "initialBuffCount": 0, "initialCrabCount": 0, "jungleCsBefore10Minutes": 0, "junglerTakedownsNearDamagedEpicMonster": 0, "kTurretsDestroyedBeforePlatesFall": 1, "kda": 10, "killAfterHiddenWithAlly": 1, "killParticipation": 0.5405405405405406, "killedChampTookFullTeamDamageSurvived": 0, "killingSprees": 3, "killsNearEnemyTurret": 3, "killsOnOtherLanesEarlyJungleAsLaner": 0, "killsOnRecentlyHealedByAramPack": 0, "killsUnderOwnTurret": 1, "killsWithHelpFromEpicMonster": 0, "knockEnemyIntoTeamAndKill": 0, "landSkillShotsEarlyGame": 1, "laneMinionsFirst10Minutes": 77, "laningPhaseGoldExpAdvantage": 1, "legendaryCount": 0, "lostAnInhibitor": 0, "maxCsAdvantageOnLaneOpponent": 53, "maxKillDeficit": 1, "maxLevelLeadLaneOpponent": 2, "mejaisFullStackInTime": 0, "moreEnemyJungleThanOpponent": 0, "multiKillOneSpell": 0, "multiTurretRiftHeraldCount": 0, "multikills": 3, "multikillsAfterAggressiveFlash": 0, "mythicItemUsed": 3142, "outerTurretExecutesBefore10Minutes": 0, "outnumberedKills": 1, "outnumberedNexusKill": 0, "perfectDragonSoulsTaken": 1, "perfectGame": 0, "pickKillWithAlly": 15, "playedChampSelectPosition": 1, "poroExplosions": 0, "quickCleanse": 0, "quickFirstTurret": 0, "quickSoloKills": 0, "riftHeraldTakedowns": 0, "saveAllyFromDeath": 0, "scuttleCrabKills": 1, "skillshotsDodged": 21, "skillshotsHit": 72, "snowballsHit": 0, "soloBaronKills": 0, "soloKills": 0, "stealthWardsPlaced": 4, "survivedSingleDigitHpCount": 0, "survivedThreeImmobilizesInFight": 0, "takedownOnFirstTurret": 0, "takedowns": 20, "takedownsAfterGainingLevelAdvantage": 0, "takedownsBeforeJungleMinionSpawn": 0, "takedownsFirstXMinutes": 7, "takedownsInAlcove": 2, "takedownsInEnemyFountain": 0, "teamBaronKills": 1, "teamDamagePercentage": 0.26460382446159086, "teamElderDragonKills": 0, "teamRiftHeraldKills": 1, "tookLargeDamageSurvived": 0, "turretPlatesTaken": 4, "turretTakedowns": 8, "turretsTakenWithRiftHerald": 0, "twentyMinionsIn3SecondsCount": 10, "twoWardsOneSweeperCount": 0, "unseenRecalls": 0, "visionScoreAdvantageLaneOpponent": 1.1864800453186035, "visionScorePerMinute": 0.7871432691289098, "wardTakedowns": 6, "wardTakedownsBefore20M": 2, "wardsGuarded": 0}, "champExperience": 14886, "champLevel": 16, "championId": 21, "championName": "MissFortune", "championTransform": 0, "commandPings": 23, "consumablesPurchased": 2, "damageDealtToBuildings": 12134, "damageDealtToObjectives": 29797, "damageDealtToTurrets": 12134, "damageSelfMitigated": 10083, "dangerPings": 0, "deaths": 2, "detectorWardsPlaced": 1, "doubleKills": 2, "dragonKills": 0, "eligibleForProgression": true, "enemyMissingPings": 6, "enemyVisionPings": 0, "firstBloodAssist": false, "firstBloodKill": true, "firstTowerAssist": false, "firstTowerKill": false, "gameEndedInEarlySurrender": false, "gameEndedInSurrender": false, "getBackPings": 5, "goldEarned": 16483, "goldSpent": 14125, "holdPings": 1, "individualPosition": "BOTTOM", "inhibitorKills": 1, "inhibitorTakedowns": 2, "inhibitorsLost": 0, "item0": 6676, "item1": 3142, "item2": 2421, "item3": 6694, "item4": 3814, "item5": 3009, "item6": 3363, "itemsPurchased": 20, "killingSprees": 3, "kills": 13, "lane": "BOTTOM", "largestCriticalStrike": 805, "largestKillingSpree": 5, "largestMultiKill": 3, "longestTimeSpentLiving": 1035, "magicDamageDealt": 2160, "magicDamageDealtToChampions": 877, "magicDamageTaken": 3128, "needVisionPings": 0, "neutralMinionsKilled": 8, "nexusKills": 1, "nexusLost": 0, "nexusTakedowns": 1, "objectivesStolen": 0, "objectivesStolenAssists": 0, "onMyWayPings": 9, "participantId": 4, "pentaKills": 0, "perks": {"statPerks": {"defense": 5002, "flex": 5008, "offense": 5008}, "styles": [{"description": "primaryStyle", "selections": [{"perk": 8369, "var1": 1043, "var2": 805, "var3": 0}, {"perk": 8304, "var1": 8, "var2": 1, "var3": 5}, {"perk": 8345, "var1": 3, "var2": 0, "var3": 0}, {"perk": 8347, "var1": 0, "var2": 0, "var3": 0}], "style": 8300}, {"description": "subStyle", "selections": [{"perk": 8236, "var1": 14, "var2": 0, "var3": 0}, {"perk": 8226, "var1": 250, "var2": 866, "var3": 0}], "style": 8200}]}, "physicalDamageDealt": 193746, "physicalDamageDealtToChampions": 24224, "physicalDamageTaken": 12738, "placement": 0, "playerAugment1": 0, "playerAugment2": 0, "playerAugment3": 0, "playerAugment4": 0, "playerSubteamId": 0, "profileIcon": 685, "pushPings": 0, "puuid": "n6UlmuWVow8qS4255iyg7y7cqAHZe4JJT9o5EONa5J5O1mf2Ct5qHyA8G2WuORwz01yB0op7LwoVuw", "quadraKills": 0, "riotIdName": "", "riotIdTagline": "", "role": "CARRY", "sightWardsBoughtInGame": 0, "spell1Casts": 119, "spell2Casts": 74, "spell3Casts": 37, "spell4Casts": 10, "subteamPlacement": 0, "summoner1Casts": 3, "summoner1Id": 7, "summoner2Casts": 3, "summoner2Id": 4, "summonerId": "MV45c0i8AbhF9QczuzMRd8EKPouVmiRigtk_b4CMiZstHSQ", "summonerLevel": 544, "summonerName": "\ud5c8\uc758 \ud638\ud761 \uae40\ucd98\ubc30", "teamEarlySurrendered": false, "teamId": 100, "teamPosition": "BOTTOM", "timeCCingOthers": 9, "timePlayed": 1691, "totalAllyJungleMinionsKilled": 0, "totalDamageDealt": 198924, "totalDamageDealtToChampions": 26534, "totalDamageShieldedOnTeammates": 0, "totalDamageTaken": 17358, "totalEnemyJungleMinionsKilled": 4, "totalHeal": 3776, "totalHealsOnTeammates": 116, "totalMinionsKilled": 244, "totalTimeCCDealt": 178, "totalTimeSpentDead": 81, "totalUnitsHealed": 2, "tripleKills": 1, "trueDamageDealt": 3017, "trueDamageDealtToChampions": 1432, "trueDamageTaken": 1491, "turretKills": 5, "turretTakedowns": 8, "turretsLost": 4, "unrealKills": 0, "visionClearedPings": 0, "visionScore": 22, "visionWardsBoughtInGame": 1, "wardsKilled": 6, "wardsPlaced": 8, "win": true}, {"allInPings": 0, "assistMePings": 10, "assists": 26, "baitPings": 0, "baronKills": 0, "basicPings": 0, "bountyLevel": 0, "challenges": {"12AssistStreakCount": 0, "abilityUses": 225, "acesBefore15Minutes": 0, "alliedJungleMonsterKills": 0, "baronTakedowns": 1, "blastConeOppositeOpponentCount": 1, "bountyGold": 300, "buffsStolen": 0, "completeSupportQuestInTime": 0, "controlWardTimeCoverageInRiverOrEnemyHalf": 0.7319940012620944, "controlWardsPlaced": 14, "damagePerMinute": 265.82169942260083, "damageTakenOnTeamPercentage": 0.1754933919142589, "dancedWithRiftHerald": 0, "deathsByEnemyChamps": 4, "dodgeSkillShotsSmallWindow": 4, "doubleAces": 0, "dragonTakedowns": 2, "earliestBaron": 1314.4455773, "earliestDragonTakedown": 853.4450011, "earlyLaningPhaseGoldExpAdvantage": 0, "effectiveHealAndShielding": 1112.245361328125, "elderDragonKillsWithOpposingSoul": 0, "elderDragonMultikills": 0, "enemyChampionImmobilizations": 65, "enemyJungleMonsterKills": 0, "epicMonsterKillsNearEnemyJungler": 0, "epicMonsterKillsWithin30SecondsOfSpawn": 0, "epicMonsterSteals": 0, "epicMonsterStolenWithoutSmite": 0, "firstTurretKilled": 0, "flawlessAces": 1, "fullTeamTakedown": 1, "gameLength": 1691.8844863, "getTakedownsInAllLanesEarlyJungleAsLaner": 0, "goldPerMinute": 322.41105704439724, "hadOpenNexus": 0, "highestWardKills": 1, "immobilizeAndKillWithAlly": 18, "initialBuffCount": 0, "initialCrabCount": 0, "jungleCsBefore10Minutes": 0, "junglerTakedownsNearDamagedEpicMonster": 0, "kTurretsDestroyedBeforePlatesFall": 1, "kda": 7.25, "killAfterHiddenWithAlly": 2, "killParticipation": 0.7837837837837838, "killedChampTookFullTeamDamageSurvived": 0, "killingSprees": 0, "killsNearEnemyTurret": 0, "killsOnOtherLanesEarlyJungleAsLaner": 0, "killsOnRecentlyHealedByAramPack": 0, "killsUnderOwnTurret": 0, "killsWithHelpFromEpicMonster": 0, "knockEnemyIntoTeamAndKill": 7, "landSkillShotsEarlyGame": 0, "laneMinionsFirst10Minutes": 16, "laningPhaseGoldExpAdvantage": 0, "legendaryCount": 0, "lostAnInhibitor": 0, "maxCsAdvantageOnLaneOpponent": 1, "maxKillDeficit": 1, "maxLevelLeadLaneOpponent": 2, "mejaisFullStackInTime": 0, "moreEnemyJungleThanOpponent": 0, "multiKillOneSpell": 0, "multiTurretRiftHeraldCount": 0, "multikills": 0, "multikillsAfterAggressiveFlash": 0, "mythicItemUsed": 3001, "outerTurretExecutesBefore10Minutes": 0, "outnumberedKills": 0, "outnumberedNexusKill": 0, "perfectDragonSoulsTaken": 1, "perfectGame": 0, "pickKillWithAlly": 24, "playedChampSelectPosition": 1, "poroExplosions": 0, "quickCleanse": 0, "quickFirstTurret": 0, "quickSoloKills": 0, "riftHeraldTakedowns": 0, "saveAllyFromDeath": 4, "scuttleCrabKills": 0, "shortestTimeToAceFromFirstTakedown": 27.926360799999884, "skillshotsDodged": 25, "skillshotsHit": 0, "snowballsHit": 0, "soloBaronKills": 0, "soloKills": 0, "stealthWardsPlaced": 29, "survivedSingleDigitHpCount": 0, "survivedThreeImmobilizesInFight": 4, "takedownOnFirstTurret": 1, "takedowns": 29, "takedownsAfterGainingLevelAdvantage": 0, "takedownsBeforeJungleMinionSpawn": 0, "takedownsFirstXMinutes": 10, "takedownsInAlcove": 0, "takedownsInEnemyFountain": 0, "teamBaronKills": 1, "teamDamagePercentage": 0.07474597994600099, "teamElderDragonKills": 0, "teamRiftHeraldKills": 1, "tookLargeDamageSurvived": 0, "turretPlatesTaken": 1, "turretTakedowns": 5, "turretsTakenWithRiftHerald": 0, "twentyMinionsIn3SecondsCount": 1, "twoWardsOneSweeperCount": 0, "unseenRecalls": 0, "visionScoreAdvantageLaneOpponent": 0.08845388889312744, "visionScorePerMinute": 3.229309757156229, "wardTakedowns": 13, "wardTakedownsBefore20M": 10, "wardsGuarded": 1}, "champExperience": 10717, "champLevel": 13, "championId": 526, "championName": "Rell", "championTransform": 0, "commandPings": 29, "consumablesPurchased": 16, "damageDealtToBuildings": 56, "damageDealtToObjectives": 3141, "damageDealtToTurrets": 56, "damageSelfMitigated": 30336, "dangerPings": 0, "deaths": 4, "detectorWardsPlaced": 14, "doubleKills": 0, "dragonKills": 0, "eligibleForProgression": true, "enemyMissingPings": 17, "enemyVisionPings": 6, "firstBloodAssist": true, "firstBloodKill": false, "firstTowerAssist": false, "firstTowerKill": false, "gameEndedInEarlySurrender": false, "gameEndedInSurrender": false, "getBackPings": 24, "goldEarned": 9091, "goldSpent": 7950, "holdPings": 0, "individualPosition": "UTILITY", "inhibitorKills": 0, "inhibitorTakedowns": 2, "inhibitorsLost": 0, "item0": 3109, "item1": 0, "item2": 3860, "item3": 3001, "item4": 3076, "item5": 3158, "item6": 3364, "itemsPurchased": 33, "killingSprees": 0, "kills": 3, "lane": "BOTTOM", "largestCriticalStrike": 0, "largestKillingSpree": 0, "largestMultiKill": 1, "longestTimeSpentLiving": 946, "magicDamageDealt": 10067, "magicDamageDealtToChampions": 4846, "magicDamageTaken": 3767, "needVisionPings": 0, "neutralMinionsKilled": 0, "nexusKills": 0, "nexusLost": 0, "nexusTakedowns": 1, "objectivesStolen": 0, "objectivesStolenAssists": 0, "onMyWayPings": 46, "participantId": 5, "pentaKills": 0, "perks": {"statPerks": {"defense": 5002, "flex": 5002, "offense": 5007}, "styles": [{"description": "primaryStyle", "selections": [{"perk": 8351, "var1": 67, "var2": 863, "var3": 0}, {"perk": 8306, "var1": 6, "var2": 0, "var3": 0}, {"perk": 8316, "var1": 521, "var2": 0, "var3": 0}, {"perk": 8347, "var1": 0, "var2": 0, "var3": 0}], "style": 8300}, {"description": "subStyle", "selections": [{"perk": 8463, "var1": 1966, "var2": 0, "var3": 0}, {"perk": 8473, "var1": 866, "var2": 0, "var3": 0}], "style": 8400}]}, "physicalDamageDealt": 5537, "physicalDamageDealtToChampions": 2010, "physicalDamageTaken": 13583, "placement": 0, "playerAugment1": 0, "playerAugment2": 0, "playerAugment3": 0, "playerAugment4": 0, "playerSubteamId": 0, "profileIcon": 20, "pushPings": 0, "puuid": "3qgg1SNPYTbh4gbEJZjjzGrahLOWxunug9lL6L447HmMoyQIp_oei26Jsg8irEJ27pakpEaOCYAcDw", "quadraKills": 0, "riotIdName": "", "riotIdTagline": "", "role": "SUPPORT", "sightWardsBoughtInGame": 0, "spell1Casts": 75, "spell2Casts": 47, "spell3Casts": 92, "spell4Casts": 11, "subteamPlacement": 0, "summoner1Casts": 11, "summoner1Id": 4, "summoner2Casts": 7, "summoner2Id": 14, "summonerId": "eFH7ot8gYIOTVeOppSzgIDHHsPgPrCVYLRwuVR1zj813fcGpT4bAuxoSYA", "summonerLevel": 161, "summonerName": "Miaoniu3", "teamEarlySurrendered": false, "teamId": 100, "teamPosition": "UTILITY", "timeCCingOthers": 52, "timePlayed": 1691, "totalAllyJungleMinionsKilled": 0, "totalDamageDealt": 23408, "totalDamageDealtToChampions": 7495, "totalDamageShieldedOnTeammates": 0, "totalDamageTaken": 17706, "totalEnemyJungleMinionsKilled": 0, "totalHeal": 2869, "totalHealsOnTeammates": 1112, "totalMinionsKilled": 35, "totalTimeCCDealt": 178, "totalTimeSpentDead": 134, "totalUnitsHealed": 5, "tripleKills": 0, "trueDamageDealt": 7804, "trueDamageDealtToChampions": 639, "trueDamageTaken": 355, "turretKills": 0, "turretTakedowns": 5, "turretsLost": 4, "unrealKills": 0, "visionClearedPings": 0, "visionScore": 91, "visionWardsBoughtInGame": 14, "wardsKilled": 13, "wardsPlaced": 44, "win": true}, {"allInPings": 0, "assistMePings": 0, "assists": 4, "baitPings": 0, "baronKills": 0, "basicPings": 0, "bountyLevel": 0, "challenges": {"12AssistStreakCount": 0, "abilityUses": 205, "acesBefore15Minutes": 0, "alliedJungleMonsterKills": 0, "baronTakedowns": 0, "blastConeOppositeOpponentCount": 0, "bountyGold": 525, "buffsStolen": 0, "completeSupportQuestInTime": 0, "controlWardTimeCoverageInRiverOrEnemyHalf": 0.7241447629674385, "controlWardsPlaced": 3, "damagePerMinute": 700.5050074543615, "damageTakenOnTeamPercentage": 0.190755109901009, "dancedWithRiftHerald": 0, "deathsByEnemyChamps": 4, "dodgeSkillShotsSmallWindow": 2, "doubleAces": 0, "dragonTakedowns": 0, "earlyLaningPhaseGoldExpAdvantage": 0, "effectiveHealAndShielding": 0, "elderDragonKillsWithOpposingSoul": 0, "elderDragonMultikills": 0, "enemyChampionImmobilizations": 19, "enemyJungleMonsterKills": 7, "epicMonsterKillsNearEnemyJungler": 0, "epicMonsterKillsWithin30SecondsOfSpawn": 0, "epicMonsterSteals": 0, "epicMonsterStolenWithoutSmite": 0, "firstTurretKilled": 1, "firstTurretKilledTime": 640.5678469, "flawlessAces": 0, "fullTeamTakedown": 0, "gameLength": 1691.8844863, "getTakedownsInAllLanesEarlyJungleAsLaner": 0, "goldPerMinute": 501.7030652422385, "hadOpenNexus": 0, "immobilizeAndKillWithAlly": 6, "initialBuffCount": 0, "initialCrabCount": 0, "jungleCsBefore10Minutes": 0, "junglerTakedownsNearDamagedEpicMonster": 0, "kTurretsDestroyedBeforePlatesFall": 1, "kda": 2, "killAfterHiddenWithAlly": 0, "killParticipation": 0.47058823529411764, "killedChampTookFullTeamDamageSurvived": 0, "killingSprees": 0, "killsNearEnemyTurret": 2, "killsOnOtherLanesEarlyJungleAsLaner": 0, "killsOnRecentlyHealedByAramPack": 0, "killsUnderOwnTurret": 0, "killsWithHelpFromEpicMonster": 0, "knockEnemyIntoTeamAndKill": 0, "landSkillShotsEarlyGame": 0, "laneMinionsFirst10Minutes": 87, "laningPhaseGoldExpAdvantage": 0, "legendaryCount": 0, "lostAnInhibitor": 0, "maxCsAdvantageOnLaneOpponent": 74.99999997019768, "maxKillDeficit": 0, "maxLevelLeadLaneOpponent": 2, "mejaisFullStackInTime": 0, "moreEnemyJungleThanOpponent": 0, "multiKillOneSpell": 0, "multiTurretRiftHeraldCount": 0, "multikills": 0, "multikillsAfterAggressiveFlash": 0, "mythicItemUsed": 3142, "outerTurretExecutesBefore10Minutes": 0, "outnumberedKills": 0, "outnumberedNexusKill": 0, "perfectDragonSoulsTaken": 0, "perfectGame": 0, "pickKillWithAlly": 5, "playedChampSelectPosition": 1, "poroExplosions": 0, "quickCleanse": 0, "quickFirstTurret": 0, "quickSoloKills": 0, "riftHeraldTakedowns": 0, "saveAllyFromDeath": 0, "scuttleCrabKills": 0, "skillshotsDodged": 10, "skillshotsHit": 0, "snowballsHit": 0, "soloBaronKills": 0, "soloKills": 2, "soloTurretsLategame": 2, "stealthWardsPlaced": 4, "survivedSingleDigitHpCount": 0, "survivedThreeImmobilizesInFight": 2, "takedownOnFirstTurret": 1, "takedowns": 8, "takedownsAfterGainingLevelAdvantage": 0, "takedownsBeforeJungleMinionSpawn": 0, "takedownsFirstXMinutes": 3, "takedownsInAlcove": 0, "takedownsInEnemyFountain": 0, "teamBaronKills": 0, "teamDamagePercentage": 0.2895259009832298, "teamElderDragonKills": 0, "teamRiftHeraldKills": 1, "tookLargeDamageSurvived": 0, "turretPlatesTaken": 8, "turretTakedowns": 3, "turretsTakenWithRiftHerald": 5, "twentyMinionsIn3SecondsCount": 11, "twoWardsOneSweeperCount": 0, "unseenRecalls": 0, "visionScoreAdvantageLaneOpponent": -0.06292533874511719, "visionScorePerMinute": 0.732459097060818, "wardTakedowns": 3, "wardTakedownsBefore20M": 2, "wardsGuarded": 0}, "champExperience": 15600, "champLevel": 16, "championId": 58, "championName": "Renekton", "championTransform": 0, "commandPings": 1, "consumablesPurchased": 4, "damageDealtToBuildings": 10476, "damageDealtToObjectives": 10476, "damageDealtToTurrets": 10476, "damageSelfMitigated": 19583, "dangerPings": 0, "deaths": 4, "detectorWardsPlaced": 3, "doubleKills": 0, "dragonKills": 0, "eligibleForProgression": true, "enemyMissingPings": 2, "enemyVisionPings": 3, "firstBloodAssist": false, "firstBloodKill": false, "firstTowerAssist": false, "firstTowerKill": true, "gameEndedInEarlySurrender": false, "gameEndedInSurrender": false, "getBackPings": 4, "goldEarned": 14147, "goldSpent": 13625, "holdPings": 0, "individualPosition": "TOP", "inhibitorKills": 0, "inhibitorTakedowns": 0, "inhibitorsLost": 2, "item0": 3142, "item1": 2421, "item2": 6694, "item3": 1038, "item4": 3047, "item5": 3153, "item6": 3364, "itemsPurchased": 26, "killingSprees": 2, "kills": 4, "lane": "TOP", "largestCriticalStrike": 0, "largestKillingSpree": 2, "largestMultiKill": 1, "longestTimeSpentLiving": 804, "magicDamageDealt": 7296, "magicDamageDealtToChampions": 2544, "magicDamageTaken": 6388, "needVisionPings": 0, "neutralMinionsKilled": 12, "nexusKills": 0, "nexusLost": 1, "nexusTakedowns": 0, "objectivesStolen": 0, "objectivesStolenAssists": 0, "onMyWayPings": 1, "participantId": 6, "pentaKills": 0, "perks": {"statPerks": {"defense": 5002, "flex": 5008, "offense": 5008}, "styles": [{"description": "primaryStyle", "selections": [{"perk": 8005, "var1": 1938, "var2": 1143, "var3": 795}, {"perk": 9111, "var1": 650, "var2": 160, "var3": 0}, {"perk": 9105, "var1": 16, "var2": 30, "var3": 0}, {"perk": 8299, "var1": 431, "var2": 0, "var3": 0}], "style": 8000}, {"description": "subStyle", "selections": [{"perk": 8446, "var1": 2581, "var2": 0, "var3": 0}, {"perk": 8473, "var1": 944, "var2": 0, "var3": 0}], "style": 8400}]}, "physicalDamageDealt": 179200, "physicalDamageDealtToChampions": 16332, "physicalDamageTaken": 16780, "placement": 0, "playerAugment1": 0, "playerAugment2": 0, "playerAugment3": 0, "playerAugment4": 0, "playerSubteamId": 0, "profileIcon": 1114, "pushPings": 0, "puuid": "Se0nhBylutdQG_zcmHMUvgc_P-PdBGC-VaQILyhKWcLaMwQ3tF3Ax_HwpfkCFUpHPysqp8zt9LVkpQ", "quadraKills": 0, "riotIdName": "", "riotIdTagline": "", "role": "SOLO", "sightWardsBoughtInGame": 0, "spell1Casts": 67, "spell2Casts": 45, "spell3Casts": 84, "spell4Casts": 9, "subteamPlacement": 0, "summoner1Casts": 5, "summoner1Id": 14, "summoner2Casts": 4, "summoner2Id": 4, "summonerId": "R7a_PAooWXXbw6wuxrvCUMd0h3ciSMP2sRDrbC7sdkAyYw", "summonerLevel": 993, "summonerName": "\uac08\uacfc \ubc30 \uc74c\ub8cc", "teamEarlySurrendered": false, "teamId": 200, "teamPosition": "TOP", "timeCCingOthers": 25, "timePlayed": 1691, "totalAllyJungleMinionsKilled": 0, "totalDamageDealt": 194938, "totalDamageDealtToChampions": 19752, "totalDamageShieldedOnTeammates": 0, "totalDamageTaken": 24294, "totalEnemyJungleMinionsKilled": 12, "totalHeal": 6468, "totalHealsOnTeammates": 0, "totalMinionsKilled": 246, "totalTimeCCDealt": 77, "totalTimeSpentDead": 128, "totalUnitsHealed": 1, "tripleKills": 0, "trueDamageDealt": 8441, "trueDamageDealtToChampions": 876, "trueDamageTaken": 1125, "turretKills": 3, "turretTakedowns": 3, "turretsLost": 10, "unrealKills": 0, "visionClearedPings": 0, "visionScore": 20, "visionWardsBoughtInGame": 3, "wardsKilled": 3, "wardsPlaced": 7, "win": false}, {"allInPings": 2, "assistMePings": 11, "assists": 6, "baitPings": 0, "baronKills": 0, "basicPings": 0, "bountyLevel": 0, "challenges": {"12AssistStreakCount": 0, "abilityUses": 492, "acesBefore15Minutes": 0, "alliedJungleMonsterKills": 69, "baronTakedowns": 0, "blastConeOppositeOpponentCount": 0, "bountyGold": 550, "buffsStolen": 3, "completeSupportQuestInTime": 0, "controlWardTimeCoverageInRiverOrEnemyHalf": 0.7908885813039682, "controlWardsPlaced": 5, "damagePerMinute": 445.7762570086107, "damageTakenOnTeamPercentage": 0.2950996155329857, "dancedWithRiftHerald": 0, "deathsByEnemyChamps": 9, "dodgeSkillShotsSmallWindow": 15, "doubleAces": 0, "dragonTakedowns": 0, "earlyLaningPhaseGoldExpAdvantage": 0, "effectiveHealAndShielding": 746.1773681640625, "elderDragonKillsWithOpposingSoul": 0, "elderDragonMultikills": 0, "enemyChampionImmobilizations": 28, "enemyJungleMonsterKills": 5, "epicMonsterKillsNearEnemyJungler": 0, "epicMonsterKillsWithin30SecondsOfSpawn": 0, "epicMonsterSteals": 0, "epicMonsterStolenWithoutSmite": 0, "firstTurretKilled": 1, "firstTurretKilledTime": 640.5678469, "flawlessAces": 0, "fullTeamTakedown": 0, "gameLength": 1691.8844863, "goldPerMinute": 402.2930204892322, "hadOpenNexus": 0, "immobilizeAndKillWithAlly": 4, "initialBuffCount": 1, "initialCrabCount": 1, "jungleCsBefore10Minutes": 52.00000008940697, "junglerKillsEarlyJungle": 0, "junglerTakedownsNearDamagedEpicMonster": 0, "kTurretsDestroyedBeforePlatesFall": 1, "kda": 1.1111111111111112, "killAfterHiddenWithAlly": 2, "killParticipation": 0.5882352941176471, "killedChampTookFullTeamDamageSurvived": 0, "killingSprees": 0, "killsNearEnemyTurret": 2, "killsOnLanersEarlyJungleAsJungler": 2, "killsOnRecentlyHealedByAramPack": 0, "killsUnderOwnTurret": 0, "killsWithHelpFromEpicMonster": 0, "knockEnemyIntoTeamAndKill": 3, "landSkillShotsEarlyGame": 2, "laneMinionsFirst10Minutes": 0, "laningPhaseGoldExpAdvantage": 0, "legendaryCount": 0, "lostAnInhibitor": 0, "maxCsAdvantageOnLaneOpponent": 6.000000029802322, "maxKillDeficit": 0, "maxLevelLeadLaneOpponent": 1, "mejaisFullStackInTime": 0, "moreEnemyJungleThanOpponent": -37.000000059604645, "multiKillOneSpell": 0, "multiTurretRiftHeraldCount": 0, "multikills": 0, "multikillsAfterAggressiveFlash": 0, "mythicItemUsed": 6630, "outerTurretExecutesBefore10Minutes": 0, "outnumberedKills": 1, "outnumberedNexusKill": 0, "perfectDragonSoulsTaken": 0, "perfectGame": 0, "pickKillWithAlly": 8, "playedChampSelectPosition": 1, "poroExplosions": 0, "quickCleanse": 0, "quickFirstTurret": 0, "quickSoloKills": 0, "riftHeraldTakedowns": 1, "saveAllyFromDeath": 0, "scuttleCrabKills": 2, "skillshotsDodged": 80, "skillshotsHit": 24, "snowballsHit": 0, "soloBaronKills": 0, "soloKills": 0, "stealthWardsPlaced": 9, "survivedSingleDigitHpCount": 0, "survivedThreeImmobilizesInFight": 4, "takedownOnFirstTurret": 0, "takedowns": 10, "takedownsAfterGainingLevelAdvantage": 0, "takedownsBeforeJungleMinionSpawn": 0, "takedownsFirstXMinutes": 2, "takedownsInAlcove": 0, "takedownsInEnemyFountain": 0, "teamBaronKills": 0, "teamDamagePercentage": 0.1842438970084856, "teamElderDragonKills": 0, "teamRiftHeraldKills": 1, "tookLargeDamageSurvived": 0, "turretPlatesTaken": 3, "turretTakedowns": 1, "turretsTakenWithRiftHerald": 5, "twentyMinionsIn3SecondsCount": 0, "twoWardsOneSweeperCount": 0, "unseenRecalls": 0, "visionScoreAdvantageLaneOpponent": -0.36569052934646606, "visionScorePerMinute": 0.9947867503060107, "wardTakedowns": 5, "wardTakedownsBefore20M": 1, "wardsGuarded": 2}, "champExperience": 12130, "champLevel": 14, "championId": 64, "championName": "LeeSin", "championTransform": 0, "commandPings": 16, "consumablesPurchased": 9, "damageDealtToBuildings": 285, "damageDealtToObjectives": 17519, "damageDealtToTurrets": 285, "damageSelfMitigated": 33262, "dangerPings": 0, "deaths": 9, "detectorWardsPlaced": 5, "doubleKills": 0, "dragonKills": 0, "eligibleForProgression": true, "enemyMissingPings": 2, "enemyVisionPings": 1, "firstBloodAssist": false, "firstBloodKill": false, "firstTowerAssist": true, "firstTowerKill": false, "gameEndedInEarlySurrender": false, "gameEndedInSurrender": false, "getBackPings": 4, "goldEarned": 11343, "goldSpent": 11125, "holdPings": 0, "individualPosition": "JUNGLE", "inhibitorKills": 0, "inhibitorTakedowns": 0, "inhibitorsLost": 2, "item0": 6630, "item1": 2055, "item2": 0, "item3": 3071, "item4": 3026, "item5": 3111, "item6": 3340, "itemsPurchased": 23, "killingSprees": 1, "kills": 4, "lane": "JUNGLE", "largestCriticalStrike": 0, "largestKillingSpree": 2, "largestMultiKill": 1, "longestTimeSpentLiving": 458, "magicDamageDealt": 35781, "magicDamageDealtToChampions": 1487, "magicDamageTaken": 11848, "needVisionPings": 0, "neutralMinionsKilled": 129, "nexusKills": 0, "nexusLost": 1, "nexusTakedowns": 0, "objectivesStolen": 0, "objectivesStolenAssists": 0, "onMyWayPings": 28, "participantId": 7, "pentaKills": 0, "perks": {"statPerks": {"defense": 5002, "flex": 5008, "offense": 5005}, "styles": [{"description": "primaryStyle", "selections": [{"perk": 8010, "var1": 303, "var2": 0, "var3": 0}, {"perk": 9111, "var1": 769, "var2": 200, "var3": 0}, {"perk": 9104, "var1": 18, "var2": 0, "var3": 0}, {"perk": 8014, "var1": 318, "var2": 0, "var3": 0}], "style": 8000}, {"description": "subStyle", "selections": [{"perk": 8304, "var1": 10, "var2": 3, "var3": 0}, {"perk": 8347, "var1": 0, "var2": 0, "var3": 0}], "style": 8300}]}, "physicalDamageDealt": 111936, "physicalDamageDealtToChampions": 9965, "physicalDamageTaken": 24997, "placement": 0, "playerAugment1": 0, "playerAugment2": 0, "playerAugment3": 0, "playerAugment4": 0, "playerSubteamId": 0, "profileIcon": 907, "pushPings": 0, "puuid": "3eh8U-42rwY5jw7o0dJpcfa67gUiUMToI1Ns12o2a7Nr2_P1YROOmsxtn5F3SEldTSjrVQR2cDch0g", "quadraKills": 0, "riotIdName": "", "riotIdTagline": "", "role": "NONE", "sightWardsBoughtInGame": 0, "spell1Casts": 193, "spell2Casts": 153, "spell3Casts": 134, "spell4Casts": 12, "subteamPlacement": 0, "summoner1Casts": 18, "summoner1Id": 11, "summoner2Casts": 4, "summoner2Id": 4, "summonerId": "G8L1xMsvrKvgT0VM4l10sWdiBHRCunxZbLwQvwDasD3PZ04e5w5x4VW5tA", "summonerLevel": 66, "summonerName": "qasdasdwqe", "teamEarlySurrendered": false, "teamId": 200, "teamPosition": "JUNGLE", "timeCCingOthers": 19, "timePlayed": 1691, "totalAllyJungleMinionsKilled": 87, "totalDamageDealt": 185528, "totalDamageDealtToChampions": 12570, "totalDamageShieldedOnTeammates": 746, "totalDamageTaken": 37583, "totalEnemyJungleMinionsKilled": 20, "totalHeal": 14880, "totalHealsOnTeammates": 0, "totalMinionsKilled": 27, "totalTimeCCDealt": 485, "totalTimeSpentDead": 235, "totalUnitsHealed": 1, "tripleKills": 0, "trueDamageDealt": 37810, "trueDamageDealtToChampions": 1117, "trueDamageTaken": 738, "turretKills": 0, "turretTakedowns": 1, "turretsLost": 10, "unrealKills": 0, "visionClearedPings": 0, "visionScore": 28, "visionWardsBoughtInGame": 8, "wardsKilled": 5, "wardsPlaced": 14, "win": false}, {"allInPings": 0, "assistMePings": 4, "assists": 5, "baitPings": 0, "baronKills": 0, "basicPings": 0, "bountyLevel": 0, "challenges": {"12AssistStreakCount": 0, "abilityUses": 195, "acesBefore15Minutes": 0, "alliedJungleMonsterKills": 0, "baronTakedowns": 0, "blastConeOppositeOpponentCount": 0, "bountyGold": 375, "buffsStolen": 0, "completeSupportQuestInTime": 0, "controlWardTimeCoverageInRiverOrEnemyHalf": 0.8129636228345385, "controlWardsPlaced": 7, "damagePerMinute": 340.81251694508785, "damageTakenOnTeamPercentage": 0.16535047487323537, "dancedWithRiftHerald": 0, "deathsByEnemyChamps": 7, "dodgeSkillShotsSmallWindow": 3, "doubleAces": 0, "dragonTakedowns": 0, "earlyLaningPhaseGoldExpAdvantage": 0, "effectiveHealAndShielding": 0, "elderDragonKillsWithOpposingSoul": 0, "elderDragonMultikills": 0, "enemyChampionImmobilizations": 16, "enemyJungleMonsterKills": 0, "epicMonsterKillsNearEnemyJungler": 0, "epicMonsterKillsWithin30SecondsOfSpawn": 0, "epicMonsterSteals": 0, "epicMonsterStolenWithoutSmite": 0, "firstTurretKilled": 1, "firstTurretKilledTime": 640.5678469, "flawlessAces": 0, "fullTeamTakedown": 0, "gameLength": 1691.8844863, "getTakedownsInAllLanesEarlyJungleAsLaner": 0, "goldPerMinute": 331.41582046330393, "hadOpenNexus": 0, "immobilizeAndKillWithAlly": 6, "initialBuffCount": 0, "initialCrabCount": 0, "jungleCsBefore10Minutes": 0, "junglerTakedownsNearDamagedEpicMonster": 0, "kTurretsDestroyedBeforePlatesFall": 0, "kda": 1.1428571428571428, "killAfterHiddenWithAlly": 2, "killParticipation": 0.47058823529411764, "killedChampTookFullTeamDamageSurvived": 0, "killingSprees": 0, "killsNearEnemyTurret": 0, "killsOnOtherLanesEarlyJungleAsLaner": 0, "killsOnRecentlyHealedByAramPack": 0, "killsUnderOwnTurret": 1, "killsWithHelpFromEpicMonster": 0, "knockEnemyIntoTeamAndKill": 0, "landSkillShotsEarlyGame": 9, "laneMinionsFirst10Minutes": 70, "laningPhaseGoldExpAdvantage": 0, "legendaryCount": 0, "lostAnInhibitor": 0, "maxCsAdvantageOnLaneOpponent": 0, "maxKillDeficit": 0, "maxLevelLeadLaneOpponent": 1, "mejaisFullStackInTime": 0, "moreEnemyJungleThanOpponent": 0, "multiKillOneSpell": 0, "multiTurretRiftHeraldCount": 0, "multikills": 0, "multikillsAfterAggressiveFlash": 0, "mythicItemUsed": 6656, "outerTurretExecutesBefore10Minutes": 0, "outnumberedKills": 0, "outnumberedNexusKill": 0, "perfectDragonSoulsTaken": 0, "perfectGame": 0, "pickKillWithAlly": 7, "playedChampSelectPosition": 1, "poroExplosions": 0, "quickCleanse": 0, "quickFirstTurret": 0, "quickSoloKills": 0, "riftHeraldTakedowns": 0, "saveAllyFromDeath": 0, "scuttleCrabKills": 0, "skillshotsDodged": 19, "skillshotsHit": 76, "snowballsHit": 0, "soloBaronKills": 0, "soloKills": 0, "stealthWardsPlaced": 5, "survivedSingleDigitHpCount": 0, "survivedThreeImmobilizesInFight": 2, "takedownOnFirstTurret": 0, "takedowns": 8, "takedownsAfterGainingLevelAdvantage": 0, "takedownsBeforeJungleMinionSpawn": 0, "takedownsFirstXMinutes": 1, "takedownsInAlcove": 0, "takedownsInEnemyFountain": 0, "teamBaronKills": 0, "teamDamagePercentage": 0.14086130717818962, "teamElderDragonKills": 0, "teamRiftHeraldKills": 1, "tookLargeDamageSurvived": 0, "turretPlatesTaken": 0, "turretTakedowns": 1, "turretsTakenWithRiftHerald": 5, "twentyMinionsIn3SecondsCount": 7, "twoWardsOneSweeperCount": 0, "unseenRecalls": 0, "visionScoreAdvantageLaneOpponent": -0.002112746238708496, "visionScorePerMinute": 1.2410644570705618, "wardTakedowns": 6, "wardTakedownsBefore20M": 4, "wardsGuarded": 1}, "champExperience": 10420, "champLevel": 13, "championId": 103, "championName": "Ahri", "championTransform": 0, "commandPings": 19, "consumablesPurchased": 12, "damageDealtToBuildings": 289, "damageDealtToObjectives": 4413, "damageDealtToTurrets": 289, "damageSelfMitigated": 8059, "dangerPings": 0, "deaths": 7, "detectorWardsPlaced": 7, "doubleKills": 0, "dragonKills": 0, "eligibleForProgression": true, "enemyMissingPings": 3, "enemyVisionPings": 3, "firstBloodAssist": false, "firstBloodKill": false, "firstTowerAssist": false, "firstTowerKill": false, "gameEndedInEarlySurrender": false, "gameEndedInSurrender": false, "getBackPings": 10, "goldEarned": 9345, "goldSpent": 9400, "holdPings": 0, "individualPosition": "MIDDLE", "inhibitorKills": 0, "inhibitorTakedowns": 0, "inhibitorsLost": 2, "item0": 6656, "item1": 2421, "item2": 2055, "item3": 3111, "item4": 3165, "item5": 3108, "item6": 3364, "itemsPurchased": 31, "killingSprees": 1, "kills": 3, "lane": "MIDDLE", "largestCriticalStrike": 0, "largestKillingSpree": 2, "largestMultiKill": 1, "longestTimeSpentLiving": 446, "magicDamageDealt": 39219, "magicDamageDealtToChampions": 6999, "magicDamageTaken": 5062, "needVisionPings": 0, "neutralMinionsKilled": 0, "nexusKills": 0, "nexusLost": 1, "nexusTakedowns": 0, "objectivesStolen": 0, "objectivesStolenAssists": 0, "onMyWayPings": 13, "participantId": 8, "pentaKills": 0, "perks": {"statPerks": {"defense": 5003, "flex": 5008, "offense": 5005}, "styles": [{"description": "primaryStyle", "selections": [{"perk": 8369, "var1": 382, "var2": 317, "var3": 0}, {"perk": 8304, "var1": 11, "var2": 1, "var3": 5}, {"perk": 8316, "var1": 3522, "var2": 0, "var3": 0}, {"perk": 8347, "var1": 0, "var2": 0, "var3": 0}], "style": 8300}, {"description": "subStyle", "selections": [{"perk": 8226, "var1": 250, "var2": 285, "var3": 0}, {"perk": 8210, "var1": 14, "var2": 0, "var3": 0}], "style": 8200}]}, "physicalDamageDealt": 14279, "physicalDamageDealtToChampions": 908, "physicalDamageTaken": 14769, "placement": 0, "playerAugment1": 0, "playerAugment2": 0, "playerAugment3": 0, "playerAugment4": 0, "playerSubteamId": 0, "profileIcon": 3478, "pushPings": 0, "puuid": "u2T4Y6r2-llySjrkM6o-WCsDGBWCeNL7UkD71vBOh9SlNjDjiH28gcPt2AlMm_8fmhjBWWFayCirvw", "quadraKills": 0, "riotIdName": "", "riotIdTagline": "", "role": "SOLO", "sightWardsBoughtInGame": 0, "spell1Casts": 61, "spell2Casts": 75, "spell3Casts": 30, "spell4Casts": 29, "subteamPlacement": 0, "summoner1Casts": 4, "summoner1Id": 12, "summoner2Casts": 5, "summoner2Id": 4, "summonerId": "Acs3nHyfe41OxAZFxi-O0uEF3nbdvZkBomQzoLdSQcDdPeU", "summonerLevel": 283, "summonerName": "Loba", "teamEarlySurrendered": false, "teamId": 200, "teamPosition": "MIDDLE", "timeCCingOthers": 16, "timePlayed": 1691, "totalAllyJungleMinionsKilled": 0, "totalDamageDealt": 84975, "totalDamageDealtToChampions": 9610, "totalDamageShieldedOnTeammates": 0, "totalDamageTaken": 21059, "totalEnemyJungleMinionsKilled": 0, "totalHeal": 2354, "totalHealsOnTeammates": 0, "totalMinionsKilled": 160, "totalTimeCCDealt": 53, "totalTimeSpentDead": 182, "totalUnitsHealed": 1, "tripleKills": 0, "trueDamageDealt": 31475, "trueDamageDealtToChampions": 1702, "trueDamageTaken": 1226, "turretKills": 0, "turretTakedowns": 1, "turretsLost": 10, "unrealKills": 0, "visionClearedPings": 0, "visionScore": 34, "visionWardsBoughtInGame": 9, "wardsKilled": 6, "wardsPlaced": 12, "win": false}, {"allInPings": 0, "assistMePings": 4, "assists": 2, "baitPings": 0, "baronKills": 0, "basicPings": 0, "bountyLevel": 0, "challenges": {"12AssistStreakCount": 0, "abilityUses": 148, "acesBefore15Minutes": 0, "alliedJungleMonsterKills": 17, "baronTakedowns": 0, "blastConeOppositeOpponentCount": 0, "bountyGold": 375, "buffsStolen": 0, "completeSupportQuestInTime": 0, "controlWardsPlaced": 0, "damagePerMinute": 656.1871685772666, "damageTakenOnTeamPercentage": 0.18549603728534897, "dancedWithRiftHerald": 0, "deathsByEnemyChamps": 10, "dodgeSkillShotsSmallWindow": 16, "doubleAces": 0, "dragonTakedowns": 0, "earlyLaningPhaseGoldExpAdvantage": 0, "effectiveHealAndShielding": 0, "elderDragonKillsWithOpposingSoul": 0, "elderDragonMultikills": 0, "enemyChampionImmobilizations": 10, "enemyJungleMonsterKills": 0, "epicMonsterKillsNearEnemyJungler": 0, "epicMonsterKillsWithin30SecondsOfSpawn": 0, "epicMonsterSteals": 0, "epicMonsterStolenWithoutSmite": 0, "firstTurretKilled": 1, "firstTurretKilledTime": 640.5678469, "flawlessAces": 0, "fullTeamTakedown": 0, "gameLength": 1691.8844863, "getTakedownsInAllLanesEarlyJungleAsLaner": 0, "goldPerMinute": 437.59189672891915, "hadOpenNexus": 0, "immobilizeAndKillWithAlly": 4, "initialBuffCount": 0, "initialCrabCount": 0, "jungleCsBefore10Minutes": 0, "junglerTakedownsNearDamagedEpicMonster": 0, "kTurretsDestroyedBeforePlatesFall": 0, "kda": 0.8, "killAfterHiddenWithAlly": 2, "killParticipation": 0.47058823529411764, "killedChampTookFullTeamDamageSurvived": 0, "killingSprees": 2, "killsNearEnemyTurret": 0, "killsOnOtherLanesEarlyJungleAsLaner": 0, "killsOnRecentlyHealedByAramPack": 0, "killsUnderOwnTurret": 1, "killsWithHelpFromEpicMonster": 0, "knockEnemyIntoTeamAndKill": 0, "landSkillShotsEarlyGame": 7, "laneMinionsFirst10Minutes": 44, "laningPhaseGoldExpAdvantage": 0, "legendaryCount": 0, "lostAnInhibitor": 0, "maxCsAdvantageOnLaneOpponent": 1, "maxKillDeficit": 0, "maxLevelLeadLaneOpponent": 0, "mejaisFullStackInTime": 0, "moreEnemyJungleThanOpponent": 0, "multiKillOneSpell": 0, "multiTurretRiftHeraldCount": 0, "multikills": 2, "multikillsAfterAggressiveFlash": 1, "mythicItemUsed": 6675, "outerTurretExecutesBefore10Minutes": 0, "outnumberedKills": 1, "outnumberedNexusKill": 0, "perfectDragonSoulsTaken": 0, "perfectGame": 0, "pickKillWithAlly": 7, "playedChampSelectPosition": 1, "poroExplosions": 0, "quickCleanse": 0, "quickFirstTurret": 0, "quickSoloKills": 0, "riftHeraldTakedowns": 0, "saveAllyFromDeath": 0, "scuttleCrabKills": 0, "skillshotsDodged": 85, "skillshotsHit": 36, "snowballsHit": 0, "soloBaronKills": 0, "soloKills": 0, "stealthWardsPlaced": 6, "survivedSingleDigitHpCount": 0, "survivedThreeImmobilizesInFight": 0, "takedownOnFirstTurret": 0, "takedowns": 8, "takedownsAfterGainingLevelAdvantage": 0, "takedownsBeforeJungleMinionSpawn": 0, "takedownsFirstXMinutes": 0, "takedownsInAlcove": 0, "takedownsInEnemyFountain": 0, "teamBaronKills": 0, "teamDamagePercentage": 0.2712088838399134, "teamElderDragonKills": 0, "teamRiftHeraldKills": 1, "tookLargeDamageSurvived": 0, "turretPlatesTaken": 1, "turretTakedowns": 1, "turretsTakenWithRiftHerald": 5, "twentyMinionsIn3SecondsCount": 9, "twoWardsOneSweeperCount": 0, "unseenRecalls": 0, "visionScoreAdvantageLaneOpponent": -0.5426439046859741, "visionScorePerMinute": 0.36000477537199865, "wardTakedowns": 1, "wardTakedownsBefore20M": 1, "wardsGuarded": 0}, "champExperience": 13050, "champLevel": 15, "championId": 498, "championName": "Xayah", "championTransform": 0, "commandPings": 14, "consumablesPurchased": 2, "damageDealtToBuildings": 1453, "damageDealtToObjectives": 3633, "damageDealtToTurrets": 1453, "damageSelfMitigated": 10571, "dangerPings": 0, "deaths": 10, "detectorWardsPlaced": 0, "doubleKills": 1, "dragonKills": 0, "eligibleForProgression": true, "enemyMissingPings": 3, "enemyVisionPings": 1, "firstBloodAssist": false, "firstBloodKill": false, "firstTowerAssist": false, "firstTowerKill": false, "gameEndedInEarlySurrender": false, "gameEndedInSurrender": false, "getBackPings": 12, "goldEarned": 12339, "goldSpent": 11825, "holdPings": 1, "individualPosition": "BOTTOM", "inhibitorKills": 0, "inhibitorTakedowns": 0, "inhibitorsLost": 2, "item0": 1055, "item1": 1053, "item2": 3036, "item3": 6675, "item4": 6672, "item5": 3006, "item6": 3363, "itemsPurchased": 25, "killingSprees": 2, "kills": 6, "lane": "BOTTOM", "largestCriticalStrike": 491, "largestKillingSpree": 3, "largestMultiKill": 3, "longestTimeSpentLiving": 334, "magicDamageDealt": 270, "magicDamageDealtToChampions": 0, "magicDamageTaken": 7165, "needVisionPings": 0, "neutralMinionsKilled": 16, "nexusKills": 0, "nexusLost": 1, "nexusTakedowns": 0, "objectivesStolen": 0, "objectivesStolenAssists": 0, "onMyWayPings": 12, "participantId": 9, "pentaKills": 0, "perks": {"statPerks": {"defense": 5002, "flex": 5008, "offense": 5005}, "styles": [{"description": "primaryStyle", "selections": [{"perk": 8008, "var1": 43, "var2": 5, "var3": 0}, {"perk": 8009, "var1": 1128, "var2": 0, "var3": 0}, {"perk": 9103, "var1": 24, "var2": 20, "var3": 0}, {"perk": 8017, "var1": 991, "var2": 0, "var3": 0}], "style": 8000}, {"description": "subStyle", "selections": [{"perk": 8345, "var1": 3, "var2": 0, "var3": 0}, {"perk": 8304, "var1": 12, "var2": 0, "var3": 0}], "style": 8300}]}, "physicalDamageDealt": 173808, "physicalDamageDealtToChampions": 18503, "physicalDamageTaken": 15511, "placement": 0, "playerAugment1": 0, "playerAugment2": 0, "playerAugment3": 0, "playerAugment4": 0, "playerSubteamId": 0, "profileIcon": 29, "pushPings": 1, "puuid": "_uo1JZcYEFP8MPoR9RHGYEW-uGi4dduu7BhopwGdi6lO_qctGGAmqg7REjCLsQJDSbbgRcpGurs9lA", "quadraKills": 0, "riotIdName": "", "riotIdTagline": "", "role": "CARRY", "sightWardsBoughtInGame": 0, "spell1Casts": 62, "spell2Casts": 32, "spell3Casts": 48, "spell4Casts": 6, "subteamPlacement": 0, "summoner1Casts": 5, "summoner1Id": 1, "summoner2Casts": 4, "summoner2Id": 4, "summonerId": "p5T5-Yl217uf84d48NglY0FqFCPD1rtoz3Cd8ht6wT4867g", "summonerLevel": 428, "summonerName": "\uc7a0\uae50\ub9cc\uc774\uac70\ub9cc\uba39\uace0", "teamEarlySurrendered": false, "teamId": 200, "teamPosition": "BOTTOM", "timeCCingOthers": 13, "timePlayed": 1691, "totalAllyJungleMinionsKilled": 14, "totalDamageDealt": 174078, "totalDamageDealtToChampions": 18503, "totalDamageShieldedOnTeammates": 0, "totalDamageTaken": 23624, "totalEnemyJungleMinionsKilled": 0, "totalHeal": 4520, "totalHealsOnTeammates": 0, "totalMinionsKilled": 219, "totalTimeCCDealt": 26, "totalTimeSpentDead": 192, "totalUnitsHealed": 1, "tripleKills": 1, "trueDamageDealt": 0, "trueDamageDealtToChampions": 0, "trueDamageTaken": 948, "turretKills": 0, "turretTakedowns": 1, "turretsLost": 10, "unrealKills": 0, "visionClearedPings": 0, "visionScore": 10, "visionWardsBoughtInGame": 1, "wardsKilled": 1, "wardsPlaced": 7, "win": false}, {"allInPings": 0, "assistMePings": 1, "assists": 11, "baitPings": 0, "baronKills": 0, "basicPings": 0, "bountyLevel": 0, "challenges": {"12AssistStreakCount": 0, "abilityUses": 150, "acesBefore15Minutes": 0, "alliedJungleMonsterKills": 0, "baronTakedowns": 0, "blastConeOppositeOpponentCount": 0, "bountyGold": 0, "buffsStolen": 0, "completeSupportQuestInTime": 0, "controlWardTimeCoverageInRiverOrEnemyHalf": 0.7784100146104638, "controlWardsPlaced": 7, "damagePerMinute": 276.2089991882947, "damageTakenOnTeamPercentage": 0.16329876240742094, "dancedWithRiftHerald": 0, "deathsByEnemyChamps": 7, "dodgeSkillShotsSmallWindow": 23, "doubleAces": 0, "dragonTakedowns": 0, "earlyLaningPhaseGoldExpAdvantage": 0, "effectiveHealAndShielding": 4701.3408203125, "elderDragonKillsWithOpposingSoul": 0, "elderDragonMultikills": 0, "enemyChampionImmobilizations": 32, "enemyJungleMonsterKills": 0, "epicMonsterKillsNearEnemyJungler": 0, "epicMonsterKillsWithin30SecondsOfSpawn": 0, "epicMonsterSteals": 0, "epicMonsterStolenWithoutSmite": 0, "firstTurretKilled": 1, "firstTurretKilledTime": 640.5678469, "flawlessAces": 0, "fullTeamTakedown": 0, "gameLength": 1691.8844863, "getTakedownsInAllLanesEarlyJungleAsLaner": 0, "goldPerMinute": 243.8536555761756, "hadOpenNexus": 0, "immobilizeAndKillWithAlly": 6, "initialBuffCount": 0, "initialCrabCount": 0, "jungleCsBefore10Minutes": 0, "junglerTakedownsNearDamagedEpicMonster": 0, "kTurretsDestroyedBeforePlatesFall": 0, "kda": 1.5714285714285714, "killAfterHiddenWithAlly": 0, "killParticipation": 0.6470588235294118, "killedChampTookFullTeamDamageSurvived": 0, "killingSprees": 0, "killsNearEnemyTurret": 0, "killsOnOtherLanesEarlyJungleAsLaner": 0, "killsOnRecentlyHealedByAramPack": 0, "killsUnderOwnTurret": 0, "killsWithHelpFromEpicMonster": 0, "knockEnemyIntoTeamAndKill": 0, "landSkillShotsEarlyGame": 5, "laneMinionsFirst10Minutes": 22, "laningPhaseGoldExpAdvantage": 0, "legendaryCount": 0, "lostAnInhibitor": 0, "maxCsAdvantageOnLaneOpponent": 6, "maxKillDeficit": 0, "maxLevelLeadLaneOpponent": 1, "mejaisFullStackInTime": 0, "moreEnemyJungleThanOpponent": 0, "multiKillOneSpell": 0, "multiTurretRiftHeraldCount": 0, "multikills": 0, "multikillsAfterAggressiveFlash": 0, "mythicItemUsed": 6667, "outerTurretExecutesBefore10Minutes": 0, "outnumberedKills": 0, "outnumberedNexusKill": 0, "perfectDragonSoulsTaken": 0, "perfectGame": 0, "pickKillWithAlly": 10, "playedChampSelectPosition": 1, "poroExplosions": 0, "quickCleanse": 0, "quickFirstTurret": 0, "quickSoloKills": 0, "riftHeraldTakedowns": 0, "saveAllyFromDeath": 0, "scuttleCrabKills": 0, "skillshotsDodged": 120, "skillshotsHit": 23, "snowballsHit": 0, "soloBaronKills": 0, "soloKills": 0, "stealthWardsPlaced": 29, "survivedSingleDigitHpCount": 0, "survivedThreeImmobilizesInFight": 4, "takedownOnFirstTurret": 0, "takedowns": 11, "takedownsAfterGainingLevelAdvantage": 0, "takedownsBeforeJungleMinionSpawn": 0, "takedownsFirstXMinutes": 0, "takedownsInAlcove": 0, "takedownsInEnemyFountain": 0, "teamBaronKills": 0, "teamDamagePercentage": 0.11416001099018167, "teamElderDragonKills": 0, "teamRiftHeraldKills": 1, "tookLargeDamageSurvived": 0, "turretPlatesTaken": 0, "turretTakedowns": 1, "turretsTakenWithRiftHerald": 5, "twentyMinionsIn3SecondsCount": 1, "twoWardsOneSweeperCount": 0, "unseenRecalls": 0, "visionScoreAdvantageLaneOpponent": -0.08126568794250488, "visionScorePerMinute": 2.966877733702635, "wardTakedowns": 7, "wardTakedownsBefore20M": 3, "wardsGuarded": 0}, "champExperience": 9418, "champLevel": 12, "championId": 497, "championName": "Rakan", "championTransform": 0, "commandPings": 11, "consumablesPurchased": 11, "damageDealtToBuildings": 225, "damageDealtToObjectives": 225, "damageDealtToTurrets": 225, "damageSelfMitigated": 20949, "dangerPings": 0, "deaths": 7, "detectorWardsPlaced": 7, "doubleKills": 0, "dragonKills": 0, "eligibleForProgression": true, "enemyMissingPings": 14, "enemyVisionPings": 9, "firstBloodAssist": false, "firstBloodKill": false, "firstTowerAssist": false, "firstTowerKill": false, "gameEndedInEarlySurrender": false, "gameEndedInSurrender": false, "getBackPings": 4, "goldEarned": 6876, "goldSpent": 6325, "holdPings": 0, "individualPosition": "UTILITY", "inhibitorKills": 0, "inhibitorTakedowns": 0, "inhibitorsLost": 2, "item0": 6667, "item1": 3158, "item2": 1029, "item3": 3860, "item4": 3023, "item5": 2055, "item6": 3364, "itemsPurchased": 25, "killingSprees": 0, "kills": 0, "lane": "BOTTOM", "largestCriticalStrike": 0, "largestKillingSpree": 0, "largestMultiKill": 0, "longestTimeSpentLiving": 453, "magicDamageDealt": 8185, "magicDamageDealtToChampions": 4536, "magicDamageTaken": 6040, "needVisionPings": 0, "neutralMinionsKilled": 0, "nexusKills": 0, "nexusLost": 1, "nexusTakedowns": 0, "objectivesStolen": 0, "objectivesStolenAssists": 0, "onMyWayPings": 9, "participantId": 10, "pentaKills": 0, "perks": {"statPerks": {"defense": 5002, "flex": 5008, "offense": 5008}, "styles": [{"description": "primaryStyle", "selections": [{"perk": 8465, "var1": 2784, "var2": 0, "var3": 0}, {"perk": 8401, "var1": 258, "var2": 0, "var3": 0}, {"perk": 8473, "var1": 678, "var2": 0, "var3": 0}, {"perk": 8242, "var1": 69, "var2": 0, "var3": 0}], "style": 8400}, {"description": "subStyle", "selections": [{"perk": 8106, "var1": 5, "var2": 0, "var3": 0}, {"perk": 8136, "var1": 12, "var2": 30, "var3": 0}], "style": 8100}]}, "physicalDamageDealt": 6396, "physicalDamageDealtToChampions": 2218, "physicalDamageTaken": 12966, "placement": 0, "playerAugment1": 0, "playerAugment2": 0, "playerAugment3": 0, "playerAugment4": 0, "playerSubteamId": 0, "profileIcon": 7, "pushPings": 0, "puuid": "smMrpOc9vfIyklOx1iSIzPDcz2eeZfu6yL0z0PTpy4JwJBWMCKvaVgP8lOYs6FcRCzMNwZ9mFWpO_g", "quadraKills": 0, "riotIdName": "", "riotIdTagline": "", "role": "SUPPORT", "sightWardsBoughtInGame": 0, "spell1Casts": 41, "spell2Casts": 47, "spell3Casts": 54, "spell4Casts": 8, "subteamPlacement": 0, "summoner1Casts": 4, "summoner1Id": 4, "summoner2Casts": 7, "summoner2Id": 14, "summonerId": "dx5oHAh67G0j-Uc3f6aX6E8wNt3C44e5pqTYNn_2HRuVrlw", "summonerLevel": 315, "summonerName": "\uc0db\ub178\ub780\uc720\ucc44\ud654", "teamEarlySurrendered": false, "teamId": 200, "teamPosition": "UTILITY", "timeCCingOthers": 31, "timePlayed": 1691, "totalAllyJungleMinionsKilled": 0, "totalDamageDealt": 21091, "totalDamageDealtToChampions": 7788, "totalDamageShieldedOnTeammates": 3086, "totalDamageTaken": 20797, "totalEnemyJungleMinionsKilled": 0, "totalHeal": 4371, "totalHealsOnTeammates": 1614, "totalMinionsKilled": 40, "totalTimeCCDealt": 62, "totalTimeSpentDead": 158, "totalUnitsHealed": 4, "tripleKills": 0, "trueDamageDealt": 6508, "trueDamageDealtToChampions": 1033, "trueDamageTaken": 1791, "turretKills": 1, "turretTakedowns": 1, "turretsLost": 10, "unrealKills": 0, "visionClearedPings": 0, "visionScore": 83, "visionWardsBoughtInGame": 9, "wardsKilled": 7, "wardsPlaced": 48, "win": false}], "platformId": "KR", "queueId": 420, "teams": [{"bans": [{"championId": 119, "pickTurn": 1}, {"championId": 33, "pickTurn": 2}, {"championId": 74, "pickTurn": 3}, {"championId": 81, "pickTurn": 4}, {"championId": 518, "pickTurn": 5}], "objectives": {"baron": {"first": true, "kills": 1}, "champion": {"first": true, "kills": 37}, "dragon": {"first": true, "kills": 4}, "inhibitor": {"first": true, "kills": 2}, "riftHerald": {"first": false, "kills": 1}, "tower": {"first": false, "kills": 10}}, "teamId": 100, "win": true}, {"bans": [{"championId": 555, "pickTurn": 6}, {"championId": 421, "pickTurn": 7}, {"championId": 76, "pickTurn": 8}, {"championId": 68, "pickTurn": 9}, {"championId": 119, "pickTurn": 10}], "objectives": {"baron": {"first": false, "kills": 0}, "champion": {"first": false, "kills": 17}, "dragon": {"first": false, "kills": 0}, "inhibitor": {"first": false, "kills": 0}, "riftHerald": {"first": true, "kills": 1}, "tower": {"first": true, "kills": 4}}, "teamId": 200, "win": false}], "tournamentCode": ""}}