{"metadata": {"dataVersion": "2", "matchId": "KR_6632327979", "participants": ["4-s6dr5s1WJ-hiTjZy1B0CeAbQKtEveAiOCe_rHNILIrf3y1pJCg0evTYSbGnUjTeVINRNhhGb1Kbw", "CLM40viH26FxSWXPmGp4ZEmjgGHFj02ByWEGKyn6CxmsMVM9dBSHlTQ4A35st8yVddyEoV3iI_1jWg", "yCheQFpNtJcRPUGBYaHbaILHSpnT_GjRU16x0iOjb-AdCYGUG0y5aztx97NRwg5bt473teujGQ3Kcg", "azmetsJMURbhheBhUntzl8VNraeBfzs0-Bepsr-33CoPd5FCcQ398ACIyIXz4Y0Wb6QwFyOhB_GSzw", "pSeLNn_nBykkSOwZHxfLx53y1tBXss5stPpbPReGEG83EOGF9XRDQwLliUNla4DO9p3gK_TwPG0KGw", "lmnJM08vWc4by13rLmSdmT95MNtDQZSfSqMzkReEP4C8Q2cn4WSAVxn-eVDQCgHGwYtBCB3TOvuICQ", "8gU_pNweRp6t5cFZdajxPLS3I7ypaBs2VvOQrHuoyjRAbXTM---xQlFL_Ktp5fXRoy3vBfhtfYrUVw", "oVa7Xp04TQFfEdd9x1PKUTdiYjNNcjG8fLYpT63b8opb30E-cwzL-VUVNuhohbdiwmBM4v87ipciwA", "fsQU8a6yWK-aXR_nxqejnclutdZxrhHxuPLxq-gXJFCuAtbui6cqiHZd92RBLGP4mh3oVPs_CF-Nzg", "X1wZJHtl_sUADq9Md8Eoip-TDb8RFiJjX0O5ZzHSQPI5mnMFRBuO46bK36aS2QG-XqDZ4bo_vD8j4A"]}, "info": {"gameCreation": 1691137815377, "gameDuration": 912, "gameEndTimestamp": 1691138744254, "gameId": 6632327979, "gameMode": "CLASSIC", "gameName": "teambuilder-match-6632327979", "gameStartTimestamp": 1691137831816, "gameType": "MATCHED_GAME", "gameVersion": "13.15.524.1760", "mapId": 11, "participants": [{"allInPings": 1, "assistMePings": 1, "assists": 2, "baitPings": 0, "baronKills": 0, "basicPings": 0, "bountyLevel": 0, "challenges": {"12AssistStreakCount": 0, "abilityUses": 83, "acesBefore15Minutes": 0, "alliedJungleMonsterKills": 0, "baronTakedowns": 0, "blastConeOppositeOpponentCount": 0, "bountyGold": 0, "buffsStolen": 0, "completeSupportQuestInTime": 0, "controlWardsPlaced": 1, "damagePerMinute": 179.7627884332835, "damageTakenOnTeamPercentage": 0.18024391108067106, "dancedWithRiftHerald": 0, "deathsByEnemyChamps": 3, "dodgeSkillShotsSmallWindow": 0, "doubleAces": 0, "dragonTakedowns": 0, "earlyLaningPhaseGoldExpAdvantage": 0, "effectiveHealAndShielding": 0, "elderDragonKillsWithOpposingSoul": 0, "elderDragonMultikills": 0, "enemyChampionImmobilizations": 8, "enemyJungleMonsterKills": 0, "epicMonsterKillsNearEnemyJungler": 0, "epicMonsterKillsWithin30SecondsOfSpawn": 0, "epicMonsterSteals": 0, "epicMonsterStolenWithoutSmite": 0, "firstTurretKilled": 0, "flawlessAces": 0, "fullTeamTakedown": 0, "gameLength": 912.5629653999999, "getTakedownsInAllLanesEarlyJungleAsLaner": 0, "goldPerMinute": 264.2938990111575, "hadOpenNexus": 0, "immobilizeAndKillWithAlly": 1, "initialBuffCount": 0, "initialCrabCount": 0, "jungleCsBefore10Minutes": 0, "junglerTakedownsNearDamagedEpicMonster": 0, "kTurretsDestroyedBeforePlatesFall": 0, "kda": 1, "killAfterHiddenWithAlly": 0, "killParticipation": 0.42857142857142855, "killedChampTookFullTeamDamageSurvived": 0, "killingSprees": 0, "killsNearEnemyTurret": 1, "killsOnOtherLanesEarlyJungleAsLaner": 1, "killsOnRecentlyHealedByAramPack": 0, "killsUnderOwnTurret": 0, "killsWithHelpFromEpicMonster": 0, "knockEnemyIntoTeamAndKill": 0, "landSkillShotsEarlyGame": 0, "laneMinionsFirst10Minutes": 28, "laningPhaseGoldExpAdvantage": 0, "legendaryCount": 0, "lostAnInhibitor": 0, "maxCsAdvantageOnLaneOpponent": 5, "maxKillDeficit": 0, "maxLevelLeadLaneOpponent": 1, "mejaisFullStackInTime": 0, "moreEnemyJungleThanOpponent": 0, "multiKillOneSpell": 0, "multiTurretRiftHeraldCount": 0, "multikills": 0, "multikillsAfterAggressiveFlash": 0, "outerTurretExecutesBefore10Minutes": 0, "outnumberedKills": 0, "outnumberedNexusKill": 0, "perfectDragonSoulsTaken": 0, "perfectGame": 0, "pickKillWithAlly": 2, "playedChampSelectPosition": 1, "poroExplosions": 0, "quickCleanse": 0, "quickFirstTurret": 0, "quickSoloKills": 0, "riftHeraldTakedowns": 0, "saveAllyFromDeath": 0, "scuttleCrabKills": 0, "skillshotsDodged": 7, "skillshotsHit": 0, "snowballsHit": 0, "soloBaronKills": 0, "soloKills": 1, "stealthWardsPlaced": 5, "survivedSingleDigitHpCount": 0, "survivedThreeImmobilizesInFight": 1, "takedownOnFirstTurret": 0, "takedowns": 3, "takedownsAfterGainingLevelAdvantage": 0, "takedownsBeforeJungleMinionSpawn": 0, "takedownsFirstXMinutes": 3, "takedownsInAlcove": 0, "takedownsInEnemyFountain": 0, "teamBaronKills": 0, "teamDamagePercentage": 0.11891420718303103, "teamElderDragonKills": 0, "teamRiftHeraldKills": 0, "tookLargeDamageSurvived": 0, "turretPlatesTaken": 0, "turretTakedowns": 0, "turretsTakenWithRiftHerald": 0, "twentyMinionsIn3SecondsCount": 2, "twoWardsOneSweeperCount": 0, "unseenRecalls": 0, "visionScoreAdvantageLaneOpponent": 1.1450908184051514, "visionScorePerMinute": 0.9562801440020208, "wardTakedowns": 0, "wardTakedownsBefore20M": 0, "wardsGuarded": 1}, "champExperience": 4702, "champLevel": 8, "championId": 24, "championName": "Jax", "championTransform": 0, "commandPings": 2, "consumablesPurchased": 2, "damageDealtToBuildings": 0, "damageDealtToObjectives": 0, "damageDealtToTurrets": 0, "damageSelfMitigated": 3120, "dangerPings": 0, "deaths": 3, "detectorWardsPlaced": 1, "doubleKills": 0, "dragonKills": 0, "eligibleForProgression": true, "enemyMissingPings": 2, "enemyVisionPings": 5, "firstBloodAssist": false, "firstBloodKill": false, "firstTowerAssist": false, "firstTowerKill": false, "gameEndedInEarlySurrender": false, "gameEndedInSurrender": true, "getBackPings": 3, "goldEarned": 4019, "goldSpent": 3075, "holdPings": 0, "individualPosition": "TOP", "inhibitorKills": 0, "inhibitorTakedowns": 0, "inhibitorsLost": 0, "item0": 3057, "item1": 2031, "item2": 1028, "item3": 1036, "item4": 3009, "item5": 1055, "item6": 3340, "itemsPurchased": 9, "killingSprees": 0, "kills": 1, "lane": "NONE", "largestCriticalStrike": 0, "largestKillingSpree": 0, "largestMultiKill": 1, "longestTimeSpentLiving": 239, "magicDamageDealt": 11267, "magicDamageDealtToChampions": 916, "magicDamageTaken": 784, "needVisionPings": 0, "neutralMinionsKilled": 0, "nexusKills": 0, "nexusLost": 0, "nexusTakedowns": 0, "objectivesStolen": 0, "objectivesStolenAssists": 0, "onMyWayPings": 3, "participantId": 1, "pentaKills": 0, "perks": {"statPerks": {"defense": 5001, "flex": 5008, "offense": 5005}, "styles": [{"description": "primaryStyle", "selections": [{"perk": 8008, "var1": 12, "var2": 0, "var3": 0}, {"perk": 9111, "var1": 117, "var2": 60, "var3": 0}, {"perk": 9105, "var1": 0, "var2": 0, "var3": 0}, {"perk": 8299, "var1": 66, "var2": 0, "var3": 0}], "style": 8000}, {"description": "subStyle", "selections": [{"perk": 8347, "var1": 0, "var2": 0, "var3": 0}, {"perk": 8345, "var1": 3, "var2": 0, "var3": 0}], "style": 8300}]}, "physicalDamageDealt": 17227, "physicalDamageDealtToChampions": 1574, "physicalDamageTaken": 6597, "placement": 0, "playerAugment1": 0, "playerAugment2": 0, "playerAugment3": 0, "playerAugment4": 0, "playerSubteamId": 0, "profileIcon": 4, "pushPings": 0, "puuid": "4-s6dr5s1WJ-hiTjZy1B0CeAbQKtEveAiOCe_rHNILIrf3y1pJCg0evTYSbGnUjTeVINRNhhGb1Kbw", "quadraKills": 0, "riotIdName": "", "riotIdTagline": "", "role": "SUPPORT", "sightWardsBoughtInGame": 0, "spell1Casts": 22, "spell2Casts": 31, "spell3Casts": 30, "spell4Casts": 0, "subteamPlacement": 0, "summoner1Casts": 2, "summoner1Id": 4, "summoner2Casts": 2, "summoner2Id": 14, "summonerId": "EaMeW1rDAXxDFKcdd1KGtOUPPNhqm7Mlc0AMrrE6jQPfdj9llugSpPHNNg", "summonerLevel": 62, "summonerName": "TF Blade2", "teamEarlySurrendered": false, "teamId": 100, "teamPosition": "TOP", "timeCCingOthers": 8, "timePlayed": 912, "totalAllyJungleMinionsKilled": 0, "totalDamageDealt": 34022, "totalDamageDealtToChampions": 2734, "totalDamageShieldedOnTeammates": 0, "totalDamageTaken": 7541, "totalEnemyJungleMinionsKilled": 0, "totalHeal": 365, "totalHealsOnTeammates": 0, "totalMinionsKilled": 65, "totalTimeCCDealt": 52, "totalTimeSpentDead": 36, "totalUnitsHealed": 1, "tripleKills": 0, "trueDamageDealt": 5527, "trueDamageDealtToChampions": 242, "trueDamageTaken": 159, "turretKills": 0, "turretTakedowns": 0, "turretsLost": 3, "unrealKills": 0, "visionClearedPings": 0, "visionScore": 14, "visionWardsBoughtInGame": 1, "wardsKilled": 0, "wardsPlaced": 6, "win": false}, {"allInPings": 0, "assistMePings": 2, "assists": 1, "baitPings": 0, "baronKills": 0, "basicPings": 0, "bountyLevel": 0, "challenges": {"12AssistStreakCount": 0, "abilityUses": 106, "acesBefore15Minutes": 0, "alliedJungleMonsterKills": 51, "baronTakedowns": 0, "blastConeOppositeOpponentCount": 0, "bountyGold": 0, "buffsStolen": 0, "completeSupportQuestInTime": 0, "controlWardTimeCoverageInRiverOrEnemyHalf": 0.3757337410133738, "controlWardsPlaced": 3, "damagePerMinute": 285.5877421683061, "damageTakenOnTeamPercentage": 0.316198962854615, "dancedWithRiftHerald": 0, "deathsByEnemyChamps": 5, "dodgeSkillShotsSmallWindow": 0, "doubleAces": 0, "dragonTakedowns": 0, "earlyLaningPhaseGoldExpAdvantage": 0, "effectiveHealAndShielding": 0, "elderDragonKillsWithOpposingSoul": 0, "elderDragonMultikills": 0, "enemyChampionImmobilizations": 4, "enemyJungleMonsterKills": 5, "epicMonsterKillsNearEnemyJungler": 0, "epicMonsterKillsWithin30SecondsOfSpawn": 0, "epicMonsterSteals": 0, "epicMonsterStolenWithoutSmite": 0, "firstTurretKilled": 0, "flawlessAces": 0, "fullTeamTakedown": 0, "gameLength": 912.5629653999999, "goldPerMinute": 312.11992249367916, "hadOpenNexus": 0, "highestCrowdControlScore": 1, "immobilizeAndKillWithAlly": 2, "initialBuffCount": 1, "initialCrabCount": 2, "jungleCsBefore10Minutes": 54.00000011920929, "junglerKillsEarlyJungle": 0, "junglerTakedownsNearDamagedEpicMonster": 0, "kTurretsDestroyedBeforePlatesFall": 0, "kda": 0.4, "killAfterHiddenWithAlly": 0, "killParticipation": 0.2857142857142857, "killedChampTookFullTeamDamageSurvived": 0, "killingSprees": 0, "killsNearEnemyTurret": 0, "killsOnLanersEarlyJungleAsJungler": 0, "killsOnRecentlyHealedByAramPack": 0, "killsUnderOwnTurret": 0, "killsWithHelpFromEpicMonster": 0, "knockEnemyIntoTeamAndKill": 0, "landSkillShotsEarlyGame": 3, "laneMinionsFirst10Minutes": 1, "laningPhaseGoldExpAdvantage": 0, "legendaryCount": 0, "lostAnInhibitor": 0, "maxCsAdvantageOnLaneOpponent": 8.000000059604645, "maxKillDeficit": 0, "maxLevelLeadLaneOpponent": 1, "mejaisFullStackInTime": 0, "moreEnemyJungleThanOpponent": -45.00000002980232, "multiKillOneSpell": 0, "multiTurretRiftHeraldCount": 0, "multikills": 0, "multikillsAfterAggressiveFlash": 0, "outerTurretExecutesBefore10Minutes": 0, "outnumberedKills": 1, "outnumberedNexusKill": 0, "perfectDragonSoulsTaken": 0, "perfectGame": 0, "pickKillWithAlly": 2, "playedChampSelectPosition": 1, "poroExplosions": 0, "quickCleanse": 0, "quickFirstTurret": 0, "quickSoloKills": 0, "riftHeraldTakedowns": 0, "saveAllyFromDeath": 0, "scuttleCrabKills": 3, "skillshotsDodged": 8, "skillshotsHit": 10, "snowballsHit": 0, "soloBaronKills": 0, "soloKills": 0, "stealthWardsPlaced": 2, "survivedSingleDigitHpCount": 0, "survivedThreeImmobilizesInFight": 0, "takedownOnFirstTurret": 0, "takedowns": 2, "takedownsAfterGainingLevelAdvantage": 0, "takedownsBeforeJungleMinionSpawn": 0, "takedownsFirstXMinutes": 2, "takedownsInAlcove": 0, "takedownsInEnemyFountain": 0, "teamBaronKills": 0, "teamDamagePercentage": 0.188918074964886, "teamElderDragonKills": 0, "teamRiftHeraldKills": 0, "tookLargeDamageSurvived": 0, "turretPlatesTaken": 0, "turretTakedowns": 0, "turretsTakenWithRiftHerald": 0, "twentyMinionsIn3SecondsCount": 0, "twoWardsOneSweeperCount": 0, "unseenRecalls": 0, "visionScoreAdvantageLaneOpponent": -0.14314383268356323, "visionScorePerMinute": 0.939878223861605, "wardTakedowns": 2, "wardTakedownsBefore20M": 2, "wardsGuarded": 2}, "champExperience": 5064, "champLevel": 9, "championId": 56, "championName": "Nocturne", "championTransform": 0, "commandPings": 8, "consumablesPurchased": 6, "damageDealtToBuildings": 0, "damageDealtToObjectives": 4351, "damageDealtToTurrets": 0, "damageSelfMitigated": 7119, "dangerPings": 0, "deaths": 5, "detectorWardsPlaced": 3, "doubleKills": 0, "dragonKills": 0, "eligibleForProgression": true, "enemyMissingPings": 3, "enemyVisionPings": 5, "firstBloodAssist": false, "firstBloodKill": false, "firstTowerAssist": false, "firstTowerKill": false, "gameEndedInEarlySurrender": false, "gameEndedInSurrender": true, "getBackPings": 8, "goldEarned": 4747, "goldSpent": 4450, "holdPings": 0, "individualPosition": "JUNGLE", "inhibitorKills": 0, "inhibitorTakedowns": 0, "inhibitorsLost": 0, "item0": 6631, "item1": 1001, "item2": 1103, "item3": 2055, "item4": 0, "item5": 0, "item6": 3364, "itemsPurchased": 14, "killingSprees": 0, "kills": 1, "lane": "NONE", "largestCriticalStrike": 0, "largestKillingSpree": 0, "largestMultiKill": 1, "longestTimeSpentLiving": 223, "magicDamageDealt": 1506, "magicDamageDealtToChampions": 226, "magicDamageTaken": 2211, "needVisionPings": 0, "neutralMinionsKilled": 87, "nexusKills": 0, "nexusLost": 0, "nexusTakedowns": 0, "objectivesStolen": 0, "objectivesStolenAssists": 0, "onMyWayPings": 10, "participantId": 2, "pentaKills": 0, "perks": {"statPerks": {"defense": 5002, "flex": 5008, "offense": 5005}, "styles": [{"description": "primaryStyle", "selections": [{"perk": 8008, "var1": 17, "var2": 1, "var3": 0}, {"perk": 9111, "var1": 44, "var2": 40, "var3": 0}, {"perk": 9104, "var1": 0, "var2": 0, "var3": 0}, {"perk": 8014, "var1": 52, "var2": 0, "var3": 0}], "style": 8000}, {"description": "subStyle", "selections": [{"perk": 8106, "var1": 1, "var2": 0, "var3": 0}, {"perk": 8138, "var1": 2, "var2": 0, "var3": 0}], "style": 8100}]}, "physicalDamageDealt": 68263, "physicalDamageDealtToChampions": 4055, "physicalDamageTaken": 10873, "placement": 0, "playerAugment1": 0, "playerAugment2": 0, "playerAugment3": 0, "playerAugment4": 0, "playerSubteamId": 0, "profileIcon": 5848, "pushPings": 0, "puuid": "CLM40viH26FxSWXPmGp4ZEmjgGHFj02ByWEGKyn6CxmsMVM9dBSHlTQ4A35st8yVddyEoV3iI_1jWg", "quadraKills": 0, "riotIdName": "", "riotIdTagline": "", "role": "SUPPORT", "sightWardsBoughtInGame": 0, "spell1Casts": 71, "spell2Casts": 6, "spell3Casts": 25, "spell4Casts": 4, "subteamPlacement": 0, "summoner1Casts": 2, "summoner1Id": 4, "summoner2Casts": 9, "summoner2Id": 11, "summonerId": "2aAgazC8FeOK12_WhLYDcpkx8v7rGeBWpqvtMXX79vb0Zx0AErRFy8SCog", "summonerLevel": 355, "summonerName": "DRX \uc601\uc28c", "teamEarlySurrendered": false, "teamId": 100, "teamPosition": "JUNGLE", "timeCCingOthers": 38, "timePlayed": 912, "totalAllyJungleMinionsKilled": 66, "totalDamageDealt": 87456, "totalDamageDealtToChampions": 4343, "totalDamageShieldedOnTeammates": 0, "totalDamageTaken": 13229, "totalEnemyJungleMinionsKilled": 2, "totalHeal": 6526, "totalHealsOnTeammates": 0, "totalMinionsKilled": 2, "totalTimeCCDealt": 200, "totalTimeSpentDead": 71, "totalUnitsHealed": 1, "tripleKills": 0, "trueDamageDealt": 17685, "trueDamageDealtToChampions": 61, "trueDamageTaken": 144, "turretKills": 0, "turretTakedowns": 0, "turretsLost": 3, "unrealKills": 0, "visionClearedPings": 0, "visionScore": 14, "visionWardsBoughtInGame": 4, "wardsKilled": 2, "wardsPlaced": 5, "win": false}, {"allInPings": 0, "assistMePings": 0, "assists": 1, "baitPings": 0, "baronKills": 0, "basicPings": 0, "bountyLevel": 0, "challenges": {"12AssistStreakCount": 0, "abilityUses": 190, "acesBefore15Minutes": 0, "alliedJungleMonsterKills": 0, "baronTakedowns": 0, "blastConeOppositeOpponentCount": 0, "bountyGold": 150, "buffsStolen": 0, "completeSupportQuestInTime": 0, "controlWardTimeCoverageInRiverOrEnemyHalf": 0.3880175415016902, "controlWardsPlaced": 4, "damagePerMinute": 515.2297300454311, "damageTakenOnTeamPercentage": 0.20762938444461176, "dancedWithRiftHerald": 0, "deathsByEnemyChamps": 4, "dodgeSkillShotsSmallWindow": 3, "doubleAces": 0, "dragonTakedowns": 0, "earlyLaningPhaseGoldExpAdvantage": 0, "effectiveHealAndShielding": 0, "elderDragonKillsWithOpposingSoul": 0, "elderDragonMultikills": 0, "enemyChampionImmobilizations": 5, "enemyJungleMonsterKills": 0, "epicMonsterKillsNearEnemyJungler": 0, "epicMonsterKillsWithin30SecondsOfSpawn": 0, "epicMonsterSteals": 0, "epicMonsterStolenWithoutSmite": 0, "firstTurretKilled": 0, "flawlessAces": 0, "fullTeamTakedown": 0, "gameLength": 912.5629653999999, "getTakedownsInAllLanesEarlyJungleAsLaner": 0, "goldPerMinute": 418.6944713364488, "hadOpenNexus": 0, "immobilizeAndKillWithAlly": 1, "initialBuffCount": 0, "initialCrabCount": 0, "jungleCsBefore10Minutes": 0, "junglerTakedownsNearDamagedEpicMonster": 0, "kTurretsDestroyedBeforePlatesFall": 0, "kda": 0.75, "killAfterHiddenWithAlly": 0, "killParticipation": 0.42857142857142855, "killedChampTookFullTeamDamageSurvived": 0, "killingSprees": 0, "killsNearEnemyTurret": 1, "killsOnOtherLanesEarlyJungleAsLaner": 0, "killsOnRecentlyHealedByAramPack": 0, "killsUnderOwnTurret": 0, "killsWithHelpFromEpicMonster": 0, "knockEnemyIntoTeamAndKill": 0, "landSkillShotsEarlyGame": 8, "laneMinionsFirst10Minutes": 89, "laningPhaseGoldExpAdvantage": 0, "legendaryCount": 0, "lostAnInhibitor": 0, "maxCsAdvantageOnLaneOpponent": 5, "maxKillDeficit": 0, "maxLevelLeadLaneOpponent": 1, "mejaisFullStackInTime": 0, "moreEnemyJungleThanOpponent": 0, "multiKillOneSpell": 0, "multiTurretRiftHeraldCount": 0, "multikills": 0, "multikillsAfterAggressiveFlash": 0, "outerTurretExecutesBefore10Minutes": 0, "outnumberedKills": 0, "outnumberedNexusKill": 0, "perfectDragonSoulsTaken": 0, "perfectGame": 0, "pickKillWithAlly": 3, "playedChampSelectPosition": 1, "poroExplosions": 0, "quickCleanse": 0, "quickFirstTurret": 0, "quickSoloKills": 0, "riftHeraldTakedowns": 0, "saveAllyFromDeath": 0, "scuttleCrabKills": 0, "skillshotsDodged": 20, "skillshotsHit": 23, "snowballsHit": 0, "soloBaronKills": 0, "soloKills": 0, "stealthWardsPlaced": 5, "survivedSingleDigitHpCount": 0, "survivedThreeImmobilizesInFight": 0, "takedownOnFirstTurret": 0, "takedowns": 3, "takedownsAfterGainingLevelAdvantage": 0, "takedownsBeforeJungleMinionSpawn": 0, "takedownsFirstXMinutes": 3, "takedownsInAlcove": 0, "takedownsInEnemyFountain": 0, "teamBaronKills": 0, "teamDamagePercentage": 0.3408276840800028, "teamElderDragonKills": 0, "teamRiftHeraldKills": 0, "tookLargeDamageSurvived": 0, "turretPlatesTaken": 1, "turretTakedowns": 0, "turretsTakenWithRiftHerald": 0, "twentyMinionsIn3SecondsCount": 6, "twoWardsOneSweeperCount": 0, "unseenRecalls": 0, "visionScoreAdvantageLaneOpponent": 0.20922935009002686, "visionScorePerMinute": 1.0009790617549836, "wardTakedowns": 2, "wardTakedownsBefore20M": 2, "wardsGuarded": 1}, "champExperience": 7469, "champLevel": 11, "championId": 126, "championName": "Jayce", "championTransform": 0, "commandPings": 0, "consumablesPurchased": 5, "damageDealtToBuildings": 637, "damageDealtToObjectives": 2214, "damageDealtToTurrets": 637, "damageSelfMitigated": 4952, "dangerPings": 0, "deaths": 4, "detectorWardsPlaced": 4, "doubleKills": 0, "dragonKills": 0, "eligibleForProgression": true, "enemyMissingPings": 7, "enemyVisionPings": 1, "firstBloodAssist": false, "firstBloodKill": false, "firstTowerAssist": false, "firstTowerKill": false, "gameEndedInEarlySurrender": false, "gameEndedInSurrender": true, "getBackPings": 0, "goldEarned": 6368, "goldSpent": 5950, "holdPings": 0, "individualPosition": "MIDDLE", "inhibitorKills": 0, "inhibitorTakedowns": 0, "inhibitorsLost": 0, "item0": 1055, "item1": 1036, "item2": 6691, "item3": 1036, "item4": 3111, "item5": 3070, "item6": 3363, "itemsPurchased": 19, "killingSprees": 1, "kills": 2, "lane": "NONE", "largestCriticalStrike": 0, "largestKillingSpree": 2, "largestMultiKill": 1, "longestTimeSpentLiving": 317, "magicDamageDealt": 5393, "magicDamageDealtToChampions": 1404, "magicDamageTaken": 3726, "needVisionPings": 0, "neutralMinionsKilled": 0, "nexusKills": 0, "nexusLost": 0, "nexusTakedowns": 0, "objectivesStolen": 0, "objectivesStolenAssists": 0, "onMyWayPings": 2, "participantId": 3, "pentaKills": 0, "perks": {"statPerks": {"defense": 5003, "flex": 5008, "offense": 5008}, "styles": [{"description": "primaryStyle", "selections": [{"perk": 8369, "var1": 417, "var2": 359, "var3": 0}, {"perk": 8304, "var1": 11, "var2": 1, "var3": 5}, {"perk": 8345, "var1": 3, "var2": 0, "var3": 0}, {"perk": 8347, "var1": 0, "var2": 0, "var3": 0}], "style": 8300}, {"description": "subStyle", "selections": [{"perk": 8226, "var1": 250, "var2": 362, "var3": 0}, {"perk": 8210, "var1": 0, "var2": 0, "var3": 0}], "style": 8200}]}, "physicalDamageDealt": 54667, "physicalDamageDealtToChampions": 6024, "physicalDamageTaken": 4789, "placement": 0, "playerAugment1": 0, "playerAugment2": 0, "playerAugment3": 0, "playerAugment4": 0, "playerSubteamId": 0, "profileIcon": 3584, "pushPings": 0, "puuid": "yCheQFpNtJcRPUGBYaHbaILHSpnT_GjRU16x0iOjb-AdCYGUG0y5aztx97NRwg5bt473teujGQ3Kcg", "quadraKills": 0, "riotIdName": "", "riotIdTagline": "", "role": "DUO", "sightWardsBoughtInGame": 0, "spell1Casts": 67, "spell2Casts": 37, "spell3Casts": 33, "spell4Casts": 53, "subteamPlacement": 0, "summoner1Casts": 2, "summoner1Id": 12, "summoner2Casts": 2, "summoner2Id": 4, "summonerId": "kYWtuIJi4XjzfsuU3DURKRE6AgW1QkZQZCvDzC6w4SmtdzA", "summonerLevel": 487, "summonerName": "\ucd5c\uace0\uc758\uc804\ud22c\uae30\uae4c\uc9c0", "teamEarlySurrendered": false, "teamId": 100, "teamPosition": "MIDDLE", "timeCCingOthers": 4, "timePlayed": 912, "totalAllyJungleMinionsKilled": 0, "totalDamageDealt": 62284, "totalDamageDealtToChampions": 7836, "totalDamageShieldedOnTeammates": 0, "totalDamageTaken": 8687, "totalEnemyJungleMinionsKilled": 0, "totalHeal": 409, "totalHealsOnTeammates": 0, "totalMinionsKilled": 141, "totalTimeCCDealt": 88, "totalTimeSpentDead": 95, "totalUnitsHealed": 1, "tripleKills": 0, "trueDamageDealt": 2222, "trueDamageDealtToChampions": 407, "trueDamageTaken": 170, "turretKills": 0, "turretTakedowns": 0, "turretsLost": 3, "unrealKills": 0, "visionClearedPings": 0, "visionScore": 15, "visionWardsBoughtInGame": 4, "wardsKilled": 2, "wardsPlaced": 9, "win": false}, {"allInPings": 1, "assistMePings": 1, "assists": 0, "baitPings": 1, "baronKills": 0, "basicPings": 0, "bountyLevel": 0, "challenges": {"12AssistStreakCount": 0, "abilityUses": 217, "acesBefore15Minutes": 0, "alliedJungleMonsterKills": 0, "baronTakedowns": 0, "blastConeOppositeOpponentCount": 0, "bountyGold": 0, "buffsStolen": 0, "completeSupportQuestInTime": 0, "controlWardsPlaced": 1, "damagePerMinute": 321.5197019612144, "damageTakenOnTeamPercentage": 0.15306693765200738, "dancedWithRiftHerald": 0, "deathsByEnemyChamps": 1, "dodgeSkillShotsSmallWindow": 1, "doubleAces": 0, "dragonTakedowns": 0, "earlyLaningPhaseGoldExpAdvantage": 0, "effectiveHealAndShielding": 0, "elderDragonKillsWithOpposingSoul": 0, "elderDragonMultikills": 0, "enemyChampionImmobilizations": 8, "enemyJungleMonsterKills": 0, "epicMonsterKillsNearEnemyJungler": 0, "epicMonsterKillsWithin30SecondsOfSpawn": 0, "epicMonsterSteals": 0, "epicMonsterStolenWithoutSmite": 0, "firstTurretKilled": 0, "flawlessAces": 0, "fullTeamTakedown": 0, "gameLength": 912.5629653999999, "getTakedownsInAllLanesEarlyJungleAsLaner": 0, "goldPerMinute": 352.31766242050264, "hadOpenNexus": 0, "immobilizeAndKillWithAlly": 2, "initialBuffCount": 0, "initialCrabCount": 0, "jungleCsBefore10Minutes": 0, "junglerTakedownsNearDamagedEpicMonster": 0, "kTurretsDestroyedBeforePlatesFall": 0, "kda": 3, "killAfterHiddenWithAlly": 0, "killParticipation": 0.42857142857142855, "killedChampTookFullTeamDamageSurvived": 0, "killingSprees": 1, "killsNearEnemyTurret": 1, "killsOnOtherLanesEarlyJungleAsLaner": 0, "killsOnRecentlyHealedByAramPack": 0, "killsUnderOwnTurret": 0, "killsWithHelpFromEpicMonster": 0, "knockEnemyIntoTeamAndKill": 0, "landSkillShotsEarlyGame": 12, "laneMinionsFirst10Minutes": 60, "laningPhaseGoldExpAdvantage": 0, "legendaryCount": 0, "lostAnInhibitor": 0, "maxCsAdvantageOnLaneOpponent": 0, "maxKillDeficit": 0, "maxLevelLeadLaneOpponent": 1, "mejaisFullStackInTime": 0, "moreEnemyJungleThanOpponent": 0, "multiKillOneSpell": 0, "multiTurretRiftHeraldCount": 0, "multikills": 0, "multikillsAfterAggressiveFlash": 0, "outerTurretExecutesBefore10Minutes": 0, "outnumberedKills": 0, "outnumberedNexusKill": 0, "perfectDragonSoulsTaken": 0, "perfectGame": 0, "pickKillWithAlly": 3, "playedChampSelectPosition": 1, "poroExplosions": 0, "quickCleanse": 2, "quickFirstTurret": 0, "quickSoloKills": 0, "riftHeraldTakedowns": 0, "saveAllyFromDeath": 0, "scuttleCrabKills": 0, "skillshotsDodged": 10, "skillshotsHit": 26, "snowballsHit": 0, "soloBaronKills": 0, "soloKills": 0, "stealthWardsPlaced": 5, "survivedSingleDigitHpCount": 0, "survivedThreeImmobilizesInFight": 2, "takedownOnFirstTurret": 0, "takedowns": 3, "takedownsAfterGainingLevelAdvantage": 0, "takedownsBeforeJungleMinionSpawn": 0, "takedownsFirstXMinutes": 3, "takedownsInAlcove": 0, "takedownsInEnemyFountain": 0, "teamBaronKills": 0, "teamDamagePercentage": 0.212687290766142, "teamElderDragonKills": 0, "teamRiftHeraldKills": 0, "tookLargeDamageSurvived": 0, "turretPlatesTaken": 0, "turretTakedowns": 0, "turretsTakenWithRiftHerald": 0, "twentyMinionsIn3SecondsCount": 4, "twoWardsOneSweeperCount": 0, "unseenRecalls": 0, "visionScoreAdvantageLaneOpponent": -0.3535519242286682, "visionScorePerMinute": 0.6713294420007581, "wardTakedowns": 1, "wardTakedownsBefore20M": 1, "wardsGuarded": 0}, "champExperience": 5198, "champLevel": 9, "championId": 523, "championName": "Aphelios", "championTransform": 0, "commandPings": 3, "consumablesPurchased": 2, "damageDealtToBuildings": 20, "damageDealtToObjectives": 20, "damageDealtToTurrets": 20, "damageSelfMitigated": 2985, "dangerPings": 0, "deaths": 1, "detectorWardsPlaced": 1, "doubleKills": 0, "dragonKills": 0, "eligibleForProgression": true, "enemyMissingPings": 11, "enemyVisionPings": 5, "firstBloodAssist": false, "firstBloodKill": false, "firstTowerAssist": false, "firstTowerKill": false, "gameEndedInEarlySurrender": false, "gameEndedInSurrender": true, "getBackPings": 6, "goldEarned": 5358, "goldSpent": 5175, "holdPings": 0, "individualPosition": "BOTTOM", "inhibitorKills": 0, "inhibitorTakedowns": 0, "inhibitorsLost": 0, "item0": 1055, "item1": 2031, "item2": 6672, "item3": 1036, "item4": 3006, "item5": 0, "item6": 3363, "itemsPurchased": 14, "killingSprees": 1, "kills": 3, "lane": "NONE", "largestCriticalStrike": 300, "largestKillingSpree": 3, "largestMultiKill": 1, "longestTimeSpentLiving": 859, "magicDamageDealt": 2796, "magicDamageDealtToChampions": 656, "magicDamageTaken": 827, "needVisionPings": 0, "neutralMinionsKilled": 0, "nexusKills": 0, "nexusLost": 0, "nexusTakedowns": 0, "objectivesStolen": 0, "objectivesStolenAssists": 0, "onMyWayPings": 8, "participantId": 4, "pentaKills": 0, "perks": {"statPerks": {"defense": 5002, "flex": 5008, "offense": 5008}, "styles": [{"description": "primaryStyle", "selections": [{"perk": 8008, "var1": 25, "var2": 3, "var3": 0}, {"perk": 9101, "var1": 31, "var2": 47, "var3": 0}, {"perk": 9103, "var1": 0, "var2": 0, "var3": 0}, {"perk": 8017, "var1": 149, "var2": 0, "var3": 0}], "style": 8000}, {"description": "subStyle", "selections": [{"perk": 8233, "var1": 4, "var2": 40, "var3": 0}, {"perk": 8236, "var1": 4, "var2": 0, "var3": 0}], "style": 8200}]}, "physicalDamageDealt": 35270, "physicalDamageDealtToChampions": 4234, "physicalDamageTaken": 5491, "placement": 0, "playerAugment1": 0, "playerAugment2": 0, "playerAugment3": 0, "playerAugment4": 0, "playerSubteamId": 0, "profileIcon": 23, "pushPings": 0, "puuid": "azmetsJMURbhheBhUntzl8VNraeBfzs0-Bepsr-33CoPd5FCcQ398ACIyIXz4Y0Wb6QwFyOhB_GSzw", "quadraKills": 0, "riotIdName": "", "riotIdTagline": "", "role": "SUPPORT", "sightWardsBoughtInGame": 0, "spell1Casts": 31, "spell2Casts": 183, "spell3Casts": 0, "spell4Casts": 3, "subteamPlacement": 0, "summoner1Casts": 2, "summoner1Id": 4, "summoner2Casts": 2, "summoner2Id": 1, "summonerId": "bh_p2U-EPG6HuucKDSvLyE9BotaEjKVpREorR6VGg8AT5NKnYigaoI0gUQ", "summonerLevel": 331, "summonerName": "ADC0419", "teamEarlySurrendered": false, "teamId": 100, "teamPosition": "BOTTOM", "timeCCingOthers": 12, "timePlayed": 912, "totalAllyJungleMinionsKilled": 0, "totalDamageDealt": 38067, "totalDamageDealtToChampions": 4890, "totalDamageShieldedOnTeammates": 0, "totalDamageTaken": 6404, "totalEnemyJungleMinionsKilled": 0, "totalHeal": 1364, "totalHealsOnTeammates": 0, "totalMinionsKilled": 119, "totalTimeCCDealt": 52, "totalTimeSpentDead": 30, "totalUnitsHealed": 1, "tripleKills": 0, "trueDamageDealt": 0, "trueDamageDealtToChampions": 0, "trueDamageTaken": 85, "turretKills": 0, "turretTakedowns": 0, "turretsLost": 3, "unrealKills": 0, "visionClearedPings": 1, "visionScore": 10, "visionWardsBoughtInGame": 1, "wardsKilled": 1, "wardsPlaced": 6, "win": false}, {"allInPings": 0, "assistMePings": 6, "assists": 6, "baitPings": 0, "baronKills": 0, "basicPings": 0, "bountyLevel": 0, "challenges": {"12AssistStreakCount": 0, "abilityUses": 74, "acesBefore15Minutes": 0, "alliedJungleMonsterKills": 0, "baronTakedowns": 0, "blastConeOppositeOpponentCount": 0, "bountyGold": 0, "buffsStolen": 0, "completeSupportQuestInTime": 0, "controlWardTimeCoverageInRiverOrEnemyHalf": 0.44886267318601397, "controlWardsPlaced": 2, "damagePerMinute": 209.60156315306625, "damageTakenOnTeamPercentage": 0.14286080396809478, "dancedWithRiftHerald": 0, "deathsByEnemyChamps": 2, "dodgeSkillShotsSmallWindow": 1, "doubleAces": 0, "dragonTakedowns": 0, "earlyLaningPhaseGoldExpAdvantage": 0, "effectiveHealAndShielding": 387.015869140625, "elderDragonKillsWithOpposingSoul": 0, "elderDragonMultikills": 0, "enemyChampionImmobilizations": 25, "enemyJungleMonsterKills": 0, "epicMonsterKillsNearEnemyJungler": 0, "epicMonsterKillsWithin30SecondsOfSpawn": 0, "epicMonsterSteals": 0, "epicMonsterStolenWithoutSmite": 0, "firstTurretKilled": 0, "flawlessAces": 0, "fullTeamTakedown": 0, "gameLength": 912.5629653999999, "getTakedownsInAllLanesEarlyJungleAsLaner": 0, "goldPerMinute": 252.31267309971312, "hadOpenNexus": 0, "immobilizeAndKillWithAlly": 6, "initialBuffCount": 0, "initialCrabCount": 0, "jungleCsBefore10Minutes": 0, "junglerTakedownsNearDamagedEpicMonster": 0, "kTurretsDestroyedBeforePlatesFall": 0, "kda": 3, "killAfterHiddenWithAlly": 0, "killParticipation": 0.8571428571428571, "killedChampTookFullTeamDamageSurvived": 0, "killingSprees": 0, "killsNearEnemyTurret": 0, "killsOnOtherLanesEarlyJungleAsLaner": 0, "killsOnRecentlyHealedByAramPack": 0, "killsUnderOwnTurret": 0, "killsWithHelpFromEpicMonster": 0, "knockEnemyIntoTeamAndKill": 2, "landSkillShotsEarlyGame": 0, "laneMinionsFirst10Minutes": 21, "laningPhaseGoldExpAdvantage": 0, "legendaryCount": 0, "lostAnInhibitor": 0, "maxCsAdvantageOnLaneOpponent": 7, "maxKillDeficit": 0, "maxLevelLeadLaneOpponent": 1, "mejaisFullStackInTime": 0, "moreEnemyJungleThanOpponent": 0, "multiKillOneSpell": 0, "multiTurretRiftHeraldCount": 0, "multikills": 0, "multikillsAfterAggressiveFlash": 0, "outerTurretExecutesBefore10Minutes": 0, "outnumberedKills": 0, "outnumberedNexusKill": 0, "perfectDragonSoulsTaken": 0, "perfectGame": 0, "pickKillWithAlly": 6, "playedChampSelectPosition": 1, "poroExplosions": 0, "quickCleanse": 0, "quickFirstTurret": 0, "quickSoloKills": 0, "riftHeraldTakedowns": 0, "saveAllyFromDeath": 12, "scuttleCrabKills": 0, "skillshotsDodged": 9, "skillshotsHit": 0, "snowballsHit": 0, "soloBaronKills": 0, "soloKills": 0, "stealthWardsPlaced": 10, "survivedSingleDigitHpCount": 0, "survivedThreeImmobilizesInFight": 4, "takedownOnFirstTurret": 0, "takedowns": 6, "takedownsAfterGainingLevelAdvantage": 0, "takedownsBeforeJungleMinionSpawn": 0, "takedownsFirstXMinutes": 6, "takedownsInAlcove": 0, "takedownsInEnemyFountain": 0, "teamBaronKills": 0, "teamDamagePercentage": 0.13865274300593813, "teamElderDragonKills": 0, "teamRiftHeraldKills": 0, "tookLargeDamageSurvived": 0, "turretPlatesTaken": 0, "turretTakedowns": 0, "turretsTakenWithRiftHerald": 0, "twentyMinionsIn3SecondsCount": 0, "twoWardsOneSweeperCount": 0, "unseenRecalls": 0, "visionScoreAdvantageLaneOpponent": -0.0004913806915283203, "visionScorePerMinute": 1.721763884921917, "wardTakedowns": 3, "wardTakedownsBefore20M": 3, "wardsGuarded": 1}, "champExperience": 4229, "champLevel": 8, "championId": 526, "championName": "Rell", "championTransform": 0, "commandPings": 1, "consumablesPurchased": 6, "damageDealtToBuildings": 0, "damageDealtToObjectives": 0, "damageDealtToTurrets": 0, "damageSelfMitigated": 5828, "dangerPings": 0, "deaths": 2, "detectorWardsPlaced": 2, "doubleKills": 0, "dragonKills": 0, "eligibleForProgression": true, "enemyMissingPings": 1, "enemyVisionPings": 8, "firstBloodAssist": false, "firstBloodKill": false, "firstTowerAssist": false, "firstTowerKill": false, "gameEndedInEarlySurrender": false, "gameEndedInSurrender": true, "getBackPings": 3, "goldEarned": 3837, "goldSpent": 3550, "holdPings": 0, "individualPosition": "UTILITY", "inhibitorKills": 0, "inhibitorTakedowns": 0, "inhibitorsLost": 0, "item0": 1033, "item1": 2055, "item2": 3859, "item3": 3158, "item4": 1029, "item5": 1011, "item6": 3364, "itemsPurchased": 14, "killingSprees": 0, "kills": 0, "lane": "NONE", "largestCriticalStrike": 0, "largestKillingSpree": 0, "largestMultiKill": 0, "longestTimeSpentLiving": 435, "magicDamageDealt": 5858, "magicDamageDealtToChampions": 1707, "magicDamageTaken": 2034, "needVisionPings": 0, "neutralMinionsKilled": 0, "nexusKills": 0, "nexusLost": 0, "nexusTakedowns": 0, "objectivesStolen": 0, "objectivesStolenAssists": 0, "onMyWayPings": 13, "participantId": 5, "pentaKills": 0, "perks": {"statPerks": {"defense": 5002, "flex": 5002, "offense": 5007}, "styles": [{"description": "primaryStyle", "selections": [{"perk": 8439, "var1": 276, "var2": 222, "var3": 0}, {"perk": 8463, "var1": 561, "var2": 0, "var3": 0}, {"perk": 8444, "var1": 256, "var2": 0, "var3": 0}, {"perk": 8242, "var1": 19, "var2": 0, "var3": 0}], "style": 8400}, {"description": "subStyle", "selections": [{"perk": 8306, "var1": 3, "var2": 0, "var3": 0}, {"perk": 8316, "var1": 443, "var2": 0, "var3": 0}], "style": 8300}]}, "physicalDamageDealt": 3017, "physicalDamageDealtToChampions": 990, "physicalDamageTaken": 3579, "placement": 0, "playerAugment1": 0, "playerAugment2": 0, "playerAugment3": 0, "playerAugment4": 0, "playerSubteamId": 0, "profileIcon": 23, "pushPings": 0, "puuid": "pSeLNn_nBykkSOwZHxfLx53y1tBXss5stPpbPReGEG83EOGF9XRDQwLliUNla4DO9p3gK_TwPG0KGw", "quadraKills": 0, "riotIdName": "", "riotIdTagline": "", "role": "SUPPORT", "sightWardsBoughtInGame": 0, "spell1Casts": 18, "spell2Casts": 22, "spell3Casts": 31, "spell4Casts": 3, "subteamPlacement": 0, "summoner1Casts": 3, "summoner1Id": 14, "summoner2Casts": 5, "summoner2Id": 4, "summonerId": "L4OolHLOdnXhak6L5Gqe5-fvmzDGqAfkDcD9UC-ow3hiE18", "summonerLevel": 230, "summonerName": "\ub098\ubb34\uad00\uc138\uc74c\ub298\ubcf4\uc0b4", "teamEarlySurrendered": false, "teamId": 100, "teamPosition": "UTILITY", "timeCCingOthers": 17, "timePlayed": 912, "totalAllyJungleMinionsKilled": 0, "totalDamageDealt": 14299, "totalDamageDealtToChampions": 3187, "totalDamageShieldedOnTeammates": 0, "totalDamageTaken": 5977, "totalEnemyJungleMinionsKilled": 0, "totalHeal": 315, "totalHealsOnTeammates": 387, "totalMinionsKilled": 26, "totalTimeCCDealt": 48, "totalTimeSpentDead": 41, "totalUnitsHealed": 4, "tripleKills": 0, "trueDamageDealt": 5423, "trueDamageDealtToChampions": 490, "trueDamageTaken": 364, "turretKills": 0, "turretTakedowns": 0, "turretsLost": 3, "unrealKills": 0, "visionClearedPings": 0, "visionScore": 26, "visionWardsBoughtInGame": 4, "wardsKilled": 3, "wardsPlaced": 12, "win": false}, {"allInPings": 0, "assistMePings": 2, "assists": 4, "baitPings": 0, "baronKills": 0, "basicPings": 0, "bountyLevel": 4, "challenges": {"12AssistStreakCount": 0, "abilityUses": 286, "acesBefore15Minutes": 0, "alliedJungleMonsterKills": 0, "baronTakedowns": 0, "blastConeOppositeOpponentCount": 0, "bountyGold": 0, "buffsStolen": 0, "completeSupportQuestInTime": 0, "controlWardsPlaced": 0, "damagePerMinute": 371.32820850911776, "damageTakenOnTeamPercentage": 0.1484295365499651, "dancedWithRiftHerald": 0, "deathsByEnemyChamps": 0, "dodgeSkillShotsSmallWindow": 0, "doubleAces": 0, "dragonTakedowns": 1, "earliestDragonTakedown": 771.7355315, "earlyLaningPhaseGoldExpAdvantage": 1, "effectiveHealAndShielding": 0, "elderDragonKillsWithOpposingSoul": 0, "elderDragonMultikills": 0, "enemyChampionImmobilizations": 18, "enemyJungleMonsterKills": 0, "epicMonsterKillsNearEnemyJungler": 0, "epicMonsterKillsWithin30SecondsOfSpawn": 0, "epicMonsterSteals": 0, "epicMonsterStolenWithoutSmite": 0, "firstTurretKilled": 1, "firstTurretKilledTime": 683.8844576, "flawlessAces": 0, "fullTeamTakedown": 1, "gameLength": 912.5629653999999, "getTakedownsInAllLanesEarlyJungleAsLaner": 0, "goldPerMinute": 526.6326354176251, "hadOpenNexus": 0, "immobilizeAndKillWithAlly": 7, "initialBuffCount": 0, "initialCrabCount": 0, "jungleCsBefore10Minutes": 0, "junglerTakedownsNearDamagedEpicMonster": 1, "kTurretsDestroyedBeforePlatesFall": 1, "kda": 8, "killAfterHiddenWithAlly": 0, "killParticipation": 0.5333333333333333, "killedChampTookFullTeamDamageSurvived": 0, "killingSprees": 1, "killsNearEnemyTurret": 2, "killsOnOtherLanesEarlyJungleAsLaner": 0, "killsOnRecentlyHealedByAramPack": 0, "killsUnderOwnTurret": 0, "killsWithHelpFromEpicMonster": 0, "knockEnemyIntoTeamAndKill": 5, "landSkillShotsEarlyGame": 1, "laneMinionsFirst10Minutes": 73, "laningPhaseGoldExpAdvantage": 1, "legendaryCount": 0, "lostAnInhibitor": 0, "maxCsAdvantageOnLaneOpponent": 65, "maxKillDeficit": 0, "maxLevelLeadLaneOpponent": 3, "mejaisFullStackInTime": 0, "moreEnemyJungleThanOpponent": 0, "multiKillOneSpell": 0, "multiTurretRiftHeraldCount": 0, "multikills": 0, "multikillsAfterAggressiveFlash": 0, "mythicItemUsed": 6630, "outerTurretExecutesBefore10Minutes": 0, "outnumberedKills": 0, "outnumberedNexusKill": 0, "perfectDragonSoulsTaken": 0, "perfectGame": 0, "pickKillWithAlly": 5, "playedChampSelectPosition": 1, "poroExplosions": 0, "quickCleanse": 0, "quickFirstTurret": 0, "quickSoloKills": 0, "riftHeraldTakedowns": 1, "saveAllyFromDeath": 0, "scuttleCrabKills": 0, "skillshotsDodged": 0, "skillshotsHit": 3, "snowballsHit": 0, "soloBaronKills": 0, "soloKills": 1, "stealthWardsPlaced": 3, "survivedSingleDigitHpCount": 0, "survivedThreeImmobilizesInFight": 2, "takedownOnFirstTurret": 1, "takedowns": 8, "takedownsAfterGainingLevelAdvantage": 0, "takedownsBeforeJungleMinionSpawn": 0, "takedownsFirstXMinutes": 8, "takedownsInAlcove": 0, "takedownsInEnemyFountain": 0, "teamBaronKills": 0, "teamDamagePercentage": 0.19388631790180366, "teamElderDragonKills": 0, "teamRiftHeraldKills": 1, "tookLargeDamageSurvived": 0, "turretPlatesTaken": 7, "turretTakedowns": 2, "turretsTakenWithRiftHerald": 0, "twentyMinionsIn3SecondsCount": 6, "twoWardsOneSweeperCount": 0, "unseenRecalls": 0, "visionScoreAdvantageLaneOpponent": -0.533819317817688, "visionScorePerMinute": 0.44579935626728706, "wardTakedowns": 0, "wardTakedownsBefore20M": 0, "wardsGuarded": 0}, "champExperience": 7932, "champLevel": 11, "championId": 92, "championName": "Riven", "championTransform": 0, "commandPings": 10, "consumablesPurchased": 5, "damageDealtToBuildings": 3443, "damageDealtToObjectives": 5523, "damageDealtToTurrets": 3443, "damageSelfMitigated": 5173, "dangerPings": 0, "deaths": 0, "detectorWardsPlaced": 0, "doubleKills": 0, "dragonKills": 0, "eligibleForProgression": true, "enemyMissingPings": 10, "enemyVisionPings": 0, "firstBloodAssist": false, "firstBloodKill": false, "firstTowerAssist": false, "firstTowerKill": true, "gameEndedInEarlySurrender": false, "gameEndedInSurrender": true, "getBackPings": 14, "goldEarned": 8009, "goldSpent": 6100, "holdPings": 0, "individualPosition": "TOP", "inhibitorKills": 0, "inhibitorTakedowns": 0, "inhibitorsLost": 0, "item0": 3047, "item1": 6630, "item2": 0, "item3": 1055, "item4": 3133, "item5": 0, "item6": 3364, "itemsPurchased": 17, "killingSprees": 1, "kills": 4, "lane": "NONE", "largestCriticalStrike": 0, "largestKillingSpree": 4, "largestMultiKill": 1, "longestTimeSpentLiving": 0, "magicDamageDealt": 0, "magicDamageDealtToChampions": 0, "magicDamageTaken": 838, "needVisionPings": 0, "neutralMinionsKilled": 0, "nexusKills": 0, "nexusLost": 0, "nexusTakedowns": 0, "objectivesStolen": 0, "objectivesStolenAssists": 0, "onMyWayPings": 4, "participantId": 6, "pentaKills": 0, "perks": {"statPerks": {"defense": 5002, "flex": 5008, "offense": 5008}, "styles": [{"description": "primaryStyle", "selections": [{"perk": 8010, "var1": 76, "var2": 0, "var3": 0}, {"perk": 9111, "var1": 430, "var2": 160, "var3": 0}, {"perk": 9105, "var1": 12, "var2": 50, "var3": 0}, {"perk": 8299, "var1": 50, "var2": 0, "var3": 0}], "style": 8000}, {"description": "subStyle", "selections": [{"perk": 8473, "var1": 229, "var2": 0, "var3": 0}, {"perk": 8242, "var1": 14, "var2": 0, "var3": 0}], "style": 8400}]}, "physicalDamageDealt": 67264, "physicalDamageDealtToChampions": 5247, "physicalDamageTaken": 4581, "placement": 0, "playerAugment1": 0, "playerAugment2": 0, "playerAugment3": 0, "playerAugment4": 0, "playerSubteamId": 0, "profileIcon": 933, "pushPings": 0, "puuid": "lmnJM08vWc4by13rLmSdmT95MNtDQZSfSqMzkReEP4C8Q2cn4WSAVxn-eVDQCgHGwYtBCB3TOvuICQ", "quadraKills": 0, "riotIdName": "", "riotIdTagline": "", "role": "SUPPORT", "sightWardsBoughtInGame": 0, "spell1Casts": 184, "spell2Casts": 35, "spell3Casts": 61, "spell4Casts": 6, "subteamPlacement": 0, "summoner1Casts": 2, "summoner1Id": 4, "summoner2Casts": 3, "summoner2Id": 14, "summonerId": "rXAqfM-RFxo-Re1hFMJp3hSHX28fY8kqqRXs_aXkT-YBt0vQ77HCVveNGA", "summonerLevel": 52, "summonerName": "AloisNL", "teamEarlySurrendered": false, "teamId": 200, "teamPosition": "TOP", "timeCCingOthers": 12, "timePlayed": 912, "totalAllyJungleMinionsKilled": 0, "totalDamageDealt": 67802, "totalDamageDealtToChampions": 5647, "totalDamageShieldedOnTeammates": 0, "totalDamageTaken": 5494, "totalEnemyJungleMinionsKilled": 0, "totalHeal": 2375, "totalHealsOnTeammates": 0, "totalMinionsKilled": 128, "totalTimeCCDealt": 83, "totalTimeSpentDead": 0, "totalUnitsHealed": 1, "tripleKills": 0, "trueDamageDealt": 538, "trueDamageDealtToChampions": 400, "trueDamageTaken": 74, "turretKills": 2, "turretTakedowns": 2, "turretsLost": 0, "unrealKills": 0, "visionClearedPings": 0, "visionScore": 6, "visionWardsBoughtInGame": 0, "wardsKilled": 0, "wardsPlaced": 3, "win": true}, {"allInPings": 1, "assistMePings": 4, "assists": 8, "baitPings": 0, "baronKills": 0, "basicPings": 0, "bountyLevel": 0, "challenges": {"12AssistStreakCount": 0, "abilityUses": 175, "acesBefore15Minutes": 0, "alliedJungleMonsterKills": 47, "baronTakedowns": 0, "blastConeOppositeOpponentCount": 0, "bountyGold": 0, "buffsStolen": 1, "completeSupportQuestInTime": 0, "controlWardTimeCoverageInRiverOrEnemyHalf": 0.17664973827788424, "controlWardsPlaced": 1, "damagePerMinute": 348.43825331411483, "damageTakenOnTeamPercentage": 0.3184864081241616, "dancedWithRiftHerald": 0, "deathsByEnemyChamps": 2, "dodgeSkillShotsSmallWindow": 0, "doubleAces": 0, "dragonTakedowns": 2, "earliestDragonTakedown": 427.6105248, "earlyLaningPhaseGoldExpAdvantage": 0, "effectiveHealAndShielding": 0, "elderDragonKillsWithOpposingSoul": 0, "elderDragonMultikills": 0, "enemyChampionImmobilizations": 4, "enemyJungleMonsterKills": 8, "epicMonsterKillsNearEnemyJungler": 0, "epicMonsterKillsWithin30SecondsOfSpawn": 0, "epicMonsterSteals": 0, "epicMonsterStolenWithoutSmite": 0, "firstTurretKilled": 1, "firstTurretKilledTime": 683.8844576, "flawlessAces": 0, "fullTeamTakedown": 1, "gameLength": 912.5629653999999, "goldPerMinute": 424.23519560133144, "hadOpenNexus": 0, "immobilizeAndKillWithAlly": 3, "initialBuffCount": 3, "initialCrabCount": 0, "jungleCsBefore10Minutes": 62.000000059604645, "junglerKillsEarlyJungle": 0, "junglerTakedownsNearDamagedEpicMonster": 0, "kTurretsDestroyedBeforePlatesFall": 0, "kda": 5, "killAfterHiddenWithAlly": 1, "killParticipation": 0.6666666666666666, "killedChampTookFullTeamDamageSurvived": 0, "killingSprees": 0, "killsNearEnemyTurret": 0, "killsOnLanersEarlyJungleAsJungler": 0, "killsOnRecentlyHealedByAramPack": 0, "killsUnderOwnTurret": 0, "killsWithHelpFromEpicMonster": 0, "knockEnemyIntoTeamAndKill": 0, "landSkillShotsEarlyGame": 0, "laneMinionsFirst10Minutes": 6, "laningPhaseGoldExpAdvantage": 0, "legendaryCount": 0, "lostAnInhibitor": 0, "maxCsAdvantageOnLaneOpponent": 16.999999970197678, "maxKillDeficit": 0, "maxLevelLeadLaneOpponent": 2, "mejaisFullStackInTime": 0, "moreEnemyJungleThanOpponent": -33.50000011920929, "multiKillOneSpell": 0, "multiTurretRiftHeraldCount": 0, "multikills": 0, "multikillsAfterAggressiveFlash": 0, "mythicItemUsed": 6630, "outerTurretExecutesBefore10Minutes": 0, "outnumberedKills": 0, "outnumberedNexusKill": 0, "perfectDragonSoulsTaken": 0, "perfectGame": 0, "pickKillWithAlly": 7, "playedChampSelectPosition": 1, "poroExplosions": 0, "quickCleanse": 0, "quickFirstTurret": 0, "quickSoloKills": 0, "riftHeraldTakedowns": 1, "saveAllyFromDeath": 0, "scuttleCrabKills": 1, "skillshotsDodged": 1, "skillshotsHit": 0, "snowballsHit": 0, "soloBaronKills": 0, "soloKills": 1, "stealthWardsPlaced": 5, "survivedSingleDigitHpCount": 0, "survivedThreeImmobilizesInFight": 0, "takedownOnFirstTurret": 0, "takedowns": 10, "takedownsAfterGainingLevelAdvantage": 0, "takedownsBeforeJungleMinionSpawn": 0, "takedownsFirstXMinutes": 10, "takedownsInAlcove": 0, "takedownsInEnemyFountain": 0, "teamBaronKills": 0, "teamDamagePercentage": 0.18193449461448827, "teamElderDragonKills": 0, "teamRiftHeraldKills": 1, "tookLargeDamageSurvived": 0, "turretPlatesTaken": 1, "turretTakedowns": 0, "turretsTakenWithRiftHerald": 0, "twentyMinionsIn3SecondsCount": 0, "twoWardsOneSweeperCount": 0, "unseenRecalls": 0, "visionScoreAdvantageLaneOpponent": 0.16705703735351562, "visionScorePerMinute": 1.096891490809021, "wardTakedowns": 3, "wardTakedownsBefore20M": 3, "wardsGuarded": 0}, "champExperience": 6401, "champLevel": 10, "championId": 59, "championName": "JarvanIV", "championTransform": 0, "commandPings": 22, "consumablesPurchased": 1, "damageDealtToBuildings": 0, "damageDealtToObjectives": 17873, "damageDealtToTurrets": 0, "damageSelfMitigated": 13384, "dangerPings": 0, "deaths": 2, "detectorWardsPlaced": 1, "doubleKills": 0, "dragonKills": 1, "eligibleForProgression": true, "enemyMissingPings": 3, "enemyVisionPings": 0, "firstBloodAssist": false, "firstBloodKill": true, "firstTowerAssist": false, "firstTowerKill": false, "gameEndedInEarlySurrender": false, "gameEndedInSurrender": true, "getBackPings": 0, "goldEarned": 6452, "goldSpent": 4925, "holdPings": 1, "individualPosition": "JUNGLE", "inhibitorKills": 0, "inhibitorTakedowns": 0, "inhibitorsLost": 0, "item0": 6630, "item1": 0, "item2": 0, "item3": 1028, "item4": 3047, "item5": 1103, "item6": 3340, "itemsPurchased": 9, "killingSprees": 1, "kills": 2, "lane": "NONE", "largestCriticalStrike": 0, "largestKillingSpree": 2, "largestMultiKill": 1, "longestTimeSpentLiving": 604, "magicDamageDealt": 6414, "magicDamageDealtToChampions": 463, "magicDamageTaken": 2171, "needVisionPings": 0, "neutralMinionsKilled": 94, "nexusKills": 0, "nexusLost": 0, "nexusTakedowns": 0, "objectivesStolen": 0, "objectivesStolenAssists": 0, "onMyWayPings": 14, "participantId": 7, "pentaKills": 0, "perks": {"statPerks": {"defense": 5002, "flex": 5008, "offense": 5005}, "styles": [{"description": "primaryStyle", "selections": [{"perk": 8010, "var1": 78, "var2": 0, "var3": 0}, {"perk": 9111, "var1": 632, "var2": 200, "var3": 0}, {"perk": 9104, "var1": 10, "var2": 0, "var3": 0}, {"perk": 8299, "var1": 172, "var2": 0, "var3": 0}], "style": 8000}, {"description": "subStyle", "selections": [{"perk": 8304, "var1": 9, "var2": 0, "var3": 0}, {"perk": 8347, "var1": 0, "var2": 0, "var3": 0}], "style": 8300}]}, "physicalDamageDealt": 75521, "physicalDamageDealtToChampions": 4522, "physicalDamageTaken": 9052, "placement": 0, "playerAugment1": 0, "playerAugment2": 0, "playerAugment3": 0, "playerAugment4": 0, "playerSubteamId": 0, "profileIcon": 11, "pushPings": 0, "puuid": "8gU_pNweRp6t5cFZdajxPLS3I7ypaBs2VvOQrHuoyjRAbXTM---xQlFL_Ktp5fXRoy3vBfhtfYrUVw", "quadraKills": 0, "riotIdName": "", "riotIdTagline": "", "role": "SUPPORT", "sightWardsBoughtInGame": 0, "spell1Casts": 68, "spell2Casts": 48, "spell3Casts": 54, "spell4Casts": 5, "subteamPlacement": 0, "summoner1Casts": 2, "summoner1Id": 4, "summoner2Casts": 11, "summoner2Id": 11, "summonerId": "CosLKfG0xxPjQwUT8vGhT8WUUVU8mipfd3rrZSEIHA9mQGiKt1lDXzuyTQ", "summonerLevel": 51, "summonerName": "Agurin\ubaa8\ubaa8", "teamEarlySurrendered": false, "teamId": 200, "teamPosition": "JUNGLE", "timeCCingOthers": 9, "timePlayed": 912, "totalAllyJungleMinionsKilled": 65, "totalDamageDealt": 104702, "totalDamageDealtToChampions": 5299, "totalDamageShieldedOnTeammates": 0, "totalDamageTaken": 11789, "totalEnemyJungleMinionsKilled": 12, "totalHeal": 6851, "totalHealsOnTeammates": 0, "totalMinionsKilled": 8, "totalTimeCCDealt": 267, "totalTimeSpentDead": 48, "totalUnitsHealed": 1, "tripleKills": 0, "trueDamageDealt": 22766, "trueDamageDealtToChampions": 312, "trueDamageTaken": 565, "turretKills": 0, "turretTakedowns": 0, "turretsLost": 0, "unrealKills": 0, "visionClearedPings": 0, "visionScore": 16, "visionWardsBoughtInGame": 1, "wardsKilled": 3, "wardsPlaced": 6, "win": true}, {"allInPings": 0, "assistMePings": 0, "assists": 4, "baitPings": 0, "baronKills": 0, "basicPings": 0, "bountyLevel": 2, "challenges": {"12AssistStreakCount": 0, "abilityUses": 134, "acesBefore15Minutes": 0, "alliedJungleMonsterKills": 0, "baronTakedowns": 0, "blastConeOppositeOpponentCount": 0, "bountyGold": 0, "buffsStolen": 0, "completeSupportQuestInTime": 0, "controlWardTimeCoverageInRiverOrEnemyHalf": 0.5713680248589234, "controlWardsPlaced": 2, "damagePerMinute": 492.53210960954044, "damageTakenOnTeamPercentage": 0.2060169797592795, "dancedWithRiftHerald": 0, "deathsByEnemyChamps": 1, "dodgeSkillShotsSmallWindow": 0, "doubleAces": 0, "dragonTakedowns": 0, "earlyLaningPhaseGoldExpAdvantage": 0, "effectiveHealAndShielding": 0, "elderDragonKillsWithOpposingSoul": 0, "elderDragonMultikills": 0, "enemyChampionImmobilizations": 15, "enemyJungleMonsterKills": 0, "epicMonsterKillsNearEnemyJungler": 0, "epicMonsterKillsWithin30SecondsOfSpawn": 0, "epicMonsterSteals": 0, "epicMonsterStolenWithoutSmite": 0, "firstTurretKilled": 1, "firstTurretKilledTime": 683.8844576, "flawlessAces": 0, "fullTeamTakedown": 1, "gameLength": 912.5629653999999, "getTakedownsInAllLanesEarlyJungleAsLaner": 0, "goldPerMinute": 453.08762464066245, "hadOpenNexus": 0, "immobilizeAndKillWithAlly": 6, "initialBuffCount": 0, "initialCrabCount": 0, "jungleCsBefore10Minutes": 0, "junglerTakedownsNearDamagedEpicMonster": 0, "kTurretsDestroyedBeforePlatesFall": 0, "kda": 8, "killAfterHiddenWithAlly": 2, "killParticipation": 0.5333333333333333, "killedChampTookFullTeamDamageSurvived": 0, "killingSprees": 0, "killsNearEnemyTurret": 4, "killsOnOtherLanesEarlyJungleAsLaner": 0, "killsOnRecentlyHealedByAramPack": 0, "killsUnderOwnTurret": 0, "killsWithHelpFromEpicMonster": 0, "knockEnemyIntoTeamAndKill": 0, "landSkillShotsEarlyGame": 15, "laneMinionsFirst10Minutes": 90, "laningPhaseGoldExpAdvantage": 0, "legendaryCount": 0, "lostAnInhibitor": 0, "maxCsAdvantageOnLaneOpponent": 8, "maxKillDeficit": 0, "maxLevelLeadLaneOpponent": 1, "mejaisFullStackInTime": 0, "moreEnemyJungleThanOpponent": 0, "multiKillOneSpell": 0, "multiTurretRiftHeraldCount": 0, "multikills": 1, "multikillsAfterAggressiveFlash": 0, "outerTurretExecutesBefore10Minutes": 0, "outnumberedKills": 0, "outnumberedNexusKill": 0, "perfectDragonSoulsTaken": 0, "perfectGame": 0, "pickKillWithAlly": 5, "playedChampSelectPosition": 1, "poroExplosions": 0, "quickCleanse": 0, "quickFirstTurret": 0, "quickSoloKills": 0, "riftHeraldTakedowns": 0, "saveAllyFromDeath": 0, "scuttleCrabKills": 0, "skillshotsDodged": 1, "skillshotsHit": 27, "snowballsHit": 0, "soloBaronKills": 0, "soloKills": 1, "stealthWardsPlaced": 2, "survivedSingleDigitHpCount": 0, "survivedThreeImmobilizesInFight": 0, "takedownOnFirstTurret": 0, "takedowns": 8, "takedownsAfterGainingLevelAdvantage": 0, "takedownsBeforeJungleMinionSpawn": 0, "takedownsFirstXMinutes": 8, "takedownsInAlcove": 0, "takedownsInEnemyFountain": 0, "teamBaronKills": 0, "teamDamagePercentage": 0.257172051549799, "teamElderDragonKills": 0, "teamRiftHeraldKills": 1, "teleportTakedowns": 3, "tookLargeDamageSurvived": 0, "turretPlatesTaken": 3, "turretTakedowns": 1, "turretsTakenWithRiftHerald": 0, "twentyMinionsIn3SecondsCount": 6, "twoWardsOneSweeperCount": 0, "unseenRecalls": 0, "visionScoreAdvantageLaneOpponent": -0.17302703857421875, "visionScorePerMinute": 0.8277826455234828, "wardTakedowns": 3, "wardTakedownsBefore20M": 3, "wardsGuarded": 0}, "champExperience": 7593, "champLevel": 11, "championId": 127, "championName": "Lissandra", "championTransform": 0, "commandPings": 2, "consumablesPurchased": 2, "damageDealtToBuildings": 1964, "damageDealtToObjectives": 1964, "damageDealtToTurrets": 1964, "damageSelfMitigated": 4933, "dangerPings": 0, "deaths": 1, "detectorWardsPlaced": 2, "doubleKills": 1, "dragonKills": 0, "eligibleForProgression": true, "enemyMissingPings": 6, "enemyVisionPings": 0, "firstBloodAssist": false, "firstBloodKill": false, "firstTowerAssist": false, "firstTowerKill": false, "gameEndedInEarlySurrender": false, "gameEndedInSurrender": true, "getBackPings": 1, "goldEarned": 6891, "goldSpent": 5150, "holdPings": 0, "individualPosition": "MIDDLE", "inhibitorKills": 0, "inhibitorTakedowns": 0, "inhibitorsLost": 0, "item0": 3191, "item1": 2033, "item2": 6656, "item3": 0, "item4": 1001, "item5": 1056, "item6": 3364, "itemsPurchased": 14, "killingSprees": 2, "kills": 4, "lane": "NONE", "largestCriticalStrike": 0, "largestKillingSpree": 2, "largestMultiKill": 2, "longestTimeSpentLiving": 729, "magicDamageDealt": 54930, "magicDamageDealtToChampions": 6316, "magicDamageTaken": 1334, "needVisionPings": 0, "neutralMinionsKilled": 0, "nexusKills": 0, "nexusLost": 0, "nexusTakedowns": 0, "objectivesStolen": 0, "objectivesStolenAssists": 0, "onMyWayPings": 7, "participantId": 8, "pentaKills": 0, "perks": {"statPerks": {"defense": 5002, "flex": 5008, "offense": 5005}, "styles": [{"description": "primaryStyle", "selections": [{"perk": 8229, "var1": 629, "var2": 0, "var3": 0}, {"perk": 8226, "var1": 250, "var2": 281, "var3": 0}, {"perk": 8210, "var1": 0, "var2": 0, "var3": 0}, {"perk": 8237, "var1": 257, "var2": 0, "var3": 0}], "style": 8200}, {"description": "subStyle", "selections": [{"perk": 8316, "var1": 2190, "var2": 0, "var3": 0}, {"perk": 8347, "var1": 0, "var2": 0, "var3": 0}], "style": 8300}]}, "physicalDamageDealt": 11011, "physicalDamageDealtToChampions": 1134, "physicalDamageTaken": 6082, "placement": 0, "playerAugment1": 0, "playerAugment2": 0, "playerAugment3": 0, "playerAugment4": 0, "playerSubteamId": 0, "profileIcon": 4096, "pushPings": 0, "puuid": "oVa7Xp04TQFfEdd9x1PKUTdiYjNNcjG8fLYpT63b8opb30E-cwzL-VUVNuhohbdiwmBM4v87ipciwA", "quadraKills": 0, "riotIdName": "", "riotIdTagline": "", "role": "SUPPORT", "sightWardsBoughtInGame": 0, "spell1Casts": 70, "spell2Casts": 25, "spell3Casts": 34, "spell4Casts": 5, "subteamPlacement": 0, "summoner1Casts": 2, "summoner1Id": 12, "summoner2Casts": 2, "summoner2Id": 4, "summonerId": "yZUWsjMtyVPswrRmVU124uTFd8bNqXQ9g6Uw4y2VnTYUKIE", "summonerLevel": 78, "summonerName": "Kakhi shoot", "teamEarlySurrendered": false, "teamId": 200, "teamPosition": "MIDDLE", "timeCCingOthers": 22, "timePlayed": 912, "totalAllyJungleMinionsKilled": 0, "totalDamageDealt": 67501, "totalDamageDealtToChampions": 7491, "totalDamageShieldedOnTeammates": 0, "totalDamageTaken": 7626, "totalEnemyJungleMinionsKilled": 0, "totalHeal": 90, "totalHealsOnTeammates": 0, "totalMinionsKilled": 135, "totalTimeCCDealt": 351, "totalTimeSpentDead": 32, "totalUnitsHealed": 1, "tripleKills": 0, "trueDamageDealt": 1559, "trueDamageDealtToChampions": 40, "trueDamageTaken": 209, "turretKills": 1, "turretTakedowns": 1, "turretsLost": 0, "unrealKills": 0, "visionClearedPings": 0, "visionScore": 12, "visionWardsBoughtInGame": 2, "wardsKilled": 3, "wardsPlaced": 4, "win": true}, {"allInPings": 0, "assistMePings": 2, "assists": 2, "baitPings": 0, "baronKills": 0, "basicPings": 0, "bountyLevel": 5, "challenges": {"12AssistStreakCount": 0, "abilityUses": 131, "acesBefore15Minutes": 0, "alliedJungleMonsterKills": 0, "baronTakedowns": 0, "blastConeOppositeOpponentCount": 0, "bountyGold": 0, "buffsStolen": 0, "completeSupportQuestInTime": 0, "controlWardsPlaced": 0, "damagePerMinute": 554.800223014562, "damageTakenOnTeamPercentage": 0.16262229626820715, "dancedWithRiftHerald": 0, "deathsByEnemyChamps": 1, "dodgeSkillShotsSmallWindow": 6, "doubleAces": 0, "dragonTakedowns": 1, "earliestDragonTakedown": 771.7355315, "earlyLaningPhaseGoldExpAdvantage": 0, "effectiveHealAndShielding": 214.8000030517578, "elderDragonKillsWithOpposingSoul": 0, "elderDragonMultikills": 0, "enemyChampionImmobilizations": 2, "enemyJungleMonsterKills": 0, "epicMonsterKillsNearEnemyJungler": 0, "epicMonsterKillsWithin30SecondsOfSpawn": 0, "epicMonsterSteals": 0, "epicMonsterStolenWithoutSmite": 0, "firstTurretKilled": 1, "firstTurretKilledTime": 683.8844576, "flawlessAces": 0, "fullTeamTakedown": 1, "gameLength": 912.5629653999999, "getTakedownsInAllLanesEarlyJungleAsLaner": 0, "goldPerMinute": 462.4603083751497, "hadOpenNexus": 0, "highestChampionDamage": 1, "highestWardKills": 1, "immobilizeAndKillWithAlly": 0, "initialBuffCount": 0, "initialCrabCount": 0, "jungleCsBefore10Minutes": 0, "junglerTakedownsNearDamagedEpicMonster": 0, "kTurretsDestroyedBeforePlatesFall": 0, "kda": 7, "killAfterHiddenWithAlly": 1, "killParticipation": 0.4666666666666667, "killedChampTookFullTeamDamageSurvived": 0, "killingSprees": 1, "killsNearEnemyTurret": 1, "killsOnOtherLanesEarlyJungleAsLaner": 1, "killsOnRecentlyHealedByAramPack": 0, "killsUnderOwnTurret": 1, "killsWithHelpFromEpicMonster": 0, "knockEnemyIntoTeamAndKill": 0, "landSkillShotsEarlyGame": 7, "laneMinionsFirst10Minutes": 73, "laningPhaseGoldExpAdvantage": 0, "legendaryCount": 0, "lostAnInhibitor": 0, "maxCsAdvantageOnLaneOpponent": 19, "maxKillDeficit": 0, "maxLevelLeadLaneOpponent": 1, "mejaisFullStackInTime": 0, "moreEnemyJungleThanOpponent": 0, "multiKillOneSpell": 0, "multiTurretRiftHeraldCount": 0, "multikills": 0, "multikillsAfterAggressiveFlash": 0, "outerTurretExecutesBefore10Minutes": 0, "outnumberedKills": 0, "outnumberedNexusKill": 0, "perfectDragonSoulsTaken": 0, "perfectGame": 0, "pickKillWithAlly": 5, "playedChampSelectPosition": 1, "poroExplosions": 0, "quickCleanse": 0, "quickFirstTurret": 0, "quickSoloKills": 0, "riftHeraldTakedowns": 0, "saveAllyFromDeath": 0, "scuttleCrabKills": 0, "skillshotsDodged": 34, "skillshotsHit": 21, "snowballsHit": 0, "soloBaronKills": 0, "soloKills": 1, "stealthWardsPlaced": 5, "survivedSingleDigitHpCount": 0, "survivedThreeImmobilizesInFight": 0, "takedownOnFirstTurret": 0, "takedowns": 7, "takedownsAfterGainingLevelAdvantage": 0, "takedownsBeforeJungleMinionSpawn": 0, "takedownsFirstXMinutes": 7, "takedownsInAlcove": 2, "takedownsInEnemyFountain": 0, "teamBaronKills": 0, "teamDamagePercentage": 0.28968489316574947, "teamElderDragonKills": 0, "teamRiftHeraldKills": 1, "tookLargeDamageSurvived": 0, "turretPlatesTaken": 2, "turretTakedowns": 0, "turretsTakenWithRiftHerald": 0, "twentyMinionsIn3SecondsCount": 5, "twoWardsOneSweeperCount": 0, "unseenRecalls": 0, "visionScoreAdvantageLaneOpponent": 0.5469146966934204, "visionScorePerMinute": 1.0384893911376216, "wardTakedowns": 6, "wardTakedownsBefore20M": 6, "wardsGuarded": 0}, "champExperience": 6188, "champLevel": 10, "championId": 222, "championName": "Jinx", "championTransform": 0, "commandPings": 11, "consumablesPurchased": 4, "damageDealtToBuildings": 891, "damageDealtToObjectives": 2710, "damageDealtToTurrets": 891, "damageSelfMitigated": 2650, "dangerPings": 0, "deaths": 1, "detectorWardsPlaced": 0, "doubleKills": 0, "dragonKills": 1, "eligibleForProgression": true, "enemyMissingPings": 7, "enemyVisionPings": 0, "firstBloodAssist": false, "firstBloodKill": false, "firstTowerAssist": false, "firstTowerKill": false, "gameEndedInEarlySurrender": false, "gameEndedInSurrender": true, "getBackPings": 3, "goldEarned": 7033, "goldSpent": 6700, "holdPings": 0, "individualPosition": "BOTTOM", "inhibitorKills": 0, "inhibitorTakedowns": 0, "inhibitorsLost": 0, "item0": 6672, "item1": 1038, "item2": 3006, "item3": 1018, "item4": 1055, "item5": 2055, "item6": 3363, "itemsPurchased": 14, "killingSprees": 1, "kills": 5, "lane": "NONE", "largestCriticalStrike": 257, "largestKillingSpree": 5, "largestMultiKill": 1, "longestTimeSpentLiving": 288, "magicDamageDealt": 673, "magicDamageDealtToChampions": 148, "magicDamageTaken": 593, "needVisionPings": 0, "neutralMinionsKilled": 4, "nexusKills": 0, "nexusLost": 0, "nexusTakedowns": 0, "objectivesStolen": 0, "objectivesStolenAssists": 0, "onMyWayPings": 8, "participantId": 9, "pentaKills": 0, "perks": {"statPerks": {"defense": 5002, "flex": 5008, "offense": 5005}, "styles": [{"description": "primaryStyle", "selections": [{"perk": 8008, "var1": 36, "var2": 5, "var3": 0}, {"perk": 8009, "var1": 940, "var2": 0, "var3": 0}, {"perk": 9103, "var1": 0, "var2": 0, "var3": 0}, {"perk": 8014, "var1": 208, "var2": 0, "var3": 0}], "style": 8000}, {"description": "subStyle", "selections": [{"perk": 8345, "var1": 3, "var2": 0, "var3": 0}, {"perk": 8347, "var1": 0, "var2": 0, "var3": 0}], "style": 8300}]}, "physicalDamageDealt": 57977, "physicalDamageDealtToChampions": 8289, "physicalDamageTaken": 5276, "placement": 0, "playerAugment1": 0, "playerAugment2": 0, "playerAugment3": 0, "playerAugment4": 0, "playerSubteamId": 0, "profileIcon": 7, "pushPings": 0, "puuid": "fsQU8a6yWK-aXR_nxqejnclutdZxrhHxuPLxq-gXJFCuAtbui6cqiHZd92RBLGP4mh3oVPs_CF-Nzg", "quadraKills": 0, "riotIdName": "", "riotIdTagline": "", "role": "SUPPORT", "sightWardsBoughtInGame": 0, "spell1Casts": 94, "spell2Casts": 26, "spell3Casts": 7, "spell4Casts": 4, "subteamPlacement": 0, "summoner1Casts": 2, "summoner1Id": 7, "summoner2Casts": 2, "summoner2Id": 4, "summonerId": "HfccCv-YOx9UrpgxDMMiKb0YybeF1VIp8sGpomTBruXkv-DRFemXfzbtig", "summonerLevel": 60, "summonerName": "\ub028\ub4e4\ub028\ub4e4", "teamEarlySurrendered": false, "teamId": 200, "teamPosition": "BOTTOM", "timeCCingOthers": 6, "timePlayed": 912, "totalAllyJungleMinionsKilled": 0, "totalDamageDealt": 58650, "totalDamageDealtToChampions": 8438, "totalDamageShieldedOnTeammates": 0, "totalDamageTaken": 6020, "totalEnemyJungleMinionsKilled": 0, "totalHeal": 2218, "totalHealsOnTeammates": 214, "totalMinionsKilled": 137, "totalTimeCCDealt": 26, "totalTimeSpentDead": 10, "totalUnitsHealed": 2, "tripleKills": 0, "trueDamageDealt": 0, "trueDamageDealtToChampions": 0, "trueDamageTaken": 150, "turretKills": 0, "turretTakedowns": 0, "turretsLost": 0, "unrealKills": 0, "visionClearedPings": 0, "visionScore": 15, "visionWardsBoughtInGame": 2, "wardsKilled": 6, "wardsPlaced": 5, "win": true}, {"allInPings": 0, "assistMePings": 0, "assists": 5, "baitPings": 0, "baronKills": 0, "basicPings": 0, "bountyLevel": 0, "challenges": {"12AssistStreakCount": 0, "abilityUses": 35, "acesBefore15Minutes": 0, "alliedJungleMonsterKills": 0, "baronTakedowns": 0, "blastConeOppositeOpponentCount": 0, "bountyGold": 0, "buffsStolen": 0, "completeSupportQuestInTime": 0, "controlWardTimeCoverageInRiverOrEnemyHalf": 0.644074841391761, "controlWardsPlaced": 5, "damagePerMinute": 148.08641577044818, "damageTakenOnTeamPercentage": 0.16444477929838663, "dancedWithRiftHerald": 0, "deathsByEnemyChamps": 3, "dodgeSkillShotsSmallWindow": 0, "doubleAces": 0, "dragonTakedowns": 1, "earliestDragonTakedown": 771.7355315, "earlyLaningPhaseGoldExpAdvantage": 0, "effectiveHealAndShielding": 232.37274169921875, "elderDragonKillsWithOpposingSoul": 0, "elderDragonMultikills": 0, "enemyChampionImmobilizations": 23, "enemyJungleMonsterKills": 0, "epicMonsterKillsNearEnemyJungler": 0, "epicMonsterKillsWithin30SecondsOfSpawn": 0, "epicMonsterSteals": 0, "epicMonsterStolenWithoutSmite": 0, "firstTurretKilled": 1, "firstTurretKilledTime": 683.8844576, "flawlessAces": 0, "fullTeamTakedown": 1, "gameLength": 912.5629653999999, "getTakedownsInAllLanesEarlyJungleAsLaner": 0, "goldPerMinute": 258.5106615147052, "hadOpenNexus": 0, "immobilizeAndKillWithAlly": 1, "initialBuffCount": 0, "initialCrabCount": 0, "jungleCsBefore10Minutes": 0, "junglerTakedownsNearDamagedEpicMonster": 0, "kTurretsDestroyedBeforePlatesFall": 0, "kda": 1.25, "killAfterHiddenWithAlly": 0, "killParticipation": 0.3333333333333333, "killedChampTookFullTeamDamageSurvived": 0, "killingSprees": 0, "killsNearEnemyTurret": 0, "killsOnOtherLanesEarlyJungleAsLaner": 0, "killsOnRecentlyHealedByAramPack": 0, "killsUnderOwnTurret": 0, "killsWithHelpFromEpicMonster": 0, "knockEnemyIntoTeamAndKill": 1, "landSkillShotsEarlyGame": 4, "laneMinionsFirst10Minutes": 16, "laningPhaseGoldExpAdvantage": 0, "legendaryCount": 0, "lostAnInhibitor": 0, "maxCsAdvantageOnLaneOpponent": 1, "maxKillDeficit": 0, "maxLevelLeadLaneOpponent": 1, "mejaisFullStackInTime": 0, "moreEnemyJungleThanOpponent": 0, "multiKillOneSpell": 0, "multiTurretRiftHeraldCount": 0, "multikills": 0, "multikillsAfterAggressiveFlash": 0, "outerTurretExecutesBefore10Minutes": 0, "outnumberedKills": 0, "outnumberedNexusKill": 0, "perfectDragonSoulsTaken": 0, "perfectGame": 0, "pickKillWithAlly": 3, "playedChampSelectPosition": 1, "poroExplosions": 0, "quickCleanse": 0, "quickFirstTurret": 0, "quickSoloKills": 0, "riftHeraldTakedowns": 0, "saveAllyFromDeath": 0, "scuttleCrabKills": 0, "skillshotsDodged": 7, "skillshotsHit": 8, "snowballsHit": 0, "soloBaronKills": 0, "soloKills": 0, "stealthWardsPlaced": 6, "survivedSingleDigitHpCount": 0, "survivedThreeImmobilizesInFight": 0, "takedownOnFirstTurret": 0, "takedowns": 5, "takedownsAfterGainingLevelAdvantage": 0, "takedownsBeforeJungleMinionSpawn": 0, "takedownsFirstXMinutes": 5, "takedownsInAlcove": 0, "takedownsInEnemyFountain": 0, "teamBaronKills": 0, "teamDamagePercentage": 0.07732224276815958, "teamElderDragonKills": 0, "teamRiftHeraldKills": 1, "tookLargeDamageSurvived": 0, "turretPlatesTaken": 2, "turretTakedowns": 0, "turretsTakenWithRiftHerald": 0, "twentyMinionsIn3SecondsCount": 0, "twoWardsOneSweeperCount": 0, "unseenRecalls": 0, "visionScoreAdvantageLaneOpponent": 0.0004916191101074219, "visionScorePerMinute": 1.7226103757675657, "wardTakedowns": 2, "wardTakedownsBefore20M": 2, "wardsGuarded": 0}, "champExperience": 4131, "champLevel": 8, "championId": 412, "championName": "Thresh", "championTransform": 0, "commandPings": 1, "consumablesPurchased": 10, "damageDealtToBuildings": 133, "damageDealtToObjectives": 355, "damageDealtToTurrets": 133, "damageSelfMitigated": 4009, "dangerPings": 0, "deaths": 4, "detectorWardsPlaced": 5, "doubleKills": 0, "dragonKills": 0, "eligibleForProgression": true, "enemyMissingPings": 2, "enemyVisionPings": 0, "firstBloodAssist": false, "firstBloodKill": false, "firstTowerAssist": false, "firstTowerKill": false, "gameEndedInEarlySurrender": false, "gameEndedInSurrender": true, "getBackPings": 0, "goldEarned": 3931, "goldSpent": 3525, "holdPings": 0, "individualPosition": "UTILITY", "inhibitorKills": 0, "inhibitorTakedowns": 0, "inhibitorsLost": 0, "item0": 0, "item1": 2055, "item2": 3855, "item3": 1033, "item4": 3023, "item5": 3158, "item6": 3364, "itemsPurchased": 18, "killingSprees": 0, "kills": 0, "lane": "NONE", "largestCriticalStrike": 0, "largestKillingSpree": 0, "largestMultiKill": 0, "longestTimeSpentLiving": 328, "magicDamageDealt": 4209, "magicDamageDealtToChampions": 1780, "magicDamageTaken": 1017, "needVisionPings": 0, "neutralMinionsKilled": 0, "nexusKills": 0, "nexusLost": 0, "nexusTakedowns": 0, "objectivesStolen": 0, "objectivesStolenAssists": 0, "onMyWayPings": 0, "participantId": 10, "pentaKills": 0, "perks": {"statPerks": {"defense": 5002, "flex": 5002, "offense": 5008}, "styles": [{"description": "primaryStyle", "selections": [{"perk": 8439, "var1": 178, "var2": 229, "var3": 0}, {"perk": 8463, "var1": 266, "var2": 0, "var3": 0}, {"perk": 8473, "var1": 167, "var2": 0, "var3": 0}, {"perk": 8242, "var1": 26, "var2": 0, "var3": 0}], "style": 8400}, {"description": "subStyle", "selections": [{"perk": 8345, "var1": 3, "var2": 0, "var3": 0}, {"perk": 8347, "var1": 0, "var2": 0, "var3": 0}], "style": 8300}]}, "physicalDamageDealt": 3022, "physicalDamageDealtToChampions": 299, "physicalDamageTaken": 4867, "placement": 0, "playerAugment1": 0, "playerAugment2": 0, "playerAugment3": 0, "playerAugment4": 0, "playerSubteamId": 0, "profileIcon": 5414, "pushPings": 0, "puuid": "X1wZJHtl_sUADq9Md8Eoip-TDb8RFiJjX0O5ZzHSQPI5mnMFRBuO46bK36aS2QG-XqDZ4bo_vD8j4A", "quadraKills": 0, "riotIdName": "", "riotIdTagline": "", "role": "SUPPORT", "sightWardsBoughtInGame": 0, "spell1Casts": 15, "spell2Casts": 10, "spell3Casts": 8, "spell4Casts": 2, "subteamPlacement": 0, "summoner1Casts": 2, "summoner1Id": 14, "summoner2Casts": 2, "summoner2Id": 4, "summonerId": "sFJWPc13somuGDGITVkIjCooICxEY6_J67geilMZlqSFtbR51xniiRAzCA", "summonerLevel": 62, "summonerName": "\uc21c\ucc9c\uae08\ub2f9\uaddc\uc0c1\ud0b9", "teamEarlySurrendered": false, "teamId": 200, "teamPosition": "UTILITY", "timeCCingOthers": 13, "timePlayed": 912, "totalAllyJungleMinionsKilled": 0, "totalDamageDealt": 11604, "totalDamageDealtToChampions": 2252, "totalDamageShieldedOnTeammates": 93, "totalDamageTaken": 6087, "totalEnemyJungleMinionsKilled": 0, "totalHeal": 329, "totalHealsOnTeammates": 138, "totalMinionsKilled": 26, "totalTimeCCDealt": 40, "totalTimeSpentDead": 59, "totalUnitsHealed": 2, "tripleKills": 0, "trueDamageDealt": 4372, "trueDamageDealtToChampions": 172, "trueDamageTaken": 202, "turretKills": 0, "turretTakedowns": 0, "turretsLost": 0, "unrealKills": 0, "visionClearedPings": 0, "visionScore": 26, "visionWardsBoughtInGame": 7, "wardsKilled": 2, "wardsPlaced": 11, "win": true}], "platformId": "KR", "queueId": 420, "teams": [{"bans": [{"championId": 238, "pickTurn": 1}, {"championId": 78, "pickTurn": 2}, {"championId": 154, "pickTurn": 3}, {"championId": 76, "pickTurn": 4}, {"championId": 950, "pickTurn": 5}], "objectives": {"baron": {"first": false, "kills": 0}, "champion": {"first": false, "kills": 8}, "dragon": {"first": false, "kills": 0}, "inhibitor": {"first": false, "kills": 0}, "riftHerald": {"first": false, "kills": 0}, "tower": {"first": false, "kills": 0}}, "teamId": 100, "win": false}, {"bans": [{"championId": 12, "pickTurn": 6}, {"championId": 119, "pickTurn": 7}, {"championId": 76, "pickTurn": 8}, {"championId": 78, "pickTurn": 9}, {"championId": 58, "pickTurn": 10}], "objectives": {"baron": {"first": false, "kills": 0}, "champion": {"first": true, "kills": 15}, "dragon": {"first": true, "kills": 2}, "inhibitor": {"first": false, "kills": 0}, "riftHerald": {"first": true, "kills": 1}, "tower": {"first": true, "kills": 3}}, "teamId": 200, "win": true}], "tournamentCode": ""}}